Workbook

Sheet Старт
A1: Курс на зачёт
A2: Бег 1 км, челночный 10×10 м, подтягивания. Параллельно уходит живот и растут мышцы.
A4: Как пользоваться
A5: 1. Лист «Расчёт» | B5: Впиши свой точный вес, талию и шею в жёлтые ячейки. Калории, белок и ориентир по жиру в теле пересчитаются сами.
A6: 2. Лист «План» | B6: 16 недель по дням. Первые 2 недели можно ежедневно, дальше 2 сессии в неделю. Отмечай «✔» в столбце «Сделано». Каждая 4-я неделя контрольная.
A7: 3. Лист «Темпы» | B7: Целевые времена отрезков для интервалов (200–800 м) по неделям.
A8: 4. Лист «Дневник» | B8: Заноси результаты и самочувствие. Справа внизу графики с плановой траекторией.
A9: 5. Листы «Меню», «Рецепты», «Покупки» | B9: Меню на неделю с граммами на тебя и на жену. Граммы сами подгоняются под твою норму калорий. Список покупок считается из меню.
A10: 6. Лист «Экипировка» | B10: Что купить, как выбирать и бюджет.
A11: 7. Лист «Техника» | B11: Как делать упражнения правильно и какие ошибки типичны.
A12: 8. Лист «Разбор плана» | B12: Что было не так в исходной таблице и что изменено.
A14: Цели из твоей таблицы | B14: 1 км — 4:30 (сейчас 5:10), подтягивания — 15 (сейчас 3), 10×10 м — 25 с (сейчас 28).
A15: Реалистичный прогноз | B15: За 12 недель: 1 км около 4:39, челночный около 26,2 с, подтягиваний 9–10. К 16-й неделе: 4:30 и 25,6 с. До 15 подтягиваний при весе 90 кг нужно 5–6 месяцев вместе с похудением.
A16: Важно про колени | B16: Хруст без боли допустим. Глубокие приседания («лягушка») и прыжки отложены. Боль, отёк, блокировка сустава означают стоп и визит к врачу. Перед стартом проверь давление и сердце у терапевта.
A17: Жёлтые ячейки | B17: Ячейки с жёлтым фоном — твои данные. Остальное считается формулами.

Sheet Расчёт
A1: Расчёт калорий и белка
A2: Жёлтые ячейки можно менять
A3: Возраст, лет | B3: 40
A4: Рост, см | B4: 176
A5: Вес, кг | B5: 90 | C5: Взвесься утром натощак. 90 кг — примерная цифра.
A6: Талия, см (на уровне пупка) | B6: 100 | C6: Измерь стоя, на выдохе. 100 — примерная цифра.
A7: Шея, см | B7: 39
A8: Коэффициент активности | B8: 1.45 | C8: 1,375 мало; 1,45 две тренировки и ходьба; 1,55 почти ежедневно
A9: Дефицит калорий, доля | B9: 0.2 | C9: 0,15–0,25. 20% даёт около −0,5 кг в неделю
A10: Порция жены от твоей, доля | B10: 0.8 | C10: Для списка покупок и граммовок
A11: Дата старта | B11: 46303 | C11: Если начнёшь в другой день, поменяй
A12: Бюджет на экипировку, ₽ (разово) | B12: 20000
A13: Бюджет на еду, ₽ (в месяц, на двоих) | B13: 20000 | C13: Поправь под себя
A14: Результаты
A15: Обмен покоя, ккал | B15: =10*B5+6.25*B4-5*B3+5 | C15: Формула Миффлина–Сан Жеора
A16: Расход с тренировками, ккал | B16: =B15*B8
A17: Норма на день, ккал | B17: =ROUND(B16*(1-B9),-1) | C17: Калорийность меню подгоняется под неё
A18: Белок, г | B18: =ROUND(B5*1.7,0) | C18: 1,7 г на кг: хватает и для мышц, и для сытости
A19: Жиры, г | B19: =ROUND(B5*0.8,0)
A20: Углеводы, г | B20: =ROUND((B17-B18*4-B19*9)/4,0) | C20: Остаток калорий
A21: Индекс массы тела | B21: =B5/(B4/100)^2
A22: Жир в теле, % (оценка по талии и шее) | B22: =495/(1.0324-0.19077*LOG10(B6-B7)+0.15456*LOG10(B4))-450 | C22: Метод ВМС США. Точность ±3–4 п.п.
A23: Безжировая масса, кг | B23: =B5*(1-B22/100)
A24: Вес при жире 20%, кг | B24: =B23/(1-0.2)
A25: Вес при жире 15%, кг | B25: =B23/(1-0.15) | C25: Первая цель: живот почти исчезает
A26: Вес при жире 12%, кг | B26: =B23/(1-0.12) | C26: Кубики видны при 12–14%
A27: Недель до 15% при −0,5 кг/нед | B27: =MAX(0,ROUND((B5-B25)/0.5,0))
A29: Если ты похудеешь на 5–7 кг за 12 недель, пересчитай всё снова с новым весом.

Sheet План
A1: План на 16 недель
A2: Недели 1–2 можно ежедневно. Недели 3–16: сессия А, сессия Б и пятиминутка каждый день. Недели 4, 8, 12, 16 контрольные.
A4: Нед. | B4: Дата | C4: День | D4: Фаза | E4: Тип | F4: Тренировка | G4: Подробности | H4: Сделано | I4: Заметки | K4: Выполнено сессий
A5: 1 | B5: ='Расчёт'!$B$11+0 | C5: =TEXT(B5,"ddd") | D5: Старт (ежедневно) | E5: бег | F5: Бег-ходьба + подтягивания в течение дня | G5: РАЗМИНКА 8–10 МИН • Ходьба и очень лёгкий бег 4–5 минут • Круги: плечи, таз, колени, голеностоп по 10 • Выпады с поворотом и махи ногами по 8 • 3 ускорения по 40 м, без усилия ОСНОВНОЕ • Бег и ходьба 20 мин: 2 мин бег / 2 мин ходьба по кругу • Подтягивания: 5×2, в разное время дня, не до отказа ЗАМИНКА 5–8 МИН • Ходьба 3–5 минут, пока пульс не успокоится • Растяжка по 30 секунд: икры, бёдра, ягодицы, грудь | K5: =COUNTIFS(H5:H116,"✔",E5:E116,"<>отдых",E5:E116,"<>по желанию")
A6: 1 | B6: ='Расчёт'!$B$11+1 | C6: =TEXT(B6,"ddd") | D6: Старт (ежедневно) | E6: сила | F6: Сила: верх тела и кор | G6: РАЗМИНКА 8–10 МИН • Ходьба и очень лёгкий бег 4–5 минут • Круги: плечи, таз, колени, голеностоп по 10 • Выпады с поворотом и махи ногами по 8 • 3 ускорения по 40 м, без усилия ПОДТЯГИВАНИЯ • 4×2 строгих повторов, отдых 2 минуты (не до отказа) • Негативные: 3×4 с опусканием 4–5 секунд (если максимум 8+, делай подтягивания с паузой 2 с вверху) • Австралийские подтягивания: 3×8–12 ОТЖИМАНИЯ • 3 подхода по (максимум − 2), руки на скамье если меньше 8 КОР (КУБИКИ) • Планка 3×35 с • Подъём коленей/ног в висе 3×6–10 • Мёртвый жук 3×8 на сторону ЗАМИНКА 5–8 МИН • Ходьба 3–5 минут, пока пульс не успокоится • Растяжка по 30 секунд: икры, бёдра, ягодицы, грудь
A7: 1 | B7: ='Расчёт'!$B$11+2 | C7: =TEXT(B7,"ddd") | D7: Старт (ежедневно) | E7: отдых | F7: Активное восстановление | G7: ЧТО ДЕЛАТЬ • Быстрая ходьба 40 минут • Мобильность таза и голеностопа 10 минут • Лёгкая растяжка
A8: 1 | B8: ='Расчёт'!$B$11+3 | C8: =TEXT(B8,"ddd") | D8: Старт (ежедневно) | E8: челнок | F8: Челночный (техника) + ноги без прыжков | G8: РАЗМИНКА 8–10 МИН • Ходьба и очень лёгкий бег 4–5 минут • Круги: плечи, таз, колени, голеностоп по 10 • Выпады с поворотом и махи ногами по 8 • 3 ускорения по 40 м, без усилия ЧЕЛНОЧНЫЙ БЕГ • Техника разворота на 5 м: 6 раз в 70% скорости • 3×10×10 м на 80–85% скорости, цель недели 27.9 с • Отдых между попытками 3 минуты, ходьба НОГИ И ЯГОДИЦЫ (КОЛЕНИ БЕРЕГУ) • Присед до скамьи 3×10, с w≥5 с рюкзаком • Подъём на скамью 3×8 на ногу • Румынская тяга с рюкзаком 3×10–12 • Ягодичный мостик 3×15 • Подъём на носки 3×15–20 ЗАМИНКА 5–8 МИН • Ходьба 3–5 минут, пока пульс не успокоится • Растяжка по 30 секунд: икры, бёдра, ягодицы, грудь
A9: 1 | B9: ='Расчёт'!$B$11+4 | C9: =TEXT(B9,"ddd") | D9: Старт (ежедневно) | E9: бег | F9: Интервалы + подтягивания | G9: РАЗМИНКА 8–10 МИН • Ходьба и очень лёгкий бег 4–5 минут • Круги: плечи, таз, колени, голеностоп по 10 • Выпады с поворотом и махи ногами по 8 • 3 ускорения по 40 м, без усилия ИНТЕРВАЛЫ: 5×200 М • Каждый отрезок за 0:58 (примерно) • Отдых между отрезками: 2 мин, ходьба • Цель недели по темпу 1 км: 5:08 • Если не получается держать время, уменьши число повторов, а не темп ПОДТЯГИВАНИЯ (БЫСТРО) • Лестница: 1-2-1-2-1-2 с отдыхом 90 секунд • Негативные 2×3 ЗАМИНКА 5–8 МИН • Ходьба 3–5 минут, пока пульс не успокоится • Растяжка по 30 секунд: икры, бёдра, ягодицы, грудь
A10: 1 | B10: ='Расчёт'!$B$11+5 | C10: =TEXT(B10,"ddd") | D10: Старт (ежедневно) | E10: сила | F10: Сила: ноги, спина, кор | G10: РАЗМИНКА 8–10 МИН • Ходьба и очень лёгкий бег 4–5 минут • Круги: плечи, таз, колени, голеностоп по 10 • Выпады с поворотом и махи ногами по 8 • 3 ускорения по 40 м, без усилия НОГИ И ЯГОДИЦЫ (КОЛЕНИ БЕРЕГУ) • Присед до скамьи 3×10, с w≥5 с рюкзаком • Подъём на скамью 3×8 на ногу • Румынская тяга с рюкзаком 3×10–12 • Ягодичный мостик 3×15 • Подъём на носки 3×15–20 АВСТРАЛИЙСКИЕ ПОДТЯГИВАНИЯ • 3×8–12 КОР (КУБИКИ) • Планка 3×35 с • Подъём коленей/ног в висе 3×6–10 • Мёртвый жук 3×8 на сторону ЗАМИНКА 5–8 МИН • Ходьба 3–5 минут, пока пульс не успокоится • Растяжка по 30 секунд: икры, бёдра, ягодицы, грудь
A11: 1 | B11: ='Расчёт'!$B$11+6 | C11: =TEXT(B11,"ddd") | D11: Старт (ежедневно) | E11: отдых | F11: Отдых | G11: ЧТО ДЕЛАТЬ • Прогулка 30–40 минут • Подготовь еду на следующую неделю
A12: 2 | B12: ='Расчёт'!$B$11+7 | C12: =TEXT(B12,"ddd") | D12: Старт (ежедневно) | E12: бег | F12: Бег-ходьба + подтягивания в течение дня | G12: РАЗМИНКА 8–10 МИН • Ходьба и очень лёгкий бег 4–5 минут • Круги: плечи, таз, колени, голеностоп по 10 • Выпады с поворотом и махи ногами по 8 • 3 ускорения по 40 м, без усилия ОСНОВНОЕ • Бег и ходьба 25 мин: 2 мин бег / 2 мин ходьба по кругу • Подтягивания: 5×2, в разное время дня, не до отказа ЗАМИНКА 5–8 МИН • Ходьба 3–5 минут, пока пульс не успокоится • Растяжка по 30 секунд: икры, бёдра, ягодицы, грудь
A13: 2 | B13: ='Расчёт'!$B$11+8 | C13: =TEXT(B13,"ddd") | D13: Старт (ежедневно) | E13: сила | F13: Сила: верх тела и кор | G13: РАЗМИНКА 8–10 МИН • Ходьба и очень лёгкий бег 4–5 минут • Круги: плечи, таз, колени, голеностоп по 10 • Выпады с поворотом и махи ногами по 8 • 3 ускорения по 40 м, без усилия ПОДТЯГИВАНИЯ • 5×2 строгих повторов, отдых 2 минуты (не до отказа) • Негативные: 3×4 с опусканием 4–5 секунд (если максимум 8+, делай подтягивания с паузой 2 с вверху) • Австралийские подтягивания: 3×8–12 ОТЖИМАНИЯ • 3 подхода по (максимум − 2), руки на скамье если меньше 8 КОР (КУБИКИ) • Планка 3×40 с • Подъём коленей/ног в висе 3×6–10 • Мёртвый жук 3×8 на сторону ЗАМИНКА 5–8 МИН • Ходьба 3–5 минут, пока пульс не успокоится • Растяжка по 30 секунд: икры, бёдра, ягодицы, грудь
A14: 2 | B14: ='Расчёт'!$B$11+9 | C14: =TEXT(B14,"ddd") | D14: Старт (ежедневно) | E14: отдых | F14: Активное восстановление | G14: ЧТО ДЕЛАТЬ • Быстрая ходьба 40 минут • Мобильность таза и голеностопа 10 минут • Лёгкая растяжка
A15: 2 | B15: ='Расчёт'!$B$11+10 | C15: =TEXT(B15,"ddd") | D15: Старт (ежедневно) | E15: челнок | F15: Челночный (техника) + ноги без прыжков | G15: РАЗМИНКА 8–10 МИН • Ходьба и очень лёгкий бег 4–5 минут • Круги: плечи, таз, колени, голеностоп по 10 • Выпады с поворотом и махи ногами по 8 • 3 ускорения по 40 м, без усилия ЧЕЛНОЧНЫЙ БЕГ • Техника разворота на 5 м: 6 раз в 70% скорости • 4×10×10 м на 80–85% скорости, цель недели 27.8 с • Отдых между попытками 3 минуты, ходьба НОГИ И ЯГОДИЦЫ (КОЛЕНИ БЕРЕГУ) • Присед до скамьи 3×10, с w≥5 с рюкзаком • Подъём на скамью 3×8 на ногу • Румынская тяга с рюкзаком 3×10–12 • Ягодичный мостик 3×15 • Подъём на носки 3×15–20 ЗАМИНКА 5–8 МИН • Ходьба 3–5 минут, пока пульс не успокоится • Растяжка по 30 секунд: икры, бёдра, ягодицы, грудь
A16: 2 | B16: ='Расчёт'!$B$11+11 | C16: =TEXT(B16,"ddd") | D16: Старт (ежедневно) | E16: бег | F16: Интервалы + подтягивания | G16: РАЗМИНКА 8–10 МИН • Ходьба и очень лёгкий бег 4–5 минут • Круги: плечи, таз, колени, голеностоп по 10 • Выпады с поворотом и махи ногами по 8 • 3 ускорения по 40 м, без усилия ИНТЕРВАЛЫ: 6×200 М • Каждый отрезок за 0:57 (примерно) • Отдых между отрезками: 90 с, ходьба • Цель недели по темпу 1 км: 5:05 • Если не получается держать время, уменьши число повторов, а не темп ПОДТЯГИВАНИЯ (БЫСТРО) • Лестница: 1-2-1-2-1-2 с отдыхом 90 секунд • Негативные 2×3 ЗАМИНКА 5–8 МИН • Ходьба 3–5 минут, пока пульс не успокоится • Растяжка по 30 секунд: икры, бёдра, ягодицы, грудь
A17: 2 | B17: ='Расчёт'!$B$11+12 | C17: =TEXT(B17,"ddd") | D17: Старт (ежедневно) | E17: сила | F17: Сила: ноги, спина, кор | G17: РАЗМИНКА 8–10 МИН • Ходьба и очень лёгкий бег 4–5 минут • Круги: плечи, таз, колени, голеностоп по 10 • Выпады с поворотом и махи ногами по 8 • 3 ускорения по 40 м, без усилия НОГИ И ЯГОДИЦЫ (КОЛЕНИ БЕРЕГУ) • Присед до скамьи 3×10, с w≥5 с рюкзаком • Подъём на скамью 3×8 на ногу • Румынская тяга с рюкзаком 3×10–12 • Ягодичный мостик 3×15 • Подъём на носки 3×15–20 АВСТРАЛИЙСКИЕ ПОДТЯГИВАНИЯ • 3×8–12 КОР (КУБИКИ) • Планка 3×40 с • Подъём коленей/ног в висе 3×6–10 • Мёртвый жук 3×8 на сторону ЗАМИНКА 5–8 МИН • Ходьба 3–5 минут, пока пульс не успокоится • Растяжка по 30 секунд: икры, бёдра, ягодицы, грудь
A18: 2 | B18: ='Расчёт'!$B$11+13 | C18: =TEXT(B18,"ddd") | D18: Старт (ежедневно) | E18: отдых | F18: Отдых | G18: ЧТО ДЕЛАТЬ • Прогулка 30–40 минут • Подготовь еду на следующую неделю
A19: 3 | B19: ='Расчёт'!$B$11+14 | C19: =TEXT(B19,"ddd") | D19: База | E19: бег | F19: Сессия А: интервальный бег + подтягивания + кор | G19: РАЗМИНКА 8–10 МИН • Ходьба и очень лёгкий бег 4–5 минут • Круги: плечи, таз, колени, голеностоп по 10 • Выпады с поворотом и махи ногами по 8 • 3 ускорения по 40 м, без усилия ИНТЕРВАЛЫ: 6×200 М • Каждый отрезок за 0:57 (примерно) • Отдых между отрезками: 90 с, ходьба • Цель недели по темпу 1 км: 5:02 • Если не получается держать время, уменьши число повторов, а не темп ПОДТЯГИВАНИЯ • 5×3 строгих повторов, отдых 2 минуты (не до отказа) • Негативные: 3×4 с опусканием 4–5 секунд (если максимум 8+, делай подтягивания с паузой 2 с вверху) • Австралийские подтягивания: 3×8–12 КОР (КУБИКИ) • Планка 3×45 с • Подъём коленей/ног в висе 3×6–10 • Мёртвый жук 3×8 на сторону ЗАМИНКА 5–8 МИН • Ходьба 3–5 минут, пока пульс не успокоится • Растяжка по 30 секунд: икры, бёдра, ягодицы, грудь КАЖДЫЙ ДЕНЬ, 5 МИНУТ (НЕ ОТДЕЛЬНАЯ ТРЕНИРОВКА) • Подтягивания 2 раза, 2–3 подхода в разное время дня, не до утомления • Ходьба: цель 8–10 тысяч шагов • Вода 2–2,5 литра и сон 7–8 часов
A20: 3 | B20: ='Расчёт'!$B$11+15 | C20: =TEXT(B20,"ddd") | D20: База | E20: отдых | F20: Лёгкий день | G20: КАЖДЫЙ ДЕНЬ, 5 МИНУТ (НЕ ОТДЕЛЬНАЯ ТРЕНИРОВКА) • Подтягивания 2 раза, 2–3 подхода в разное время дня, не до утомления • Ходьба: цель 8–10 тысяч шагов • Вода 2–2,5 литра и сон 7–8 часов
A21: 3 | B21: ='Расчёт'!$B$11+16 | C21: =TEXT(B21,"ddd") | D21: База | E21: отдых | F21: Лёгкий день | G21: КАЖДЫЙ ДЕНЬ, 5 МИНУТ (НЕ ОТДЕЛЬНАЯ ТРЕНИРОВКА) • Подтягивания 2 раза, 2–3 подхода в разное время дня, не до утомления • Ходьба: цель 8–10 тысяч шагов • Вода 2–2,5 литра и сон 7–8 часов
A22: 3 | B22: ='Расчёт'!$B$11+17 | C22: =TEXT(B22,"ddd") | D22: База | E22: челнок | F22: Сессия Б: челночный + ноги + подтягивания | G22: РАЗМИНКА 8–10 МИН • Ходьба и очень лёгкий бег 4–5 минут • Круги: плечи, таз, колени, голеностоп по 10 • Выпады с поворотом и махи ногами по 8 • 3 ускорения по 40 м, без усилия ЧЕЛНОЧНЫЙ БЕГ • Техника разворота на 5 м: 6 раз • 4×10×10 м, из них 2 быстрых (цель 27.6 с), отдых 3 минуты, ходьба • Остальные на 85% скорости НОГИ И ЯГОДИЦЫ (КОЛЕНИ БЕРЕГУ) • Присед до скамьи 3×10, с w≥5 с рюкзаком • Подъём на скамью 3×8 на ногу • Румынская тяга с рюкзаком 3×10–12 • Ягодичный мостик 3×15 • Подъём на носки 3×15–20 ПОДТЯГИВАНИЯ: ЛЕСТНИЦЫ • 3 лестницы 1-2-…-2 с отдыхом 2 минуты ОТЖИМАНИЯ И КОР • Отжимания 3×(максимум − 2) • Скручивания 3×15 ЗАМИНКА 5–8 МИН • Ходьба 3–5 минут, пока пульс не успокоится • Растяжка по 30 секунд: икры, бёдра, ягодицы, грудь КАЖДЫЙ ДЕНЬ, 5 МИНУТ (НЕ ОТДЕЛЬНАЯ ТРЕНИРОВКА) • Подтягивания 2 раза, 2–3 подхода в разное время дня, не до утомления • Ходьба: цель 8–10 тысяч шагов • Вода 2–2,5 литра и сон 7–8 часов
A23: 3 | B23: ='Расчёт'!$B$11+18 | C23: =TEXT(B23,"ddd") | D23: База | E23: отдых | F23: Лёгкий день | G23: КАЖДЫЙ ДЕНЬ, 5 МИНУТ (НЕ ОТДЕЛЬНАЯ ТРЕНИРОВКА) • Подтягивания 2 раза, 2–3 подхода в разное время дня, не до утомления • Ходьба: цель 8–10 тысяч шагов • Вода 2–2,5 литра и сон 7–8 часов
A24: 3 | B24: ='Расчёт'!$B$11+19 | C24: =TEXT(B24,"ddd") | D24: База | E24: по желанию | F24: Необязательно: лёгкий бег | G24: ЧТО ДЕЛАТЬ • Лёгкий бег 25 мин (разговорный темп), при необходимости с ходьбой по 1 мин каждые 5 • Если колени болят, замени на ходьбу 40 минут
A25: 3 | B25: ='Расчёт'!$B$11+20 | C25: =TEXT(B25,"ddd") | D25: База | E25: отдых | F25: Отдых | G25: ЧТО ДЕЛАТЬ • Прогулка 30 минут • Подготовь еду на неделю
A26: 4 | B26: ='Расчёт'!$B$11+21 | C26: =TEXT(B26,"ddd") | D26: Контроль | E26: контроль | F26: Контроль: 1 км | G26: РАЗМИНКА 8–10 МИН • Ходьба и очень лёгкий бег 4–5 минут • Круги: плечи, таз, колени, голеностоп по 10 • Выпады с поворотом и махи ногами по 8 • 3 ускорения по 40 м, без усилия ТЕСТ • Один забег на 1 км на максимум. Равномерный темп, финиш с ускорением. • Запиши время в дневник. ЗАМИНКА 5–8 МИН • Ходьба 3–5 минут, пока пульс не успокоится • Растяжка по 30 секунд: икры, бёдра, ягодицы, грудь
A27: 4 | B27: ='Расчёт'!$B$11+22 | C27: =TEXT(B27,"ddd") | D27: Контроль | E27: контроль | F27: Контроль: подтягивания | G27: РАЗМИНКА 8–10 МИН • Ходьба и очень лёгкий бег 4–5 минут • Круги: плечи, таз, колени, голеностоп по 10 • Выпады с поворотом и махи ногами по 8 • 3 ускорения по 40 м, без усилия ТЕСТ • Один подход максимума, строго: руки выпрямлены внизу, подбородок над перекладиной. • Затем лёгкая сила: отжимания 2×(максимум − 4), планка 2×40 с ЗАМИНКА 5–8 МИН • Ходьба 3–5 минут, пока пульс не успокоится • Растяжка по 30 секунд: икры, бёдра, ягодицы, грудь
A28: 4 | B28: ='Расчёт'!$B$11+23 | C28: =TEXT(B28,"ddd") | D28: Контроль | E28: отдых | F28: Восстановление | G28: ЧТО ДЕЛАТЬ • Быстрая ходьба 40 минут • Мобильность и растяжка
A29: 4 | B29: ='Расчёт'!$B$11+24 | C29: =TEXT(B29,"ddd") | D29: Контроль | E29: контроль | F29: Контроль: челночный 10×10 | G29: РАЗМИНКА 8–10 МИН • Ходьба и очень лёгкий бег 4–5 минут • Круги: плечи, таз, колени, голеностоп по 10 • Выпады с поворотом и махи ногами по 8 • 3 ускорения по 40 м, без усилия ТЕСТ • 3 попытки по 10×10 м, отдых 4 минуты, лучшая идёт в дневник. • Следи за правилом касания линии. ЗАМИНКА 5–8 МИН • Ходьба 3–5 минут, пока пульс не успокоится • Растяжка по 30 секунд: икры, бёдра, ягодицы, грудь
A30: 4 | B30: ='Расчёт'!$B$11+25 | C30: =TEXT(B30,"ddd") | D30: Контроль | E30: отдых | F30: Отдых | G30: ЧТО ДЕЛАТЬ • Отдых, сон 7–8 часов
A31: 4 | B31: ='Расчёт'!$B$11+26 | C31: =TEXT(B31,"ddd") | D31: Контроль | E31: по желанию | F31: Необязательно: лёгкая прогулка-бег | G31: ЧТО ДЕЛАТЬ • Ходьба 40 минут или лёгкий бег 20 минут
A32: 4 | B32: ='Расчёт'!$B$11+27 | C32: =TEXT(B32,"ddd") | D32: Контроль | E32: отдых | F32: Отдых | G32: ЧТО ДЕЛАТЬ • Отдых • Подведи итоги теста в дневнике
A33: 5 | B33: ='Расчёт'!$B$11+28 | C33: =TEXT(B33,"ddd") | D33: Развитие | E33: бег | F33: Сессия А: интервальный бег + подтягивания + кор | G33: РАЗМИНКА 8–10 МИН • Ходьба и очень лёгкий бег 4–5 минут • Круги: плечи, таз, колени, голеностоп по 10 • Выпады с поворотом и махи ногами по 8 • 3 ускорения по 40 м, без усилия ИНТЕРВАЛЫ: 5×300 М • Каждый отрезок за 1:26 (примерно) • Отдых между отрезками: 2 мин, ходьба • Цель недели по темпу 1 км: 4:57 • Если не получается держать время, уменьши число повторов, а не темп ПОДТЯГИВАНИЯ • 4×3 строгих повторов, отдых 2 минуты (не до отказа) • Негативные: 3×4 с опусканием 4–5 секунд (если максимум 8+, делай подтягивания с паузой 2 с вверху) • Австралийские подтягивания: 3×8–12 КОР (КУБИКИ) • Планка 3×55 с • Подъём коленей/ног в висе 3×6–10 • Мёртвый жук 3×8 на сторону ЗАМИНКА 5–8 МИН • Ходьба 3–5 минут, пока пульс не успокоится • Растяжка по 30 секунд: икры, бёдра, ягодицы, грудь КАЖДЫЙ ДЕНЬ, 5 МИНУТ (НЕ ОТДЕЛЬНАЯ ТРЕНИРОВКА) • Подтягивания 2 раза, 2–3 подхода в разное время дня, не до утомления • Ходьба: цель 8–10 тысяч шагов • Вода 2–2,5 литра и сон 7–8 часов
A34: 5 | B34: ='Расчёт'!$B$11+29 | C34: =TEXT(B34,"ddd") | D34: Развитие | E34: отдых | F34: Лёгкий день | G34: КАЖДЫЙ ДЕНЬ, 5 МИНУТ (НЕ ОТДЕЛЬНАЯ ТРЕНИРОВКА) • Подтягивания 2 раза, 2–3 подхода в разное время дня, не до утомления • Ходьба: цель 8–10 тысяч шагов • Вода 2–2,5 литра и сон 7–8 часов
A35: 5 | B35: ='Расчёт'!$B$11+30 | C35: =TEXT(B35,"ddd") | D35: Развитие | E35: отдых | F35: Лёгкий день | G35: КАЖДЫЙ ДЕНЬ, 5 МИНУТ (НЕ ОТДЕЛЬНАЯ ТРЕНИРОВКА) • Подтягивания 2 раза, 2–3 подхода в разное время дня, не до утомления • Ходьба: цель 8–10 тысяч шагов • Вода 2–2,5 литра и сон 7–8 часов
A36: 5 | B36: ='Расчёт'!$B$11+31 | C36: =TEXT(B36,"ddd") | D36: Развитие | E36: челнок | F36: Сессия Б: челночный + ноги + подтягивания | G36: РАЗМИНКА 8–10 МИН • Ходьба и очень лёгкий бег 4–5 минут • Круги: плечи, таз, колени, голеностоп по 10 • Выпады с поворотом и махи ногами по 8 • 3 ускорения по 40 м, без усилия ЧЕЛНОЧНЫЙ БЕГ • Техника разворота на 5 м: 6 раз • 5×10×10 м, из них 2 быстрых (цель 27.3 с), отдых 3 минуты, ходьба • Остальные на 85% скорости НОГИ И ЯГОДИЦЫ (КОЛЕНИ БЕРЕГУ) • Присед до скамьи 4×12, с w≥5 с рюкзаком • Подъём на скамью 3×8 на ногу • Румынская тяга с рюкзаком 3×10–12 • Ягодичный мостик 3×15 • Подъём на носки 3×15–20 ПОДТЯГИВАНИЯ: ЛЕСТНИЦЫ • 3 лестницы 1-2-…-2 с отдыхом 2 минуты ОТЖИМАНИЯ И КОР • Отжимания 3×(максимум − 2) • Скручивания 3×15 ЗАМИНКА 5–8 МИН • Ходьба 3–5 минут, пока пульс не успокоится • Растяжка по 30 секунд: икры, бёдра, ягодицы, грудь КАЖДЫЙ ДЕНЬ, 5 МИНУТ (НЕ ОТДЕЛЬНАЯ ТРЕНИРОВКА) • Подтягивания 2 раза, 2–3 подхода в разное время дня, не до утомления • Ходьба: цель 8–10 тысяч шагов • Вода 2–2,5 литра и сон 7–8 часов
A37: 5 | B37: ='Расчёт'!$B$11+32 | C37: =TEXT(B37,"ddd") | D37: Развитие | E37: отдых | F37: Лёгкий день | G37: КАЖДЫЙ ДЕНЬ, 5 МИНУТ (НЕ ОТДЕЛЬНАЯ ТРЕНИРОВКА) • Подтягивания 2 раза, 2–3 подхода в разное время дня, не до утомления • Ходьба: цель 8–10 тысяч шагов • Вода 2–2,5 литра и сон 7–8 часов
A38: 5 | B38: ='Расчёт'!$B$11+33 | C38: =TEXT(B38,"ddd") | D38: Развитие | E38: по желанию | F38: Необязательно: лёгкий бег | G38: ЧТО ДЕЛАТЬ • Лёгкий бег 30 мин (разговорный темп), при необходимости с ходьбой по 1 мин каждые 5 • Если колени болят, замени на ходьбу 40 минут
A39: 5 | B39: ='Расчёт'!$B$11+34 | C39: =TEXT(B39,"ddd") | D39: Развитие | E39: отдых | F39: Отдых | G39: ЧТО ДЕЛАТЬ • Прогулка 30 минут • Подготовь еду на неделю
A40: 6 | B40: ='Расчёт'!$B$11+35 | C40: =TEXT(B40,"ddd") | D40: Развитие | E40: бег | F40: Сессия А: интервальный бег + подтягивания + кор | G40: РАЗМИНКА 8–10 МИН • Ходьба и очень лёгкий бег 4–5 минут • Круги: плечи, таз, колени, голеностоп по 10 • Выпады с поворотом и махи ногами по 8 • 3 ускорения по 40 м, без усилия ИНТЕРВАЛЫ: 4×400 М • Каждый отрезок за 1:54 (примерно) • Отдых между отрезками: 2:30, ходьба • Цель недели по темпу 1 км: 4:54 • Если не получается держать время, уменьши число повторов, а не темп ПОДТЯГИВАНИЯ • 5×4 строгих повторов, отдых 2 минуты (не до отказа) • Негативные: 3×4 с опусканием 4–5 секунд (если максимум 8+, делай подтягивания с паузой 2 с вверху) • Австралийские подтягивания: 3×8–12 КОР (КУБИКИ) • Планка 3×60 с • Подъём коленей/ног в висе 3×6–10 • Мёртвый жук 3×8 на сторону ЗАМИНКА 5–8 МИН • Ходьба 3–5 минут, пока пульс не успокоится • Растяжка по 30 секунд: икры, бёдра, ягодицы, грудь КАЖДЫЙ ДЕНЬ, 5 МИНУТ (НЕ ОТДЕЛЬНАЯ ТРЕНИРОВКА) • Подтягивания 2 раза, 2–3 подхода в разное время дня, не до утомления • Ходьба: цель 8–10 тысяч шагов • Вода 2–2,5 литра и сон 7–8 часов
A41: 6 | B41: ='Расчёт'!$B$11+36 | C41: =TEXT(B41,"ddd") | D41: Развитие | E41: отдых | F41: Лёгкий день | G41: КАЖДЫЙ ДЕНЬ, 5 МИНУТ (НЕ ОТДЕЛЬНАЯ ТРЕНИРОВКА) • Подтягивания 2 раза, 2–3 подхода в разное время дня, не до утомления • Ходьба: цель 8–10 тысяч шагов • Вода 2–2,5 литра и сон 7–8 часов
A42: 6 | B42: ='Расчёт'!$B$11+37 | C42: =TEXT(B42,"ddd") | D42: Развитие | E42: отдых | F42: Лёгкий день | G42: КАЖДЫЙ ДЕНЬ, 5 МИНУТ (НЕ ОТДЕЛЬНАЯ ТРЕНИРОВКА) • Подтягивания 2 раза, 2–3 подхода в разное время дня, не до утомления • Ходьба: цель 8–10 тысяч шагов • Вода 2–2,5 литра и сон 7–8 часов
A43: 6 | B43: ='Расчёт'!$B$11+38 | C43: =TEXT(B43,"ddd") | D43: Развитие | E43: челнок | F43: Сессия Б: челночный + ноги + подтягивания | G43: РАЗМИНКА 8–10 МИН • Ходьба и очень лёгкий бег 4–5 минут • Круги: плечи, таз, колени, голеностоп по 10 • Выпады с поворотом и махи ногами по 8 • 3 ускорения по 40 м, без усилия ЧЕЛНОЧНЫЙ БЕГ • Техника разворота на 5 м: 6 раз • 5×10×10 м, из них 2 быстрых (цель 27.1 с), отдых 3 минуты, ходьба • Остальные на 85% скорости НОГИ И ЯГОДИЦЫ (КОЛЕНИ БЕРЕГУ) • Присед до скамьи 4×12, с w≥5 с рюкзаком • Подъём на скамью 3×8 на ногу • Румынская тяга с рюкзаком 3×10–12 • Ягодичный мостик 3×15 • Подъём на носки 3×15–20 ПОДТЯГИВАНИЯ: ЛЕСТНИЦЫ • 3 лестницы 1-2-…-2 с отдыхом 2 минуты ОТЖИМАНИЯ И КОР • Отжимания 3×(максимум − 2) • Скручивания 3×15 ЗАМИНКА 5–8 МИН • Ходьба 3–5 минут, пока пульс не успокоится • Растяжка по 30 секунд: икры, бёдра, ягодицы, грудь КАЖДЫЙ ДЕНЬ, 5 МИНУТ (НЕ ОТДЕЛЬНАЯ ТРЕНИРОВКА) • Подтягивания 2 раза, 2–3 подхода в разное время дня, не до утомления • Ходьба: цель 8–10 тысяч шагов • Вода 2–2,5 литра и сон 7–8 часов
A44: 6 | B44: ='Расчёт'!$B$11+39 | C44: =TEXT(B44,"ddd") | D44: Развитие | E44: отдых | F44: Лёгкий день | G44: КАЖДЫЙ ДЕНЬ, 5 МИНУТ (НЕ ОТДЕЛЬНАЯ ТРЕНИРОВКА) • Подтягивания 2 раза, 2–3 подхода в разное время дня, не до утомления • Ходьба: цель 8–10 тысяч шагов • Вода 2–2,5 литра и сон 7–8 часов
A45: 6 | B45: ='Расчёт'!$B$11+40 | C45: =TEXT(B45,"ddd") | D45: Развитие | E45: по желанию | F45: Необязательно: лёгкий бег | G45: ЧТО ДЕЛАТЬ • Лёгкий бег 30 мин (разговорный темп), при необходимости с ходьбой по 1 мин каждые 5 • Если колени болят, замени на ходьбу 40 минут
A46: 6 | B46: ='Расчёт'!$B$11+41 | C46: =TEXT(B46,"ddd") | D46: Развитие | E46: отдых | F46: Отдых | G46: ЧТО ДЕЛАТЬ • Прогулка 30 минут • Подготовь еду на неделю
A47: 7 | B47: ='Расчёт'!$B$11+42 | C47: =TEXT(B47,"ddd") | D47: Развитие | E47: бег | F47: Сессия А: интервальный бег + подтягивания + кор | G47: РАЗМИНКА 8–10 МИН • Ходьба и очень лёгкий бег 4–5 минут • Круги: плечи, таз, колени, голеностоп по 10 • Выпады с поворотом и махи ногами по 8 • 3 ускорения по 40 м, без усилия ИНТЕРВАЛЫ: 6×300 М • Каждый отрезок за 1:24 (примерно) • Отдых между отрезками: 90 с, ходьба • Цель недели по темпу 1 км: 4:52 • Если не получается держать время, уменьши число повторов, а не темп ПОДТЯГИВАНИЯ • 5×4 строгих повторов, отдых 2 минуты (не до отказа) • Негативные: 3×4 с опусканием 4–5 секунд (если максимум 8+, делай подтягивания с паузой 2 с вверху) • Австралийские подтягивания: 3×8–12 КОР (КУБИКИ) • Планка 3×65 с • Подъём коленей/ног в висе 3×6–10 • Мёртвый жук 3×8 на сторону ЗАМИНКА 5–8 МИН • Ходьба 3–5 минут, пока пульс не успокоится • Растяжка по 30 секунд: икры, бёдра, ягодицы, грудь КАЖДЫЙ ДЕНЬ, 5 МИНУТ (НЕ ОТДЕЛЬНАЯ ТРЕНИРОВКА) • Подтягивания 2 раза, 2–3 подхода в разное время дня, не до утомления • Ходьба: цель 8–10 тысяч шагов • Вода 2–2,5 литра и сон 7–8 часов
A48: 7 | B48: ='Расчёт'!$B$11+43 | C48: =TEXT(B48,"ddd") | D48: Развитие | E48: отдых | F48: Лёгкий день | G48: КАЖДЫЙ ДЕНЬ, 5 МИНУТ (НЕ ОТДЕЛЬНАЯ ТРЕНИРОВКА) • Подтягивания 2 раза, 2–3 подхода в разное время дня, не до утомления • Ходьба: цель 8–10 тысяч шагов • Вода 2–2,5 литра и сон 7–8 часов
A49: 7 | B49: ='Расчёт'!$B$11+44 | C49: =TEXT(B49,"ddd") | D49: Развитие | E49: отдых | F49: Лёгкий день | G49: КАЖДЫЙ ДЕНЬ, 5 МИНУТ (НЕ ОТДЕЛЬНАЯ ТРЕНИРОВКА) • Подтягивания 2 раза, 2–3 подхода в разное время дня, не до утомления • Ходьба: цель 8–10 тысяч шагов • Вода 2–2,5 литра и сон 7–8 часов
A50: 7 | B50: ='Расчёт'!$B$11+45 | C50: =TEXT(B50,"ddd") | D50: Развитие | E50: челнок | F50: Сессия Б: челночный + ноги + подтягивания | G50: РАЗМИНКА 8–10 МИН • Ходьба и очень лёгкий бег 4–5 минут • Круги: плечи, таз, колени, голеностоп по 10 • Выпады с поворотом и махи ногами по 8 • 3 ускорения по 40 м, без усилия ЧЕЛНОЧНЫЙ БЕГ • Техника разворота на 5 м: 6 раз • 6×10×10 м, из них 3 быстрых (цель 27.0 с), отдых 3 минуты, ходьба • Остальные на 85% скорости НОГИ И ЯГОДИЦЫ (КОЛЕНИ БЕРЕГУ) • Присед до скамьи 4×12, с w≥5 с рюкзаком • Подъём на скамью 3×8 на ногу • Румынская тяга с рюкзаком 3×10–12 • Ягодичный мостик 3×15 • Подъём на носки 3×15–20 ПОДТЯГИВАНИЯ: ЛЕСТНИЦЫ • 3 лестницы 1-2-…-2 с отдыхом 2 минуты ОТЖИМАНИЯ И КОР • Отжимания 3×(максимум − 2) • Скручивания 3×15 ЗАМИНКА 5–8 МИН • Ходьба 3–5 минут, пока пульс не успокоится • Растяжка по 30 секунд: икры, бёдра, ягодицы, грудь КАЖДЫЙ ДЕНЬ, 5 МИНУТ (НЕ ОТДЕЛЬНАЯ ТРЕНИРОВКА) • Подтягивания 2 раза, 2–3 подхода в разное время дня, не до утомления • Ходьба: цель 8–10 тысяч шагов • Вода 2–2,5 литра и сон 7–8 часов
A51: 7 | B51: ='Расчёт'!$B$11+46 | C51: =TEXT(B51,"ddd") | D51: Развитие | E51: отдых | F51: Лёгкий день | G51: КАЖДЫЙ ДЕНЬ, 5 МИНУТ (НЕ ОТДЕЛЬНАЯ ТРЕНИРОВКА) • Подтягивания 2 раза, 2–3 подхода в разное время дня, не до утомления • Ходьба: цель 8–10 тысяч шагов • Вода 2–2,5 литра и сон 7–8 часов
A52: 7 | B52: ='Расчёт'!$B$11+47 | C52: =TEXT(B52,"ddd") | D52: Развитие | E52: по желанию | F52: Необязательно: лёгкий бег | G52: ЧТО ДЕЛАТЬ • Лёгкий бег 35 мин в разговорном темпе • Если колени болят, замени на ходьбу 40 минут
A53: 7 | B53: ='Расчёт'!$B$11+48 | C53: =TEXT(B53,"ddd") | D53: Развитие | E53: отдых | F53: Отдых | G53: ЧТО ДЕЛАТЬ • Прогулка 30 минут • Подготовь еду на неделю
A54: 8 | B54: ='Расчёт'!$B$11+49 | C54: =TEXT(B54,"ddd") | D54: Контроль | E54: контроль | F54: Контроль: 1 км | G54: РАЗМИНКА 8–10 МИН • Ходьба и очень лёгкий бег 4–5 минут • Круги: плечи, таз, колени, голеностоп по 10 • Выпады с поворотом и махи ногами по 8 • 3 ускорения по 40 м, без усилия ТЕСТ • Один забег на 1 км на максимум. Равномерный темп, финиш с ускорением. • Запиши время в дневник. ЗАМИНКА 5–8 МИН • Ходьба 3–5 минут, пока пульс не успокоится • Растяжка по 30 секунд: икры, бёдра, ягодицы, грудь
A55: 8 | B55: ='Расчёт'!$B$11+50 | C55: =TEXT(B55,"ddd") | D55: Контроль | E55: контроль | F55: Контроль: подтягивания | G55: РАЗМИНКА 8–10 МИН • Ходьба и очень лёгкий бег 4–5 минут • Круги: плечи, таз, колени, голеностоп по 10 • Выпады с поворотом и махи ногами по 8 • 3 ускорения по 40 м, без усилия ТЕСТ • Один подход максимума, строго: руки выпрямлены внизу, подбородок над перекладиной. • Затем лёгкая сила: отжимания 2×(максимум − 4), планка 2×40 с ЗАМИНКА 5–8 МИН • Ходьба 3–5 минут, пока пульс не успокоится • Растяжка по 30 секунд: икры, бёдра, ягодицы, грудь
A56: 8 | B56: ='Расчёт'!$B$11+51 | C56: =TEXT(B56,"ddd") | D56: Контроль | E56: отдых | F56: Восстановление | G56: ЧТО ДЕЛАТЬ • Быстрая ходьба 40 минут • Мобильность и растяжка
A57: 8 | B57: ='Расчёт'!$B$11+52 | C57: =TEXT(B57,"ddd") | D57: Контроль | E57: контроль | F57: Контроль: челночный 10×10 | G57: РАЗМИНКА 8–10 МИН • Ходьба и очень лёгкий бег 4–5 минут • Круги: плечи, таз, колени, голеностоп по 10 • Выпады с поворотом и махи ногами по 8 • 3 ускорения по 40 м, без усилия ТЕСТ • 3 попытки по 10×10 м, отдых 4 минуты, лучшая идёт в дневник. • Следи за правилом касания линии. ЗАМИНКА 5–8 МИН • Ходьба 3–5 минут, пока пульс не успокоится • Растяжка по 30 секунд: икры, бёдра, ягодицы, грудь
A58: 8 | B58: ='Расчёт'!$B$11+53 | C58: =TEXT(B58,"ddd") | D58: Контроль | E58: отдых | F58: Отдых | G58: ЧТО ДЕЛАТЬ • Отдых, сон 7–8 часов
A59: 8 | B59: ='Расчёт'!$B$11+54 | C59: =TEXT(B59,"ddd") | D59: Контроль | E59: по желанию | F59: Необязательно: лёгкая прогулка-бег | G59: ЧТО ДЕЛАТЬ • Ходьба 40 минут или лёгкий бег 20 минут
A60: 8 | B60: ='Расчёт'!$B$11+55 | C60: =TEXT(B60,"ddd") | D60: Контроль | E60: отдых | F60: Отдых | G60: ЧТО ДЕЛАТЬ • Отдых • Подведи итоги теста в дневнике
A61: 9 | B61: ='Расчёт'!$B$11+56 | C61: =TEXT(B61,"ddd") | D61: Пик | E61: бег | F61: Сессия А: интервальный бег + подтягивания + кор | G61: РАЗМИНКА 8–10 МИН • Ходьба и очень лёгкий бег 4–5 минут • Круги: плечи, таз, колени, голеностоп по 10 • Выпады с поворотом и махи ногами по 8 • 3 ускорения по 40 м, без усилия ИНТЕРВАЛЫ: 5×400 М • Каждый отрезок за 1:51 (примерно) • Отдых между отрезками: 2 мин, ходьба • Цель недели по темпу 1 км: 4:46 • Если не получается держать время, уменьши число повторов, а не темп ПОДТЯГИВАНИЯ • 5×4 строгих повторов, отдых 2 минуты (не до отказа) • Негативные: 3×4 с опусканием 4–5 секунд (если максимум 8+, делай подтягивания с паузой 2 с вверху) • Австралийские подтягивания: 3×8–12 КОР (КУБИКИ) • Планка 3×75 с • Подъём коленей/ног в висе 3×6–10 • Мёртвый жук 3×8 на сторону ЗАМИНКА 5–8 МИН • Ходьба 3–5 минут, пока пульс не успокоится • Растяжка по 30 секунд: икры, бёдра, ягодицы, грудь КАЖДЫЙ ДЕНЬ, 5 МИНУТ (НЕ ОТДЕЛЬНАЯ ТРЕНИРОВКА) • Подтягивания 3 раза, 2–3 подхода в разное время дня, не до утомления • Ходьба: цель 8–10 тысяч шагов • Вода 2–2,5 литра и сон 7–8 часов
A62: 9 | B62: ='Расчёт'!$B$11+57 | C62: =TEXT(B62,"ddd") | D62: Пик | E62: отдых | F62: Лёгкий день | G62: КАЖДЫЙ ДЕНЬ, 5 МИНУТ (НЕ ОТДЕЛЬНАЯ ТРЕНИРОВКА) • Подтягивания 3 раза, 2–3 подхода в разное время дня, не до утомления • Ходьба: цель 8–10 тысяч шагов • Вода 2–2,5 литра и сон 7–8 часов
A63: 9 | B63: ='Расчёт'!$B$11+58 | C63: =TEXT(B63,"ddd") | D63: Пик | E63: отдых | F63: Лёгкий день | G63: КАЖДЫЙ ДЕНЬ, 5 МИНУТ (НЕ ОТДЕЛЬНАЯ ТРЕНИРОВКА) • Подтягивания 3 раза, 2–3 подхода в разное время дня, не до утомления • Ходьба: цель 8–10 тысяч шагов • Вода 2–2,5 литра и сон 7–8 часов
A64: 9 | B64: ='Расчёт'!$B$11+59 | C64: =TEXT(B64,"ddd") | D64: Пик | E64: челнок | F64: Сессия Б: челночный + ноги + подтягивания | G64: РАЗМИНКА 8–10 МИН • Ходьба и очень лёгкий бег 4–5 минут • Круги: плечи, таз, колени, голеностоп по 10 • Выпады с поворотом и махи ногами по 8 • 3 ускорения по 40 м, без усилия ЧЕЛНОЧНЫЙ БЕГ • Техника разворота на 5 м: 6 раз • 5×10×10 м, из них 2 быстрых (цель 26.6 с), отдых 3 минуты, ходьба • Остальные на 85% скорости НОГИ И ЯГОДИЦЫ (КОЛЕНИ БЕРЕГУ) • Присед до скамьи 4×12, с w≥5 с рюкзаком • Подъём на скамью 3×8 на ногу • Румынская тяга с рюкзаком 3×10–12 • Ягодичный мостик 3×15 • Подъём на носки 3×15–20 ПОДТЯГИВАНИЯ: ЛЕСТНИЦЫ • 4 лестницы 1-2-…-3 с отдыхом 2 минуты ОТЖИМАНИЯ И КОР • Отжимания 3×(максимум − 2) • Скручивания 3×15 ЗАМИНКА 5–8 МИН • Ходьба 3–5 минут, пока пульс не успокоится • Растяжка по 30 секунд: икры, бёдра, ягодицы, грудь КАЖДЫЙ ДЕНЬ, 5 МИНУТ (НЕ ОТДЕЛЬНАЯ ТРЕНИРОВКА) • Подтягивания 3 раза, 2–3 подхода в разное время дня, не до утомления • Ходьба: цель 8–10 тысяч шагов • Вода 2–2,5 литра и сон 7–8 часов
A65: 9 | B65: ='Расчёт'!$B$11+60 | C65: =TEXT(B65,"ddd") | D65: Пик | E65: отдых | F65: Лёгкий день | G65: КАЖДЫЙ ДЕНЬ, 5 МИНУТ (НЕ ОТДЕЛЬНАЯ ТРЕНИРОВКА) • Подтягивания 3 раза, 2–3 подхода в разное время дня, не до утомления • Ходьба: цель 8–10 тысяч шагов • Вода 2–2,5 литра и сон 7–8 часов
A66: 9 | B66: ='Расчёт'!$B$11+61 | C66: =TEXT(B66,"ddd") | D66: Пик | E66: по желанию | F66: Необязательно: лёгкий бег | G66: ЧТО ДЕЛАТЬ • Лёгкий бег 35 мин в разговорном темпе • Если колени болят, замени на ходьбу 40 минут
A67: 9 | B67: ='Расчёт'!$B$11+62 | C67: =TEXT(B67,"ddd") | D67: Пик | E67: отдых | F67: Отдых | G67: ЧТО ДЕЛАТЬ • Прогулка 30 минут • Подготовь еду на неделю
A68: 10 | B68: ='Расчёт'!$B$11+63 | C68: =TEXT(B68,"ddd") | D68: Пик | E68: бег | F68: Сессия А: интервальный бег + подтягивания + кор | G68: РАЗМИНКА 8–10 МИН • Ходьба и очень лёгкий бег 4–5 минут • Круги: плечи, таз, колени, голеностоп по 10 • Выпады с поворотом и махи ногами по 8 • 3 ускорения по 40 м, без усилия ИНТЕРВАЛЫ: 4×600 М • Каждый отрезок за 2:49 (примерно) • Отдых между отрезками: 2:30, ходьба • Цель недели по темпу 1 км: 4:44 • Если не получается держать время, уменьши число повторов, а не темп ПОДТЯГИВАНИЯ • 6×5 строгих повторов, отдых 2 минуты (не до отказа) • Негативные: 3×4 с опусканием 4–5 секунд (если максимум 8+, делай подтягивания с паузой 2 с вверху) • Австралийские подтягивания: 3×8–12 КОР (КУБИКИ) • Планка 3×80 с • Подъём коленей/ног в висе 3×6–10 • Мёртвый жук 3×8 на сторону ЗАМИНКА 5–8 МИН • Ходьба 3–5 минут, пока пульс не успокоится • Растяжка по 30 секунд: икры, бёдра, ягодицы, грудь КАЖДЫЙ ДЕНЬ, 5 МИНУТ (НЕ ОТДЕЛЬНАЯ ТРЕНИРОВКА) • Подтягивания 3 раза, 2–3 подхода в разное время дня, не до утомления • Ходьба: цель 8–10 тысяч шагов • Вода 2–2,5 литра и сон 7–8 часов
A69: 10 | B69: ='Расчёт'!$B$11+64 | C69: =TEXT(B69,"ddd") | D69: Пик | E69: отдых | F69: Лёгкий день | G69: КАЖДЫЙ ДЕНЬ, 5 МИНУТ (НЕ ОТДЕЛЬНАЯ ТРЕНИРОВКА) • Подтягивания 3 раза, 2–3 подхода в разное время дня, не до утомления • Ходьба: цель 8–10 тысяч шагов • Вода 2–2,5 литра и сон 7–8 часов
A70: 10 | B70: ='Расчёт'!$B$11+65 | C70: =TEXT(B70,"ddd") | D70: Пик | E70: отдых | F70: Лёгкий день | G70: КАЖДЫЙ ДЕНЬ, 5 МИНУТ (НЕ ОТДЕЛЬНАЯ ТРЕНИРОВКА) • Подтягивания 3 раза, 2–3 подхода в разное время дня, не до утомления • Ходьба: цель 8–10 тысяч шагов • Вода 2–2,5 литра и сон 7–8 часов
A71: 10 | B71: ='Расчёт'!$B$11+66 | C71: =TEXT(B71,"ddd") | D71: Пик | E71: челнок | F71: Сессия Б: челночный + ноги + подтягивания | G71: РАЗМИНКА 8–10 МИН • Ходьба и очень лёгкий бег 4–5 минут • Круги: плечи, таз, колени, голеностоп по 10 • Выпады с поворотом и махи ногами по 8 • 3 ускорения по 40 м, без усилия ЧЕЛНОЧНЫЙ БЕГ • Техника разворота на 5 м: 6 раз • 6×10×10 м, из них 3 быстрых (цель 26.5 с), отдых 3 минуты, ходьба • Остальные на 85% скорости НОГИ И ЯГОДИЦЫ (КОЛЕНИ БЕРЕГУ) • Присед до скамьи 4×12, с w≥5 с рюкзаком • Подъём на скамью 3×8 на ногу • Румынская тяга с рюкзаком 3×10–12 • Ягодичный мостик 3×15 • Подъём на носки 3×15–20 ПОДТЯГИВАНИЯ: ЛЕСТНИЦЫ • 4 лестницы 1-2-…-3 с отдыхом 2 минуты ОТЖИМАНИЯ И КОР • Отжимания 3×(максимум − 2) • Скручивания 3×15 ЗАМИНКА 5–8 МИН • Ходьба 3–5 минут, пока пульс не успокоится • Растяжка по 30 секунд: икры, бёдра, ягодицы, грудь КАЖДЫЙ ДЕНЬ, 5 МИНУТ (НЕ ОТДЕЛЬНАЯ ТРЕНИРОВКА) • Подтягивания 3 раза, 2–3 подхода в разное время дня, не до утомления • Ходьба: цель 8–10 тысяч шагов • Вода 2–2,5 литра и сон 7–8 часов
A72: 10 | B72: ='Расчёт'!$B$11+67 | C72: =TEXT(B72,"ddd") | D72: Пик | E72: отдых | F72: Лёгкий день | G72: КАЖДЫЙ ДЕНЬ, 5 МИНУТ (НЕ ОТДЕЛЬНАЯ ТРЕНИРОВКА) • Подтягивания 3 раза, 2–3 подхода в разное время дня, не до утомления • Ходьба: цель 8–10 тысяч шагов • Вода 2–2,5 литра и сон 7–8 часов
A73: 10 | B73: ='Расчёт'!$B$11+68 | C73: =TEXT(B73,"ddd") | D73: Пик | E73: по желанию | F73: Необязательно: лёгкий бег | G73: ЧТО ДЕЛАТЬ • Лёгкий бег 35 мин в разговорном темпе • Если колени болят, замени на ходьбу 40 минут
A74: 10 | B74: ='Расчёт'!$B$11+69 | C74: =TEXT(B74,"ddd") | D74: Пик | E74: отдых | F74: Отдых | G74: ЧТО ДЕЛАТЬ • Прогулка 30 минут • Подготовь еду на неделю
A75: 11 | B75: ='Расчёт'!$B$11+70 | C75: =TEXT(B75,"ddd") | D75: Пик | E75: бег | F75: Сессия А: интервальный бег + подтягивания + кор | G75: РАЗМИНКА 8–10 МИН • Ходьба и очень лёгкий бег 4–5 минут • Круги: плечи, таз, колени, голеностоп по 10 • Выпады с поворотом и махи ногами по 8 • 3 ускорения по 40 м, без усилия ИНТЕРВАЛЫ: 3×800 М • Каждый отрезок за 3:45 (примерно) • Отдых между отрезками: 3 мин, ходьба • Цель недели по темпу 1 км: 4:42 • Если не получается держать время, уменьши число повторов, а не темп ПОДТЯГИВАНИЯ • 6×6 строгих повторов, отдых 2 минуты (не до отказа) • Негативные: 3×4 с опусканием 4–5 секунд (если максимум 8+, делай подтягивания с паузой 2 с вверху) • Австралийские подтягивания: 3×8–12 КОР (КУБИКИ) • Планка 3×85 с • Подъём коленей/ног в висе 3×6–10 • Мёртвый жук 3×8 на сторону ЗАМИНКА 5–8 МИН • Ходьба 3–5 минут, пока пульс не успокоится • Растяжка по 30 секунд: икры, бёдра, ягодицы, грудь КАЖДЫЙ ДЕНЬ, 5 МИНУТ (НЕ ОТДЕЛЬНАЯ ТРЕНИРОВКА) • Подтягивания 3 раза, 2–3 подхода в разное время дня, не до утомления • Ходьба: цель 8–10 тысяч шагов • Вода 2–2,5 литра и сон 7–8 часов
A76: 11 | B76: ='Расчёт'!$B$11+71 | C76: =TEXT(B76,"ddd") | D76: Пик | E76: отдых | F76: Лёгкий день | G76: КАЖДЫЙ ДЕНЬ, 5 МИНУТ (НЕ ОТДЕЛЬНАЯ ТРЕНИРОВКА) • Подтягивания 3 раза, 2–3 подхода в разное время дня, не до утомления • Ходьба: цель 8–10 тысяч шагов • Вода 2–2,5 литра и сон 7–8 часов
A77: 11 | B77: ='Расчёт'!$B$11+72 | C77: =TEXT(B77,"ddd") | D77: Пик | E77: отдых | F77: Лёгкий день | G77: КАЖДЫЙ ДЕНЬ, 5 МИНУТ (НЕ ОТДЕЛЬНАЯ ТРЕНИРОВКА) • Подтягивания 3 раза, 2–3 подхода в разное время дня, не до утомления • Ходьба: цель 8–10 тысяч шагов • Вода 2–2,5 литра и сон 7–8 часов
A78: 11 | B78: ='Расчёт'!$B$11+73 | C78: =TEXT(B78,"ddd") | D78: Пик | E78: челнок | F78: Сессия Б: челночный + ноги + подтягивания | G78: РАЗМИНКА 8–10 МИН • Ходьба и очень лёгкий бег 4–5 минут • Круги: плечи, таз, колени, голеностоп по 10 • Выпады с поворотом и махи ногами по 8 • 3 ускорения по 40 м, без усилия ЧЕЛНОЧНЫЙ БЕГ • Техника разворота на 5 м: 6 раз • 4×10×10 м, из них 2 быстрых (цель 26.4 с), отдых 3 минуты, ходьба • Остальные на 85% скорости НОГИ И ЯГОДИЦЫ (КОЛЕНИ БЕРЕГУ) • Присед до скамьи 4×12, с w≥5 с рюкзаком • Подъём на скамью 3×8 на ногу • Румынская тяга с рюкзаком 3×10–12 • Ягодичный мостик 3×15 • Подъём на носки 3×15–20 ПОДТЯГИВАНИЯ: ЛЕСТНИЦЫ • 4 лестницы 1-2-…-3 с отдыхом 2 минуты ОТЖИМАНИЯ И КОР • Отжимания 3×(максимум − 2) • Скручивания 3×15 ЗАМИНКА 5–8 МИН • Ходьба 3–5 минут, пока пульс не успокоится • Растяжка по 30 секунд: икры, бёдра, ягодицы, грудь КАЖДЫЙ ДЕНЬ, 5 МИНУТ (НЕ ОТДЕЛЬНАЯ ТРЕНИРОВКА) • Подтягивания 3 раза, 2–3 подхода в разное время дня, не до утомления • Ходьба: цель 8–10 тысяч шагов • Вода 2–2,5 литра и сон 7–8 часов
A79: 11 | B79: ='Расчёт'!$B$11+74 | C79: =TEXT(B79,"ddd") | D79: Пик | E79: отдых | F79: Лёгкий день | G79: КАЖДЫЙ ДЕНЬ, 5 МИНУТ (НЕ ОТДЕЛЬНАЯ ТРЕНИРОВКА) • Подтягивания 3 раза, 2–3 подхода в разное время дня, не до утомления • Ходьба: цель 8–10 тысяч шагов • Вода 2–2,5 литра и сон 7–8 часов
A80: 11 | B80: ='Расчёт'!$B$11+75 | C80: =TEXT(B80,"ddd") | D80: Пик | E80: по желанию | F80: Необязательно: лёгкий бег | G80: ЧТО ДЕЛАТЬ • Лёгкий бег 40 мин в разговорном темпе • Если колени болят, замени на ходьбу 40 минут
A81: 11 | B81: ='Расчёт'!$B$11+76 | C81: =TEXT(B81,"ddd") | D81: Пик | E81: отдых | F81: Отдых | G81: ЧТО ДЕЛАТЬ • Прогулка 30 минут • Подготовь еду на неделю
A82: 12 | B82: ='Расчёт'!$B$11+77 | C82: =TEXT(B82,"ddd") | D82: Контроль | E82: контроль | F82: Контроль: 1 км | G82: РАЗМИНКА 8–10 МИН • Ходьба и очень лёгкий бег 4–5 минут • Круги: плечи, таз, колени, голеностоп по 10 • Выпады с поворотом и махи ногами по 8 • 3 ускорения по 40 м, без усилия ТЕСТ • Один забег на 1 км на максимум. Равномерный темп, финиш с ускорением. • Запиши время в дневник. ЗАМИНКА 5–8 МИН • Ходьба 3–5 минут, пока пульс не успокоится • Растяжка по 30 секунд: икры, бёдра, ягодицы, грудь
A83: 12 | B83: ='Расчёт'!$B$11+78 | C83: =TEXT(B83,"ddd") | D83: Контроль | E83: контроль | F83: Контроль: подтягивания | G83: РАЗМИНКА 8–10 МИН • Ходьба и очень лёгкий бег 4–5 минут • Круги: плечи, таз, колени, голеностоп по 10 • Выпады с поворотом и махи ногами по 8 • 3 ускорения по 40 м, без усилия ТЕСТ • Один подход максимума, строго: руки выпрямлены внизу, подбородок над перекладиной. • Затем лёгкая сила: отжимания 2×(максимум − 4), планка 2×40 с ЗАМИНКА 5–8 МИН • Ходьба 3–5 минут, пока пульс не успокоится • Растяжка по 30 секунд: икры, бёдра, ягодицы, грудь
A84: 12 | B84: ='Расчёт'!$B$11+79 | C84: =TEXT(B84,"ddd") | D84: Контроль | E84: отдых | F84: Восстановление | G84: ЧТО ДЕЛАТЬ • Быстрая ходьба 40 минут • Мобильность и растяжка
A85: 12 | B85: ='Расчёт'!$B$11+80 | C85: =TEXT(B85,"ddd") | D85: Контроль | E85: контроль | F85: Контроль: челночный 10×10 | G85: РАЗМИНКА 8–10 МИН • Ходьба и очень лёгкий бег 4–5 минут • Круги: плечи, таз, колени, голеностоп по 10 • Выпады с поворотом и махи ногами по 8 • 3 ускорения по 40 м, без усилия ТЕСТ • 3 попытки по 10×10 м, отдых 4 минуты, лучшая идёт в дневник. • Следи за правилом касания линии. ЗАМИНКА 5–8 МИН • Ходьба 3–5 минут, пока пульс не успокоится • Растяжка по 30 секунд: икры, бёдра, ягодицы, грудь
A86: 12 | B86: ='Расчёт'!$B$11+81 | C86: =TEXT(B86,"ddd") | D86: Контроль | E86: отдых | F86: Отдых | G86: ЧТО ДЕЛАТЬ • Отдых, сон 7–8 часов
A87: 12 | B87: ='Расчёт'!$B$11+82 | C87: =TEXT(B87,"ddd") | D87: Контроль | E87: по желанию | F87: Необязательно: лёгкая прогулка-бег | G87: ЧТО ДЕЛАТЬ • Ходьба 40 минут или лёгкий бег 20 минут
A88: 12 | B88: ='Расчёт'!$B$11+83 | C88: =TEXT(B88,"ddd") | D88: Контроль | E88: отдых | F88: Отдых | G88: ЧТО ДЕЛАТЬ • Отдых • Подведи итоги теста в дневнике
A89: 13 | B89: ='Расчёт'!$B$11+84 | C89: =TEXT(B89,"ddd") | D89: Продление | E89: бег | F89: Сессия А: интервальный бег + подтягивания + кор | G89: РАЗМИНКА 8–10 МИН • Ходьба и очень лёгкий бег 4–5 минут • Круги: плечи, таз, колени, голеностоп по 10 • Выпады с поворотом и махи ногами по 8 • 3 ускорения по 40 м, без усилия ИНТЕРВАЛЫ: 6×400 М • Каждый отрезок за 1:47 (примерно) • Отдых между отрезками: 90 с, ходьба • Цель недели по темпу 1 км: 4:37 • Если не получается держать время, уменьши число повторов, а не темп ПОДТЯГИВАНИЯ • 5×5 строгих повторов, отдых 2 минуты (не до отказа) • Негативные: 3×4 с опусканием 4–5 секунд (если максимум 8+, делай подтягивания с паузой 2 с вверху) • Австралийские подтягивания: 3×8–12 КОР (КУБИКИ) • Планка 3×90 с • Подъём коленей/ног в висе 3×6–10 • Мёртвый жук 3×8 на сторону ЗАМИНКА 5–8 МИН • Ходьба 3–5 минут, пока пульс не успокоится • Растяжка по 30 секунд: икры, бёдра, ягодицы, грудь КАЖДЫЙ ДЕНЬ, 5 МИНУТ (НЕ ОТДЕЛЬНАЯ ТРЕНИРОВКА) • Подтягивания 4 раза, 2–3 подхода в разное время дня, не до утомления • Ходьба: цель 8–10 тысяч шагов • Вода 2–2,5 литра и сон 7–8 часов
A90: 13 | B90: ='Расчёт'!$B$11+85 | C90: =TEXT(B90,"ddd") | D90: Продление | E90: отдых | F90: Лёгкий день | G90: КАЖДЫЙ ДЕНЬ, 5 МИНУТ (НЕ ОТДЕЛЬНАЯ ТРЕНИРОВКА) • Подтягивания 4 раза, 2–3 подхода в разное время дня, не до утомления • Ходьба: цель 8–10 тысяч шагов • Вода 2–2,5 литра и сон 7–8 часов
A91: 13 | B91: ='Расчёт'!$B$11+86 | C91: =TEXT(B91,"ddd") | D91: Продление | E91: отдых | F91: Лёгкий день | G91: КАЖДЫЙ ДЕНЬ, 5 МИНУТ (НЕ ОТДЕЛЬНАЯ ТРЕНИРОВКА) • Подтягивания 4 раза, 2–3 подхода в разное время дня, не до утомления • Ходьба: цель 8–10 тысяч шагов • Вода 2–2,5 литра и сон 7–8 часов
A92: 13 | B92: ='Расчёт'!$B$11+87 | C92: =TEXT(B92,"ddd") | D92: Продление | E92: челнок | F92: Сессия Б: челночный + ноги + подтягивания | G92: РАЗМИНКА 8–10 МИН • Ходьба и очень лёгкий бег 4–5 минут • Круги: плечи, таз, колени, голеностоп по 10 • Выпады с поворотом и махи ногами по 8 • 3 ускорения по 40 м, без усилия ЧЕЛНОЧНЫЙ БЕГ • Техника разворота на 5 м: 6 раз • 5×10×10 м, из них 2 быстрых (цель 26.1 с), отдых 3 минуты, ходьба • Остальные на 85% скорости НОГИ И ЯГОДИЦЫ (КОЛЕНИ БЕРЕГУ) • Присед до скамьи 4×12, с w≥5 с рюкзаком • Подъём на скамью 3×8 на ногу • Румынская тяга с рюкзаком 3×10–12 • Ягодичный мостик 3×15 • Подъём на носки 3×15–20 ПОДТЯГИВАНИЯ: ЛЕСТНИЦЫ • 4 лестницы 1-2-…-4 с отдыхом 2 минуты ОТЖИМАНИЯ И КОР • Отжимания 3×(максимум − 2) • Скручивания 3×15 ЗАМИНКА 5–8 МИН • Ходьба 3–5 минут, пока пульс не успокоится • Растяжка по 30 секунд: икры, бёдра, ягодицы, грудь КАЖДЫЙ ДЕНЬ, 5 МИНУТ (НЕ ОТДЕЛЬНАЯ ТРЕНИРОВКА) • Подтягивания 4 раза, 2–3 подхода в разное время дня, не до утомления • Ходьба: цель 8–10 тысяч шагов • Вода 2–2,5 литра и сон 7–8 часов
A93: 13 | B93: ='Расчёт'!$B$11+88 | C93: =TEXT(B93,"ddd") | D93: Продление | E93: отдых | F93: Лёгкий день | G93: КАЖДЫЙ ДЕНЬ, 5 МИНУТ (НЕ ОТДЕЛЬНАЯ ТРЕНИРОВКА) • Подтягивания 4 раза, 2–3 подхода в разное время дня, не до утомления • Ходьба: цель 8–10 тысяч шагов • Вода 2–2,5 литра и сон 7–8 часов
A94: 13 | B94: ='Расчёт'!$B$11+89 | C94: =TEXT(B94,"ddd") | D94: Продление | E94: по желанию | F94: Необязательно: лёгкий бег | G94: ЧТО ДЕЛАТЬ • Лёгкий бег 40 мин в разговорном темпе • Если колени болят, замени на ходьбу 40 минут
A95: 13 | B95: ='Расчёт'!$B$11+90 | C95: =TEXT(B95,"ddd") | D95: Продление | E95: отдых | F95: Отдых | G95: ЧТО ДЕЛАТЬ • Прогулка 30 минут • Подготовь еду на неделю
A96: 14 | B96: ='Расчёт'!$B$11+91 | C96: =TEXT(B96,"ddd") | D96: Продление | E96: бег | F96: Сессия А: интервальный бег + подтягивания + кор | G96: РАЗМИНКА 8–10 МИН • Ходьба и очень лёгкий бег 4–5 минут • Круги: плечи, таз, колени, голеностоп по 10 • Выпады с поворотом и махи ногами по 8 • 3 ускорения по 40 м, без усилия ИНТЕРВАЛЫ: 4×600 М • Каждый отрезок за 2:43 (примерно) • Отдых между отрезками: 2 мин, ходьба • Цель недели по темпу 1 км: 4:34 • Если не получается держать время, уменьши число повторов, а не темп ПОДТЯГИВАНИЯ • 6×6 строгих повторов, отдых 2 минуты (не до отказа) • Негативные: 3×4 с опусканием 4–5 секунд (если максимум 8+, делай подтягивания с паузой 2 с вверху) • Австралийские подтягивания: 3×8–12 КОР (КУБИКИ) • Планка 3×90 с • Подъём коленей/ног в висе 3×6–10 • Мёртвый жук 3×8 на сторону ЗАМИНКА 5–8 МИН • Ходьба 3–5 минут, пока пульс не успокоится • Растяжка по 30 секунд: икры, бёдра, ягодицы, грудь КАЖДЫЙ ДЕНЬ, 5 МИНУТ (НЕ ОТДЕЛЬНАЯ ТРЕНИРОВКА) • Подтягивания 4 раза, 2–3 подхода в разное время дня, не до утомления • Ходьба: цель 8–10 тысяч шагов • Вода 2–2,5 литра и сон 7–8 часов
A97: 14 | B97: ='Расчёт'!$B$11+92 | C97: =TEXT(B97,"ddd") | D97: Продление | E97: отдых | F97: Лёгкий день | G97: КАЖДЫЙ ДЕНЬ, 5 МИНУТ (НЕ ОТДЕЛЬНАЯ ТРЕНИРОВКА) • Подтягивания 4 раза, 2–3 подхода в разное время дня, не до утомления • Ходьба: цель 8–10 тысяч шагов • Вода 2–2,5 литра и сон 7–8 часов
A98: 14 | B98: ='Расчёт'!$B$11+93 | C98: =TEXT(B98,"ddd") | D98: Продление | E98: отдых | F98: Лёгкий день | G98: КАЖДЫЙ ДЕНЬ, 5 МИНУТ (НЕ ОТДЕЛЬНАЯ ТРЕНИРОВКА) • Подтягивания 4 раза, 2–3 подхода в разное время дня, не до утомления • Ходьба: цель 8–10 тысяч шагов • Вода 2–2,5 литра и сон 7–8 часов
A99: 14 | B99: ='Расчёт'!$B$11+94 | C99: =TEXT(B99,"ddd") | D99: Продление | E99: челнок | F99: Сессия Б: челночный + ноги + подтягивания | G99: РАЗМИНКА 8–10 МИН • Ходьба и очень лёгкий бег 4–5 минут • Круги: плечи, таз, колени, голеностоп по 10 • Выпады с поворотом и махи ногами по 8 • 3 ускорения по 40 м, без усилия ЧЕЛНОЧНЫЙ БЕГ • Техника разворота на 5 м: 6 раз • 6×10×10 м, из них 3 быстрых (цель 25.9 с), отдых 3 минуты, ходьба • Остальные на 85% скорости НОГИ И ЯГОДИЦЫ (КОЛЕНИ БЕРЕГУ) • Присед до скамьи 4×12, с w≥5 с рюкзаком • Подъём на скамью 3×8 на ногу • Румынская тяга с рюкзаком 3×10–12 • Ягодичный мостик 3×15 • Подъём на носки 3×15–20 ПОДТЯГИВАНИЯ: ЛЕСТНИЦЫ • 4 лестницы 1-2-…-4 с отдыхом 2 минуты ОТЖИМАНИЯ И КОР • Отжимания 3×(максимум − 2) • Скручивания 3×15 ЗАМИНКА 5–8 МИН • Ходьба 3–5 минут, пока пульс не успокоится • Растяжка по 30 секунд: икры, бёдра, ягодицы, грудь КАЖДЫЙ ДЕНЬ, 5 МИНУТ (НЕ ОТДЕЛЬНАЯ ТРЕНИРОВКА) • Подтягивания 4 раза, 2–3 подхода в разное время дня, не до утомления • Ходьба: цель 8–10 тысяч шагов • Вода 2–2,5 литра и сон 7–8 часов
A100: 14 | B100: ='Расчёт'!$B$11+95 | C100: =TEXT(B100,"ddd") | D100: Продление | E100: отдых | F100: Лёгкий день | G100: КАЖДЫЙ ДЕНЬ, 5 МИНУТ (НЕ ОТДЕЛЬНАЯ ТРЕНИРОВКА) • Подтягивания 4 раза, 2–3 подхода в разное время дня, не до утомления • Ходьба: цель 8–10 тысяч шагов • Вода 2–2,5 литра и сон 7–8 часов
A101: 14 | B101: ='Расчёт'!$B$11+96 | C101: =TEXT(B101,"ddd") | D101: Продление | E101: по желанию | F101: Необязательно: лёгкий бег | G101: ЧТО ДЕЛАТЬ • Лёгкий бег 40 мин в разговорном темпе • Если колени болят, замени на ходьбу 40 минут
...

Sheet Темпы
A1: Целевые времена по неделям
A2: Темп 1 км и время отрезков. Берётся из реалистичной траектории. Если на тесте ты быстрее или медленнее, ориентируйся на свой результат.
A4: Нед. | B4: Темп 1 км | C4: 100 м | D4: 200 м | E4: 300 м | F4: 400 м | G4: 600 м | H4: 800 м | I4: 10×10, с | J4: Подтяг. (ориентир) | K4: Вес, кг (ориентир)
A5: 1 | B5: 0.0035590278 | C5: =$B5*0.1*0.93 | D5: =$B5*0.2*0.94 | E5: =$B5*0.3*0.96 | F5: =$B5*0.4*0.97 | G5: =$B5*0.6*0.99 | H5: =$B5*0.8*1.0 | I5: 27.88 | J5: 3.5 | K5: ='Расчёт'!$B$5-0.5
A6: 2 | B6: 0.0035300926 | C6: =$B6*0.1*0.93 | D6: =$B6*0.2*0.94 | E6: =$B6*0.3*0.96 | F6: =$B6*0.4*0.97 | G6: =$B6*0.6*0.99 | H6: =$B6*0.8*1.0 | I6: 27.75 | J6: 4 | K6: ='Расчёт'!$B$5-1.0
A7: 3 | B7: 0.0035011574 | C7: =$B7*0.1*0.93 | D7: =$B7*0.2*0.94 | E7: =$B7*0.3*0.96 | F7: =$B7*0.4*0.97 | G7: =$B7*0.6*0.99 | H7: =$B7*0.8*1.0 | I7: 27.62 | J7: 4.5 | K7: ='Расчёт'!$B$5-1.5
A8: 4 | B8: 0.0034722222 | C8: =$B8*0.1*0.93 | D8: =$B8*0.2*0.94 | E8: =$B8*0.3*0.96 | F8: =$B8*0.4*0.97 | G8: =$B8*0.6*0.99 | H8: =$B8*0.8*1.0 | I8: 27.5 | J8: 5 | K8: ='Расчёт'!$B$5-2.0
A9: 5 | B9: 0.0034403935 | C9: =$B9*0.1*0.93 | D9: =$B9*0.2*0.94 | E9: =$B9*0.3*0.96 | F9: =$B9*0.4*0.97 | G9: =$B9*0.6*0.99 | H9: =$B9*0.8*1.0 | I9: 27.32 | J9: 5.5 | K9: ='Расчёт'!$B$5-2.6200000000000045
A10: 6 | B10: 0.0034085648 | C10: =$B10*0.1*0.93 | D10: =$B10*0.2*0.94 | E10: =$B10*0.3*0.96 | F10: =$B10*0.4*0.97 | G10: =$B10*0.6*0.99 | H10: =$B10*0.8*1.0 | I10: 27.15 | J10: 6 | K10: ='Расчёт'!$B$5-3.25
A11: 7 | B11: 0.0033767361 | C11: =$B11*0.1*0.93 | D11: =$B11*0.2*0.94 | E11: =$B11*0.3*0.96 | F11: =$B11*0.4*0.97 | G11: =$B11*0.6*0.99 | H11: =$B11*0.8*1.0 | I11: 26.98 | J11: 6.5 | K11: ='Расчёт'!$B$5-3.8799999999999955
A12: 8 | B12: 0.0033449074 | C12: =$B12*0.1*0.93 | D12: =$B12*0.2*0.94 | E12: =$B12*0.3*0.96 | F12: =$B12*0.4*0.97 | G12: =$B12*0.6*0.99 | H12: =$B12*0.8*1.0 | I12: 26.8 | J12: 7 | K12: ='Расчёт'!$B$5-4.5
A13: 9 | B13: 0.0033159722 | C13: =$B13*0.1*0.93 | D13: =$B13*0.2*0.94 | E13: =$B13*0.3*0.96 | F13: =$B13*0.4*0.97 | G13: =$B13*0.6*0.99 | H13: =$B13*0.8*1.0 | I13: 26.65 | J13: 7.5 | K13: ='Расчёт'!$B$5-5.1200000000000045
A14: 10 | B14: 0.003287037 | C14: =$B14*0.1*0.93 | D14: =$B14*0.2*0.94 | E14: =$B14*0.3*0.96 | F14: =$B14*0.4*0.97 | G14: =$B14*0.6*0.99 | H14: =$B14*0.8*1.0 | I14: 26.5 | J14: 8 | K14: ='Расчёт'!$B$5-5.75
A15: 11 | B15: 0.0032581019 | C15: =$B15*0.1*0.93 | D15: =$B15*0.2*0.94 | E15: =$B15*0.3*0.96 | F15: =$B15*0.4*0.97 | G15: =$B15*0.6*0.99 | H15: =$B15*0.8*1.0 | I15: 26.35 | J15: 8.5 | K15: ='Расчёт'!$B$5-6.3799999999999955
A16: 12 | B16: 0.0032291667 | C16: =$B16*0.1*0.93 | D16: =$B16*0.2*0.94 | E16: =$B16*0.3*0.96 | F16: =$B16*0.4*0.97 | G16: =$B16*0.6*0.99 | H16: =$B16*0.8*1.0 | I16: 26.2 | J16: 9 | K16: ='Расчёт'!$B$5-7.0
A17: 13 | B17: 0.003203125 | C17: =$B17*0.1*0.93 | D17: =$B17*0.2*0.94 | E17: =$B17*0.3*0.96 | F17: =$B17*0.4*0.97 | G17: =$B17*0.6*0.99 | H17: =$B17*0.8*1.0 | I17: 26.05 | J17: 9.5 | K17: ='Расчёт'!$B$5-7.5
A18: 14 | B18: 0.0031770833 | C18: =$B18*0.1*0.93 | D18: =$B18*0.2*0.94 | E18: =$B18*0.3*0.96 | F18: =$B18*0.4*0.97 | G18: =$B18*0.6*0.99 | H18: =$B18*0.8*1.0 | I18: 25.9 | J18: 10 | K18: ='Расчёт'!$B$5-8.0
A19: 15 | B19: 0.0031510417 | C19: =$B19*0.1*0.93 | D19: =$B19*0.2*0.94 | E19: =$B19*0.3*0.96 | F19: =$B19*0.4*0.97 | G19: =$B19*0.6*0.99 | H19: =$B19*0.8*1.0 | I19: 25.75 | J19: 10.5 | K19: ='Расчёт'!$B$5-8.5
A20: 16 | B20: 0.003125 | C20: =$B20*0.1*0.93 | D20: =$B20*0.2*0.94 | E20: =$B20*0.3*0.96 | F20: =$B20*0.4*0.97 | G20: =$B20*0.6*0.99 | H20: =$B20*0.8*1.0 | I20: 25.6 | J20: 11 | K20: ='Расчёт'!$B$5-9.0
A22: Серым выделены контрольные недели.

Sheet Дневник
A1: Дневник результатов
A2: Вноси данные в жёлтые ячейки. 1 км вводи в двух колонках: минуты и секунды.
P3: Плановая траектория (для графиков)
A4: Дата | B4: Вес, кг | C4: Талия, см | D4: 1 км, мин | E4: 1 км, сек | F4: Подтягивания | G4: 10×10, с | H4: Шаги | I4: Самочувствие 1–5 | J4: Сон, ч | K4: Колени 0–10 | L4: Комментарий | M4: 1 км, всего сек | P4: Нед. | Q4: Дата | R4: 1 км, с | S4: Подтяг. | T4: 10×10, с | U4: Вес, кг
A5: 46296 | D5: 5 | E5: 10 | F5: 3 | G5: 28 | L5: Исходные данные из таблицы | M5: =IF(AND(D5<>"",E5<>""),D5*60+E5,"") | P5: 0 | Q5: ='Расчёт'!$B$11+0 | R5: 310 | S5: 3 | T5: 28 | U5: ='Расчёт'!$B$5-0.0
M6: =IF(AND(D6<>"",E6<>""),D6*60+E6,"") | P6: 1 | Q6: ='Расчёт'!$B$11+7 | R6: 307.5 | S6: 3.5 | T6: 27.88 | U6: ='Расчёт'!$B$5-0.5
M7: =IF(AND(D7<>"",E7<>""),D7*60+E7,"") | P7: 2 | Q7: ='Расчёт'!$B$11+14 | R7: 305 | S7: 4 | T7: 27.75 | U7: ='Расчёт'!$B$5-1.0
M8: =IF(AND(D8<>"",E8<>""),D8*60+E8,"") | P8: 3 | Q8: ='Расчёт'!$B$11+21 | R8: 302.5 | S8: 4.5 | T8: 27.62 | U8: ='Расчёт'!$B$5-1.5
M9: =IF(AND(D9<>"",E9<>""),D9*60+E9,"") | P9: 4 | Q9: ='Расчёт'!$B$11+28 | R9: 300 | S9: 5 | T9: 27.5 | U9: ='Расчёт'!$B$5-2.0
M10: =IF(AND(D10<>"",E10<>""),D10*60+E10,"") | P10: 5 | Q10: ='Расчёт'!$B$11+35 | R10: 297.25 | S10: 5.5 | T10: 27.32 | U10: ='Расчёт'!$B$5-2.6200000000000045
M11: =IF(AND(D11<>"",E11<>""),D11*60+E11,"") | P11: 6 | Q11: ='Расчёт'!$B$11+42 | R11: 294.5 | S11: 6 | T11: 27.15 | U11: ='Расчёт'!$B$5-3.25
M12: =IF(AND(D12<>"",E12<>""),D12*60+E12,"") | P12: 7 | Q12: ='Расчёт'!$B$11+49 | R12: 291.75 | S12: 6.5 | T12: 26.98 | U12: ='Расчёт'!$B$5-3.8799999999999955
M13: =IF(AND(D13<>"",E13<>""),D13*60+E13,"") | P13: 8 | Q13: ='Расчёт'!$B$11+56 | R13: 289 | S13: 7 | T13: 26.8 | U13: ='Расчёт'!$B$5-4.5
M14: =IF(AND(D14<>"",E14<>""),D14*60+E14,"") | P14: 9 | Q14: ='Расчёт'!$B$11+63 | R14: 286.5 | S14: 7.5 | T14: 26.65 | U14: ='Расчёт'!$B$5-5.1200000000000045
M15: =IF(AND(D15<>"",E15<>""),D15*60+E15,"") | P15: 10 | Q15: ='Расчёт'!$B$11+70 | R15: 284 | S15: 8 | T15: 26.5 | U15: ='Расчёт'!$B$5-5.75
M16: =IF(AND(D16<>"",E16<>""),D16*60+E16,"") | P16: 11 | Q16: ='Расчёт'!$B$11+77 | R16: 281.5 | S16: 8.5 | T16: 26.35 | U16: ='Расчёт'!$B$5-6.3799999999999955
M17: =IF(AND(D17<>"",E17<>""),D17*60+E17,"") | P17: 12 | Q17: ='Расчёт'!$B$11+84 | R17: 279 | S17: 9 | T17: 26.2 | U17: ='Расчёт'!$B$5-7.0
M18: =IF(AND(D18<>"",E18<>""),D18*60+E18,"") | P18: 13 | Q18: ='Расчёт'!$B$11+91 | R18: 276.75 | S18: 9.5 | T18: 26.05 | U18: ='Расчёт'!$B$5-7.5
M19: =IF(AND(D19<>"",E19<>""),D19*60+E19,"") | P19: 14 | Q19: ='Расчёт'!$B$11+98 | R19: 274.5 | S19: 10 | T19: 25.9 | U19: ='Расчёт'!$B$5-8.0
M20: =IF(AND(D20<>"",E20<>""),D20*60+E20,"") | P20: 15 | Q20: ='Расчёт'!$B$11+105 | R20: 272.25 | S20: 10.5 | T20: 25.75 | U20: ='Расчёт'!$B$5-8.5
M21: =IF(AND(D21<>"",E21<>""),D21*60+E21,"") | P21: 16 | Q21: ='Расчёт'!$B$11+112 | R21: 270 | S21: 11 | T21: 25.6 | U21: ='Расчёт'!$B$5-9.0
M22: =IF(AND(D22<>"",E22<>""),D22*60+E22,"")
M23: =IF(AND(D23<>"",E23<>""),D23*60+E23,"")
M24: =IF(AND(D24<>"",E24<>""),D24*60+E24,"")
M25: =IF(AND(D25<>"",E25<>""),D25*60+E25,"")
M26: =IF(AND(D26<>"",E26<>""),D26*60+E26,"")
M27: =IF(AND(D27<>"",E27<>""),D27*60+E27,"")
M28: =IF(AND(D28<>"",E28<>""),D28*60+E28,"")
M29: =IF(AND(D29<>"",E29<>""),D29*60+E29,"")
M30: =IF(AND(D30<>"",E30<>""),D30*60+E30,"")
M31: =IF(AND(D31<>"",E31<>""),D31*60+E31,"")
M32: =IF(AND(D32<>"",E32<>""),D32*60+E32,"")
M33: =IF(AND(D33<>"",E33<>""),D33*60+E33,"")
... M154: =IF(AND(D154<>"",E154<>""),D154*60+E154,"")

Sheet Меню
A1: Меню на неделю: он и жена
A2: Граммы подгоняются под твою норму ккал из листа «Расчёт». Продукты берутся из листа «Продукты».
A4: День | B4: Приём | C4: Блюдо | D4: Продукт | E4: База, г | F4: Множитель | G4: Он, г | H4: Жена, г | I4: Ккал (он) | J4: Белок (он) | K4: Жиры (он) | L4: Углев. (он) | N4: Итоги дня
A5: Пн | B5: Завтрак | C5: Овсянка на молоке с бананом | D5: Овсяные хлопья (сухие) | E5: 70 | F5: =MIN(1.7,MAX(0.65,'Расчёт'!$B$17/2170.5)) | G5: =ROUND(E5*F5/5,0)*5 | H5: =ROUND(E5*F5*'Расчёт'!$B$10/5,0)*5 | I5: =G5*VLOOKUP($D5,'Продукты'!$A$4:$G$34,2,FALSE)/100 | J5: =G5*VLOOKUP($D5,'Продукты'!$A$4:$G$34,3,FALSE)/100 | K5: =G5*VLOOKUP($D5,'Продукты'!$A$4:$G$34,4,FALSE)/100 | L5: =G5*VLOOKUP($D5,'Продукты'!$A$4:$G$34,5,FALSE)/100 | N5: День | O5: Ккал | P5: Белок, г | Q5: Жиры, г | R5: Углев., г | S5: Норма ккал
A6: Пн | B6: Завтрак | C6: Овсянка на молоке с бананом | D6: Молоко 2.5% | E6: 200 | F6: =MIN(1.7,MAX(0.65,'Расчёт'!$B$17/2170.5)) | G6: =ROUND(E6*F6/5,0)*5 | H6: =ROUND(E6*F6*'Расчёт'!$B$10/5,0)*5 | I6: =G6*VLOOKUP($D6,'Продукты'!$A$4:$G$34,2,FALSE)/100 | J6: =G6*VLOOKUP($D6,'Продукты'!$A$4:$G$34,3,FALSE)/100 | K6: =G6*VLOOKUP($D6,'Продукты'!$A$4:$G$34,4,FALSE)/100 | L6: =G6*VLOOKUP($D6,'Продукты'!$A$4:$G$34,5,FALSE)/100 | N6: Пн | O6: =SUMIFS(I$5:I$149,$A$5:$A$149,$N6) | P6: =SUMIFS(J$5:J$149,$A$5:$A$149,$N6) | Q6: =SUMIFS(K$5:K$149,$A$5:$A$149,$N6) | R6: =SUMIFS(L$5:L$149,$A$5:$A$149,$N6) | S6: ='Расчёт'!$B$17
A7: Пн | B7: Завтрак | C7: Овсянка на молоке с бананом | D7: Бананы (очищенные) | E7: 100 | F7: =MIN(1.7,MAX(0.65,'Расчёт'!$B$17/2170.5)) | G7: =ROUND(E7*F7/5,0)*5 | H7: =ROUND(E7*F7*'Расчёт'!$B$10/5,0)*5 | I7: =G7*VLOOKUP($D7,'Продукты'!$A$4:$G$34,2,FALSE)/100 | J7: =G7*VLOOKUP($D7,'Продукты'!$A$4:$G$34,3,FALSE)/100 | K7: =G7*VLOOKUP($D7,'Продукты'!$A$4:$G$34,4,FALSE)/100 | L7: =G7*VLOOKUP($D7,'Продукты'!$A$4:$G$34,5,FALSE)/100 | N7: Вт | O7: =SUMIFS(I$5:I$149,$A$5:$A$149,$N7) | P7: =SUMIFS(J$5:J$149,$A$5:$A$149,$N7) | Q7: =SUMIFS(K$5:K$149,$A$5:$A$149,$N7) | R7: =SUMIFS(L$5:L$149,$A$5:$A$149,$N7) | S7: ='Расчёт'!$B$17
A8: Пн | B8: Завтрак | C8: Овсянка на молоке с бананом | D8: Грецкие орехи | E8: 10 | F8: =MIN(1.7,MAX(0.65,'Расчёт'!$B$17/2170.5)) | G8: =ROUND(E8*F8/5,0)*5 | H8: =ROUND(E8*F8*'Расчёт'!$B$10/5,0)*5 | I8: =G8*VLOOKUP($D8,'Продукты'!$A$4:$G$34,2,FALSE)/100 | J8: =G8*VLOOKUP($D8,'Продукты'!$A$4:$G$34,3,FALSE)/100 | K8: =G8*VLOOKUP($D8,'Продукты'!$A$4:$G$34,4,FALSE)/100 | L8: =G8*VLOOKUP($D8,'Продукты'!$A$4:$G$34,5,FALSE)/100 | N8: Ср | O8: =SUMIFS(I$5:I$149,$A$5:$A$149,$N8) | P8: =SUMIFS(J$5:J$149,$A$5:$A$149,$N8) | Q8: =SUMIFS(K$5:K$149,$A$5:$A$149,$N8) | R8: =SUMIFS(L$5:L$149,$A$5:$A$149,$N8) | S8: ='Расчёт'!$B$17
A9: Пн | B9: Завтрак | C9: Добавка | D9: Яйцо | E9: 110 | F9: =MIN(1.7,MAX(0.65,'Расчёт'!$B$17/2170.5)) | G9: =ROUND(E9*F9/5,0)*5 | H9: =ROUND(E9*F9*'Расчёт'!$B$10/5,0)*5 | I9: =G9*VLOOKUP($D9,'Продукты'!$A$4:$G$34,2,FALSE)/100 | J9: =G9*VLOOKUP($D9,'Продукты'!$A$4:$G$34,3,FALSE)/100 | K9: =G9*VLOOKUP($D9,'Продукты'!$A$4:$G$34,4,FALSE)/100 | L9: =G9*VLOOKUP($D9,'Продукты'!$A$4:$G$34,5,FALSE)/100 | N9: Чт | O9: =SUMIFS(I$5:I$149,$A$5:$A$149,$N9) | P9: =SUMIFS(J$5:J$149,$A$5:$A$149,$N9) | Q9: =SUMIFS(K$5:K$149,$A$5:$A$149,$N9) | R9: =SUMIFS(L$5:L$149,$A$5:$A$149,$N9) | S9: ='Расчёт'!$B$17
A10: Пн | B10: Обед | C10: Гречка с тушёной курицей и капустой | D10: Гречка (сухая) | E10: 70 | F10: =MIN(1.7,MAX(0.65,'Расчёт'!$B$17/2170.5)) | G10: =ROUND(E10*F10/5,0)*5 | H10: =ROUND(E10*F10*'Расчёт'!$B$10/5,0)*5 | I10: =G10*VLOOKUP($D10,'Продукты'!$A$4:$G$34,2,FALSE)/100 | J10: =G10*VLOOKUP($D10,'Продукты'!$A$4:$G$34,3,FALSE)/100 | K10: =G10*VLOOKUP($D10,'Продукты'!$A$4:$G$34,4,FALSE)/100 | L10: =G10*VLOOKUP($D10,'Продукты'!$A$4:$G$34,5,FALSE)/100 | N10: Пт | O10: =SUMIFS(I$5:I$149,$A$5:$A$149,$N10) | P10: =SUMIFS(J$5:J$149,$A$5:$A$149,$N10) | Q10: =SUMIFS(K$5:K$149,$A$5:$A$149,$N10) | R10: =SUMIFS(L$5:L$149,$A$5:$A$149,$N10) | S10: ='Расчёт'!$B$17
A11: Пн | B11: Обед | C11: Гречка с тушёной курицей и капустой | D11: Куриные бёдра/голень без кожи | E11: 170 | F11: =MIN(1.7,MAX(0.65,'Расчёт'!$B$17/2170.5)) | G11: =ROUND(E11*F11/5,0)*5 | H11: =ROUND(E11*F11*'Расчёт'!$B$10/5,0)*5 | I11: =G11*VLOOKUP($D11,'Продукты'!$A$4:$G$34,2,FALSE)/100 | J11: =G11*VLOOKUP($D11,'Продукты'!$A$4:$G$34,3,FALSE)/100 | K11: =G11*VLOOKUP($D11,'Продукты'!$A$4:$G$34,4,FALSE)/100 | L11: =G11*VLOOKUP($D11,'Продукты'!$A$4:$G$34,5,FALSE)/100 | N11: Сб | O11: =SUMIFS(I$5:I$149,$A$5:$A$149,$N11) | P11: =SUMIFS(J$5:J$149,$A$5:$A$149,$N11) | Q11: =SUMIFS(K$5:K$149,$A$5:$A$149,$N11) | R11: =SUMIFS(L$5:L$149,$A$5:$A$149,$N11) | S11: ='Расчёт'!$B$17
A12: Пн | B12: Обед | C12: Гречка с тушёной курицей и капустой | D12: Капуста белокочанная | E12: 150 | F12: =MIN(1.7,MAX(0.65,'Расчёт'!$B$17/2170.5)) | G12: =ROUND(E12*F12/5,0)*5 | H12: =ROUND(E12*F12*'Расчёт'!$B$10/5,0)*5 | I12: =G12*VLOOKUP($D12,'Продукты'!$A$4:$G$34,2,FALSE)/100 | J12: =G12*VLOOKUP($D12,'Продукты'!$A$4:$G$34,3,FALSE)/100 | K12: =G12*VLOOKUP($D12,'Продукты'!$A$4:$G$34,4,FALSE)/100 | L12: =G12*VLOOKUP($D12,'Продукты'!$A$4:$G$34,5,FALSE)/100 | N12: Вс | O12: =SUMIFS(I$5:I$149,$A$5:$A$149,$N12) | P12: =SUMIFS(J$5:J$149,$A$5:$A$149,$N12) | Q12: =SUMIFS(K$5:K$149,$A$5:$A$149,$N12) | R12: =SUMIFS(L$5:L$149,$A$5:$A$149,$N12) | S12: ='Расчёт'!$B$17
A13: Пн | B13: Обед | C13: Гречка с тушёной курицей и капустой | D13: Морковь | E13: 40 | F13: =MIN(1.7,MAX(0.65,'Расчёт'!$B$17/2170.5)) | G13: =ROUND(E13*F13/5,0)*5 | H13: =ROUND(E13*F13*'Расчёт'!$B$10/5,0)*5 | I13: =G13*VLOOKUP($D13,'Продукты'!$A$4:$G$34,2,FALSE)/100 | J13: =G13*VLOOKUP($D13,'Продукты'!$A$4:$G$34,3,FALSE)/100 | K13: =G13*VLOOKUP($D13,'Продукты'!$A$4:$G$34,4,FALSE)/100 | L13: =G13*VLOOKUP($D13,'Продукты'!$A$4:$G$34,5,FALSE)/100
A14: Пн | B14: Обед | C14: Гречка с тушёной курицей и капустой | D14: Лук репчатый | E14: 30 | F14: =MIN(1.7,MAX(0.65,'Расчёт'!$B$17/2170.5)) | G14: =ROUND(E14*F14/5,0)*5 | H14: =ROUND(E14*F14*'Расчёт'!$B$10/5,0)*5 | I14: =G14*VLOOKUP($D14,'Продукты'!$A$4:$G$34,2,FALSE)/100 | J14: =G14*VLOOKUP($D14,'Продукты'!$A$4:$G$34,3,FALSE)/100 | K14: =G14*VLOOKUP($D14,'Продукты'!$A$4:$G$34,4,FALSE)/100 | L14: =G14*VLOOKUP($D14,'Продукты'!$A$4:$G$34,5,FALSE)/100
A15: Пн | B15: Обед | C15: Гречка с тушёной курицей и капустой | D15: Масло растительное | E15: 5 | F15: =MIN(1.7,MAX(0.65,'Расчёт'!$B$17/2170.5)) | G15: =ROUND(E15*F15/5,0)*5 | H15: =ROUND(E15*F15*'Расчёт'!$B$10/5,0)*5 | I15: =G15*VLOOKUP($D15,'Продукты'!$A$4:$G$34,2,FALSE)/100 | J15: =G15*VLOOKUP($D15,'Продукты'!$A$4:$G$34,3,FALSE)/100 | K15: =G15*VLOOKUP($D15,'Продукты'!$A$4:$G$34,4,FALSE)/100 | L15: =G15*VLOOKUP($D15,'Продукты'!$A$4:$G$34,5,FALSE)/100
A16: Пн | B16: Перекус | C16: Кефир с бананом | D16: Кефир 1% | E16: 300 | F16: =MIN(1.7,MAX(0.65,'Расчёт'!$B$17/2170.5)) | G16: =ROUND(E16*F16/5,0)*5 | H16: =ROUND(E16*F16*'Расчёт'!$B$10/5,0)*5 | I16: =G16*VLOOKUP($D16,'Продукты'!$A$4:$G$34,2,FALSE)/100 | J16: =G16*VLOOKUP($D16,'Продукты'!$A$4:$G$34,3,FALSE)/100 | K16: =G16*VLOOKUP($D16,'Продукты'!$A$4:$G$34,4,FALSE)/100 | L16: =G16*VLOOKUP($D16,'Продукты'!$A$4:$G$34,5,FALSE)/100
A17: Пн | B17: Перекус | C17: Кефир с бананом | D17: Бананы (очищенные) | E17: 110 | F17: =MIN(1.7,MAX(0.65,'Расчёт'!$B$17/2170.5)) | G17: =ROUND(E17*F17/5,0)*5 | H17: =ROUND(E17*F17*'Расчёт'!$B$10/5,0)*5 | I17: =G17*VLOOKUP($D17,'Продукты'!$A$4:$G$34,2,FALSE)/100 | J17: =G17*VLOOKUP($D17,'Продукты'!$A$4:$G$34,3,FALSE)/100 | K17: =G17*VLOOKUP($D17,'Продукты'!$A$4:$G$34,4,FALSE)/100 | L17: =G17*VLOOKUP($D17,'Продукты'!$A$4:$G$34,5,FALSE)/100
A18: Пн | B18: Перекус | C18: Кефир с бананом | D18: Хлеб цельнозерновой/ржаной | E18: 30 | F18: =MIN(1.7,MAX(0.65,'Расчёт'!$B$17/2170.5)) | G18: =ROUND(E18*F18/5,0)*5 | H18: =ROUND(E18*F18*'Расчёт'!$B$10/5,0)*5 | I18: =G18*VLOOKUP($D18,'Продукты'!$A$4:$G$34,2,FALSE)/100 | J18: =G18*VLOOKUP($D18,'Продукты'!$A$4:$G$34,3,FALSE)/100 | K18: =G18*VLOOKUP($D18,'Продукты'!$A$4:$G$34,4,FALSE)/100 | L18: =G18*VLOOKUP($D18,'Продукты'!$A$4:$G$34,5,FALSE)/100
A19: Пн | B19: Ужин | C19: Минтай с картофелем, запечённые | D19: Белая рыба (минтай, хек) | E19: 200 | F19: =MIN(1.7,MAX(0.65,'Расчёт'!$B$17/2170.5)) | G19: =ROUND(E19*F19/5,0)*5 | H19: =ROUND(E19*F19*'Расчёт'!$B$10/5,0)*5 | I19: =G19*VLOOKUP($D19,'Продукты'!$A$4:$G$34,2,FALSE)/100 | J19: =G19*VLOOKUP($D19,'Продукты'!$A$4:$G$34,3,FALSE)/100 | K19: =G19*VLOOKUP($D19,'Продукты'!$A$4:$G$34,4,FALSE)/100 | L19: =G19*VLOOKUP($D19,'Продукты'!$A$4:$G$34,5,FALSE)/100
A20: Пн | B20: Ужин | C20: Минтай с картофелем, запечённые | D20: Картофель | E20: 300 | F20: =MIN(1.7,MAX(0.65,'Расчёт'!$B$17/2170.5)) | G20: =ROUND(E20*F20/5,0)*5 | H20: =ROUND(E20*F20*'Расчёт'!$B$10/5,0)*5 | I20: =G20*VLOOKUP($D20,'Продукты'!$A$4:$G$34,2,FALSE)/100 | J20: =G20*VLOOKUP($D20,'Продукты'!$A$4:$G$34,3,FALSE)/100 | K20: =G20*VLOOKUP($D20,'Продукты'!$A$4:$G$34,4,FALSE)/100 | L20: =G20*VLOOKUP($D20,'Продукты'!$A$4:$G$34,5,FALSE)/100
A21: Пн | B21: Ужин | C21: Минтай с картофелем, запечённые | D21: Масло растительное | E21: 8 | F21: =MIN(1.7,MAX(0.65,'Расчёт'!$B$17/2170.5)) | G21: =ROUND(E21*F21/5,0)*5 | H21: =ROUND(E21*F21*'Расчёт'!$B$10/5,0)*5 | I21: =G21*VLOOKUP($D21,'Продукты'!$A$4:$G$34,2,FALSE)/100 | J21: =G21*VLOOKUP($D21,'Продукты'!$A$4:$G$34,3,FALSE)/100 | K21: =G21*VLOOKUP($D21,'Продукты'!$A$4:$G$34,4,FALSE)/100 | L21: =G21*VLOOKUP($D21,'Продукты'!$A$4:$G$34,5,FALSE)/100
A22: Пн | B22: Ужин | C22: Минтай с картофелем, запечённые | D22: Лук репчатый | E22: 30 | F22: =MIN(1.7,MAX(0.65,'Расчёт'!$B$17/2170.5)) | G22: =ROUND(E22*F22/5,0)*5 | H22: =ROUND(E22*F22*'Расчёт'!$B$10/5,0)*5 | I22: =G22*VLOOKUP($D22,'Продукты'!$A$4:$G$34,2,FALSE)/100 | J22: =G22*VLOOKUP($D22,'Продукты'!$A$4:$G$34,3,FALSE)/100 | K22: =G22*VLOOKUP($D22,'Продукты'!$A$4:$G$34,4,FALSE)/100 | L22: =G22*VLOOKUP($D22,'Продукты'!$A$4:$G$34,5,FALSE)/100
A23: Пн | B23: Ужин | C23: Минтай с картофелем, запечённые | D23: Огурцы | E23: 100 | F23: =MIN(1.7,MAX(0.65,'Расчёт'!$B$17/2170.5)) | G23: =ROUND(E23*F23/5,0)*5 | H23: =ROUND(E23*F23*'Расчёт'!$B$10/5,0)*5 | I23: =G23*VLOOKUP($D23,'Продукты'!$A$4:$G$34,2,FALSE)/100 | J23: =G23*VLOOKUP($D23,'Продукты'!$A$4:$G$34,3,FALSE)/100 | K23: =G23*VLOOKUP($D23,'Продукты'!$A$4:$G$34,4,FALSE)/100 | L23: =G23*VLOOKUP($D23,'Продукты'!$A$4:$G$34,5,FALSE)/100
A24: Пн | B24: Ужин | C24: Капустный салат | D24: Капуста белокочанная | E24: 150 | F24: =MIN(1.7,MAX(0.65,'Расчёт'!$B$17/2170.5)) | G24: =ROUND(E24*F24/5,0)*5 | H24: =ROUND(E24*F24*'Расчёт'!$B$10/5,0)*5 | I24: =G24*VLOOKUP($D24,'Продукты'!$A$4:$G$34,2,FALSE)/100 | J24: =G24*VLOOKUP($D24,'Продукты'!$A$4:$G$34,3,FALSE)/100 | K24: =G24*VLOOKUP($D24,'Продукты'!$A$4:$G$34,4,FALSE)/100 | L24: =G24*VLOOKUP($D24,'Продукты'!$A$4:$G$34,5,FALSE)/100
... A26: Пн | B26: Ужин | C26: Капустный салат | D26: Масло растительное | E26: 8 | F26: =MIN(1.7,MAX(0.65,'Расчёт'!$B$17/2170.5)) | G26: =ROUND(E26*F26/5,0)*5 | H26: =ROUND(E26*F26*'Расчёт'!$B$10/5,0)*5 | I26: =G26*VLOOKUP($D26,'Продукты'!$A$4:$G$34,2,FALSE)/100 | J26: =G26*VLOOKUP($D26,'Продукты'!$A$4:$G$34,3,FALSE)/100 | K26: =G26*VLOOKUP($D26,'Продукты'!$A$4:$G$34,4,FALSE)/100 | L26: =G26*VLOOKUP($D26,'Продукты'!$A$4:$G$34,5,FALSE)/100
A27: Вт | B27: Завтрак | C27: Омлет с овощами и хлебом | D27: Яйцо | E27: 165 | F27: =MIN(1.7,MAX(0.65,'Расчёт'!$B$17/1978.5)) | G27: =ROUND(E27*F27/5,0)*5 | H27: =ROUND(E27*F27*'Расчёт'!$B$10/5,0)*5 | I27: =G27*VLOOKUP($D27,'Продукты'!$A$4:$G$34,2,FALSE)/100 | J27: =G27*VLOOKUP($D27,'Продукты'!$A$4:$G$34,3,FALSE)/100 | K27: =G27*VLOOKUP($D27,'Продукты'!$A$4:$G$34,4,FALSE)/100 | L27: =G27*VLOOKUP($D27,'Продукты'!$A$4:$G$34,5,FALSE)/100
A28: Вт | B28: Завтрак | C28: Омлет с овощами и хлебом | D28: Помидоры | E28: 80 | F28: =MIN(1.7,MAX(0.65,'Расчёт'!$B$17/1978.5)) | G28: =ROUND(E28*F28/5,0)*5 | H28: =ROUND(E28*F28*'Расчёт'!$B$10/5,0)*5 | I28: =G28*VLOOKUP($D28,'Продукты'!$A$4:$G$34,2,FALSE)/100 | J28: =G28*VLOOKUP($D28,'Продукты'!$A$4:$G$34,3,FALSE)/100 | K28: =G28*VLOOKUP($D28,'Продукты'!$A$4:$G$34,4,FALSE)/100 | L28: =G28*VLOOKUP($D28,'Продукты'!$A$4:$G$34,5,FALSE)/100
A29: Вт | B29: Завтрак | C29: Омлет с овощами и хлебом | D29: Лук репчатый | E29: 20 | F29: =MIN(1.7,MAX(0.65,'Расчёт'!$B$17/1978.5)) | G29: =ROUND(E29*F29/5,0)*5 | H29: =ROUND(E29*F29*'Расчёт'!$B$10/5,0)*5 | I29: =G29*VLOOKUP($D29,'Продукты'!$A$4:$G$34,2,FALSE)/100 | J29: =G29*VLOOKUP($D29,'Продукты'!$A$4:$G$34,3,FALSE)/100 | K29: =G29*VLOOKUP($D29,'Продукты'!$A$4:$G$34,4,FALSE)/100 | L29: =G29*VLOOKUP($D29,'Продукты'!$A$4:$G$34,5,FALSE)/100
A30: Вт | B30: Завтрак | C30: Омлет с овощами и хлебом | D30: Масло растительное | E30: 5 | F30: =MIN(1.7,MAX(0.65,'Расчёт'!$B$17/1978.5)) | G30: =ROUND(E30*F30/5,0)*5 | H30: =ROUND(E30*F30*'Расчёт'!$B$10/5,0)*5 | I30: =G30*VLOOKUP($D30,'Продукты'!$A$4:$G$34,2,FALSE)/100 | J30: =G30*VLOOKUP($D30,'Продукты'!$A$4:$G$34,3,FALSE)/100 | K30: =G30*VLOOKUP($D30,'Продукты'!$A$4:$G$34,4,FALSE)/100 | L30: =G30*VLOOKUP($D30,'Продукты'!$A$4:$G$34,5,FALSE)/100
A31: Вт | B31: Завтрак | C31: Омлет с овощами и хлебом | D31: Хлеб цельнозерновой/ржаной | E31: 40 | F31: =MIN(1.7,MAX(0.65,'Расчёт'!$B$17/1978.5)) | G31: =ROUND(E31*F31/5,0)*5 | H31: =ROUND(E31*F31*'Расчёт'!$B$10/5,0)*5 | I31: =G31*VLOOKUP($D31,'Продукты'!$A$4:$G$34,2,FALSE)/100 | J31: =G31*VLOOKUP($D31,'Продукты'!$A$4:$G$34,3,FALSE)/100 | K31: =G31*VLOOKUP($D31,'Продукты'!$A$4:$G$34,4,FALSE)/100 | L31: =G31*VLOOKUP($D31,'Продукты'!$A$4:$G$34,5,FALSE)/100
A32: Вт | B32: Обед | C32: Рис с запечёнными бёдрами и овощами | D32: Рис (сухой) | E32: 70 | F32: =MIN(1.7,MAX(0.65,'Расчёт'!$B$17/1978.5)) | G32: =ROUND(E32*F32/5,0)*5 | H32: =ROUND(E32*F32*'Расчёт'!$B$10/5,0)*5 | I32: =G32*VLOOKUP($D32,'Продукты'!$A$4:$G$34,2,FALSE)/100 | J32: =G32*VLOOKUP($D32,'Продукты'!$A$4:$G$34,3,FALSE)/100 | K32: =G32*VLOOKUP($D32,'Продукты'!$A$4:$G$34,4,FALSE)/100 | L32: =G32*VLOOKUP($D32,'Продукты'!$A$4:$G$34,5,FALSE)/100
A33: Вт | B33: Обед | C33: Рис с запечёнными бёдрами и овощами | D33: Куриные бёдра/голень без кожи | E33: 180 | F33: =MIN(1.7,MAX(0.65,'Расчёт'!$B$17/1978.5)) | G33: =ROUND(E33*F33/5,0)*5 | H33: =ROUND(E33*F33*'Расчёт'!$B$10/5,0)*5 | I33: =G33*VLOOKUP($D33,'Продукты'!$A$4:$G$34,2,FALSE)/100 | J33: =G33*VLOOKUP($D33,'Продукты'!$A$4:$G$34,3,FALSE)/100 | K33: =G33*VLOOKUP($D33,'Продукты'!$A$4:$G$34,4,FALSE)/100 | L33: =G33*VLOOKUP($D33,'Продукты'!$A$4:$G$34,5,FALSE)/100
A34: Вт | B34: Обед | C34: Рис с запечёнными бёдрами и овощами | D34: Морковь | E34: 50 | F34: =MIN(1.7,MAX(0.65,'Расчёт'!$B$17/1978.5)) | G34: =ROUND(E34*F34/5,0)*5 | H34: =ROUND(E34*F34*'Расчёт'!$B$10/5,0)*5 | I34: =G34*VLOOKUP($D34,'Продукты'!$A$4:$G$34,2,FALSE)/100 | J34: =G34*VLOOKUP($D34,'Продукты'!$A$4:$G$34,3,FALSE)/100 | K34: =G34*VLOOKUP($D34,'Продукты'!$A$4:$G$34,4,FALSE)/100 | L34: =G34*VLOOKUP($D34,'Продукты'!$A$4:$G$34,5,FALSE)/100
A35: Вт | B35: Обед | C35: Рис с запечёнными бёдрами и овощами | D35: Лук репчатый | E35: 30 | F35: =MIN(1.7,MAX(0.65,'Расчёт'!$B$17/1978.5)) | G35: =ROUND(E35*F35/5,0)*5 | H35: =ROUND(E35*F35*'Расчёт'!$B$10/5,0)*5 | I35: =G35*VLOOKUP($D35,'Продукты'!$A$4:$G$34,2,FALSE)/100 | J35: =G35*VLOOKUP($D35,'Продукты'!$A$4:$G$34,3,FALSE)/100 | K35: =G35*VLOOKUP($D35,'Продукты'!$A$4:$G$34,4,FALSE)/100 | L35: =G35*VLOOKUP($D35,'Продукты'!$A$4:$G$34,5,FALSE)/100
A36: Вт | B36: Обед | C36: Рис с запечёнными бёдрами и овощами | D36: Помидоры | E36: 100 | F36: =MIN(1.7,MAX(0.65,'Расчёт'!$B$17/1978.5)) | G36: =ROUND(E36*F36/5,0)*5 | H36: =ROUND(E36*F36*'Расчёт'!$B$10/5,0)*5 | I36: =G36*VLOOKUP($D36,'Продукты'!$A$4:$G$34,2,FALSE)/100 | J36: =G36*VLOOKUP($D36,'Продукты'!$A$4:$G$34,3,FALSE)/100 | K36: =G36*VLOOKUP($D36,'Продукты'!$A$4:$G$34,4,FALSE)/100 | L36: =G36*VLOOKUP($D36,'Продукты'!$A$4:$G$34,5,FALSE)/100
A37: Вт | B37: Обед | C37: Рис с запечёнными бёдрами и овощами | D37: Масло растительное | E37: 5 | F37: =MIN(1.7,MAX(0.65,'Расчёт'!$B$17/1978.5)) | G37: =ROUND(E37*F37/5,0)*5 | H37: =ROUND(E37*F37*'Расчёт'!$B$10/5,0)*5 | I37: =G37*VLOOKUP($D37,'Продукты'!$A$4:$G$34,2,FALSE)/100 | J37: =G37*VLOOKUP($D37,'Продукты'!$A$4:$G$34,3,FALSE)/100 | K37: =G37*VLOOKUP($D37,'Продукты'!$A$4:$G$34,4,FALSE)/100 | L37: =G37*VLOOKUP($D37,'Продукты'!$A$4:$G$34,5,FALSE)/100
A38: Вт | B38: Обед | C38: Салат айсберг с яйцом и йогуртом | D38: Салат айсберг | E38: 150 | F38: =MIN(1.7,MAX(0.65,'Расчёт'!$B$17/1978.5)) | G38: =ROUND(E38*F38/5,0)*5 | H38: =ROUND(E38*F38*'Расчёт'!$B$10/5,0)*5 | I38: =G38*VLOOKUP($D38,'Продукты'!$A$4:$G$34,2,FALSE)/100 | J38: =G38*VLOOKUP($D38,'Продукты'!$A$4:$G$34,3,FALSE)/100 | K38: =G38*VLOOKUP($D38,'Продукты'!$A$4:$G$34,4,FALSE)/100 | L38: =G38*VLOOKUP($D38,'Продукты'!$A$4:$G$34,5,FALSE)/100
... A49: Вт | B49: Ужин | C49: Творожная запеканка с бананом | D49: Бананы (очищенные) | E49: 100 | F49: =MIN(1.7,MAX(0.65,'Расчёт'!$B$17/1978.5)) | G49: =ROUND(E49*F49/5,0)*5 | H49: =ROUND(E49*F49*'Расчёт'!$B$10/5,0)*5 | I49: =G49*VLOOKUP($D49,'Продукты'!$A$4:$G$34,2,FALSE)/100 | J49: =G49*VLOOKUP($D49,'Продукты'!$A$4:$G$34,3,FALSE)/100 | K49: =G49*VLOOKUP($D49,'Продукты'!$A$4:$G$34,4,FALSE)/100 | L49: =G49*VLOOKUP($D49,'Продукты'!$A$4:$G$34,5,FALSE)/100
A50: Ср | B50: Завтрак | C50: Овсянка с йогуртом и яблоком | D50: Овсяные хлопья (сухие) | E50: 70 | F50: =MIN(1.7,MAX(0.65,'Расчёт'!$B$17/1884.6)) | G50: =ROUND(E50*F50/5,0)*5 | H50: =ROUND(E50*F50*'Расчёт'!$B$10/5,0)*5 | I50: =G50*VLOOKUP($D50,'Продукты'!$A$4:$G$34,2,FALSE)/100 | J50: =G50*VLOOKUP($D50,'Продукты'!$A$4:$G$34,3,FALSE)/100 | K50: =G50*VLOOKUP($D50,'Продукты'!$A$4:$G$34,4,FALSE)/100 | L50: =G50*VLOOKUP($D50,'Продукты'!$A$4:$G$34,5,FALSE)/100
A51: Ср | B51: Завтрак | C51: Овсянка с йогуртом и яблоком | D51: Йогурт натуральный | E51: 150 | F51: =MIN(1.7,MAX(0.65,'Расчёт'!$B$17/1884.6)) | G51: =ROUND(E51*F51/5,0)*5 | H51: =ROUND(E51*F51*'Расчёт'!$B$10/5,0)*5 | I51: =G51*VLOOKUP($D51,'Продукты'!$A$4:$G$34,2,FALSE)/100 | J51: =G51*VLOOKUP($D51,'Продукты'!$A$4:$G$34,3,FALSE)/100 | K51: =G51*VLOOKUP($D51,'Продукты'!$A$4:$G$34,4,FALSE)/100 | L51: =G51*VLOOKUP($D51,'Продукты'!$A$4:$G$34,5,FALSE)/100
A52: Ср | B52: Завтрак | C52: Овсянка с йогуртом и яблоком | D52: Яблоки | E52: 100 | F52: =MIN(1.7,MAX(0.65,'Расчёт'!$B$17/1884.6)) | G52: =ROUND(E52*F52/5,0)*5 | H52: =ROUND(E52*F52*'Расчёт'!$B$10/5,0)*5 | I52: =G52*VLOOKUP($D52,'Продукты'!$A$4:$G$34,2,FALSE)/100 | J52: =G52*VLOOKUP($D52,'Продукты'!$A$4:$G$34,3,FALSE)/100 | K52: =G52*VLOOKUP($D52,'Продукты'!$A$4:$G$34,4,FALSE)/100 | L52: =G52*VLOOKUP($D52,'Продукты'!$A$4:$G$34,5,FALSE)/100
A53: Ср | B53: Завтрак | C53: Овсянка с йогуртом и яблоком | D53: Творог 5% | E53: 100 | F53: =MIN(1.7,MAX(0.65,'Расчёт'!$B$17/1884.6)) | G53: =ROUND(E53*F53/5,0)*5 | H53: =ROUND(E53*F53*'Расчёт'!$B$10/5,0)*5 | I53: =G53*VLOOKUP($D53,'Продукты'!$A$4:$G$34,2,FALSE)/100 | J53: =G53*VLOOKUP($D53,'Продукты'!$A$4:$G$34,3,FALSE)/100 | K53: =G53*VLOOKUP($D53,'Продукты'!$A$4:$G$34,4,FALSE)/100 | L53: =G53*VLOOKUP($D53,'Продукты'!$A$4:$G$34,5,FALSE)/100
A54: Ср | B54: Завтрак | C54: Добавка | D54: Яйцо | E54: 110 | F54: =MIN(1.7,MAX(0.65,'Расчёт'!$B$17/1884.6)) | G54: =ROUND(E54*F54/5,0)*5 | H54: =ROUND(E54*F54*'Расчёт'!$B$10/5,0)*5 | I54: =G54*VLOOKUP($D54,'Продукты'!$A$4:$G$34,2,FALSE)/100 | J54: =G54*VLOOKUP($D54,'Продукты'!$A$4:$G$34,3,FALSE)/100 | K54: =G54*VLOOKUP($D54,'Продукты'!$A$4:$G$34,4,FALSE)/100 | L54: =G54*VLOOKUP($D54,'Продукты'!$A$4:$G$34,5,FALSE)/100
A55: Ср | B55: Обед | C55: Чечевица с курицей | D55: Чечевица (сухая) | E55: 70 | F55: =MIN(1.7,MAX(0.65,'Расчёт'!$B$17/1884.6)) | G55: =ROUND(E55*F55/5,0)*5 | H55: =ROUND(E55*F55*'Расчёт'!$B$10/5,0)*5 | I55: =G55*VLOOKUP($D55,'Продукты'!$A$4:$G$34,2,FALSE)/100 | J55: =G55*VLOOKUP($D55,'Продукты'!$A$4:$G$34,3,FALSE)/100 | K55: =G55*VLOOKUP($D55,'Продукты'!$A$4:$G$34,4,FALSE)/100 | L55: =G55*VLOOKUP($D55,'Продукты'!$A$4:$G$34,5,FALSE)/100
A56: Ср | B56: Обед | C56: Чечевица с курицей | D56: Куриные бёдра/голень без кожи | E56: 150 | F56: =MIN(1.7,MAX(0.65,'Расчёт'!$B$17/1884.6)) | G56: =ROUND(E56*F56/5,0)*5 | H56: =ROUND(E56*F56*'Расчёт'!$B$10/5,0)*5 | I56: =G56*VLOOKUP($D56,'Продукты'!$A$4:$G$34,2,FALSE)/100 | J56: =G56*VLOOKUP($D56,'Продукты'!$A$4:$G$34,3,FALSE)/100 | K56: =G56*VLOOKUP($D56,'Продукты'!$A$4:$G$34,4,FALSE)/100 | L56: =G56*VLOOKUP($D56,'Продукты'!$A$4:$G$34,5,FALSE)/100
A57: Ср | B57: Обед | C57: Чечевица с курицей | D57: Морковь | E57: 50 | F57: =MIN(1.7,MAX(0.65,'Расчёт'!$B$17/1884.6)) | G57: =ROUND(E57*F57/5,0)*5 | H57: =ROUND(E57*F57*'Расчёт'!$B$10/5,0)*5 | I57: =G57*VLOOKUP($D57,'Продукты'!$A$4:$G$34,2,FALSE)/100 | J57: =G57*VLOOKUP($D57,'Продукты'!$A$4:$G$34,3,FALSE)/100 | K57: =G57*VLOOKUP($D57,'Продукты'!$A$4:$G$34,4,FALSE)/100 | L57: =G57*VLOOKUP($D57,'Продукты'!$A$4:$G$34,5,FALSE)/100
A58: Ср | B58: Обед | C58: Чечевица с курицей | D58: Лук репчатый | E58: 40 | F58: =MIN(1.7,MAX(0.65,'Расчёт'!$B$17/1884.6)) | G58: =ROUND(E58*F58/5,0)*5 | H58: =ROUND(E58*F58*'Расчёт'!$B$10/5,0)*5 | I58: =G58*VLOOKUP($D58,'Продукты'!$A$4:$G$34,2,FALSE)/100 | J58: =G58*VLOOKUP($D58,'Продукты'!$A$4:$G$34,3,FALSE)/100 | K58: =G58*VLOOKUP($D58,'Продукты'!$A$4:$G$34,4,FALSE)/100 | L58: =G58*VLOOKUP($D58,'Продукты'!$A$4:$G$34,5,FALSE)/100
A59: Ср | B59: Обед | C59: Чечевица с курицей | D59: Томатная паста | E59: 15 | F59: =MIN(1.7,MAX(0.65,'Расчёт'!$B$17/1884.6)) | G59: =ROUND(E59*F59/5,0)*5 | H59: =ROUND(E59*F59*'Расчёт'!$B$10/5,0)*5 | I59: =G59*VLOOKUP($D59,'Продукты'!$A$4:$G$34,2,FALSE)/100 | J59: =G59*VLOOKUP($D59,'Продукты'!$A$4:$G$34,3,FALSE)/100 | K59: =G59*VLOOKUP($D59,'Продукты'!$A$4:$G$34,4,FALSE)/100 | L59: =G59*VLOOKUP($D59,'Продукты'!$A$4:$G$34,5,FALSE)/100
A60: Ср | B60: Обед | C60: Чечевица с курицей | D60: Масло растительное | E60: 5 | F60: =MIN(1.7,MAX(0.65,'Расчёт'!$B$17/1884.6)) | G60: =ROUND(E60*F60/5,0)*5 | H60: =ROUND(E60*F60*'Расчёт'!$B$10/5,0)*5 | I60: =G60*VLOOKUP($D60,'Продукты'!$A$4:$G$34,2,FALSE)/100 | J60: =G60*VLOOKUP($D60,'Продукты'!$A$4:$G$34,3,FALSE)/100 | K60: =G60*VLOOKUP($D60,'Продукты'!$A$4:$G$34,4,FALSE)/100 | L60: =G60*VLOOKUP($D60,'Продукты'!$A$4:$G$34,5,FALSE)/100
A61: Ср | B61: Перекус | C61: Кефир с бананом | D61: Кефир 1% | E61: 300 | F61: =MIN(1.7,MAX(0.65,'Расчёт'!$B$17/1884.6)) | G61: =ROUND(E61*F61/5,0)*5 | H61: =ROUND(E61*F61*'Расчёт'!$B$10/5,0)*5 | I61: =G61*VLOOKUP($D61,'Продукты'!$A$4:$G$34,2,FALSE)/100 | J61: =G61*VLOOKUP($D61,'Продукты'!$A$4:$G$34,3,FALSE)/100 | K61: =G61*VLOOKUP($D61,'Продукты'!$A$4:$G$34,4,FALSE)/100 | L61: =G61*VLOOKUP($D61,'Продукты'!$A$4:$G$34,5,FALSE)/100
... A68: Ср | B68: Ужин | C68: Омлет с овощами и хлебом | D68: Хлеб цельнозерновой/ржаной | E68: 40 | F68: =MIN(1.7,MAX(0.65,'Расчёт'!$B$17/1884.6)) | G68: =ROUND(E68*F68/5,0)*5 | H68: =ROUND(E68*F68*'Расчёт'!$B$10/5,0)*5 | I68: =G68*VLOOKUP($D68,'Продукты'!$A$4:$G$34,2,FALSE)/100 | J68: =G68*VLOOKUP($D68,'Продукты'!$A$4:$G$34,3,FALSE)/100 | K68: =G68*VLOOKUP($D68,'Продукты'!$A$4:$G$34,4,FALSE)/100 | L68: =G68*VLOOKUP($D68,'Продукты'!$A$4:$G$34,5,FALSE)/100
A69: Чт | B69: Завтрак | C69: Яйца вкрутую, хлеб, творог, овощи | D69: Яйцо | E69: 110 | F69: =MIN(1.7,MAX(0.65,'Расчёт'!$B$17/2013.1)) | G69: =ROUND(E69*F69/5,0)*5 | H69: =ROUND(E69*F69*'Расчёт'!$B$10/5,0)*5 | I69: =G69*VLOOKUP($D69,'Продукты'!$A$4:$G$34,2,FALSE)/100 | J69: =G69*VLOOKUP($D69,'Продукты'!$A$4:$G$34,3,FALSE)/100 | K69: =G69*VLOOKUP($D69,'Продукты'!$A$4:$G$34,4,FALSE)/100 | L69: =G69*VLOOKUP($D69,'Продукты'!$A$4:$G$34,5,FALSE)/100
A70: Чт | B70: Завтрак | C70: Яйца вкрутую, хлеб, творог, овощи | D70: Хлеб цельнозерновой/ржаной | E70: 50 | F70: =MIN(1.7,MAX(0.65,'Расчёт'!$B$17/2013.1)) | G70: =ROUND(E70*F70/5,0)*5 | H70: =ROUND(E70*F70*'Расчёт'!$B$10/5,0)*5 | I70: =G70*VLOOKUP($D70,'Продукты'!$A$4:$G$34,2,FALSE)/100 | J70: =G70*VLOOKUP($D70,'Продукты'!$A$4:$G$34,3,FALSE)/100 | K70: =G70*VLOOKUP($D70,'Продукты'!$A$4:$G$34,4,FALSE)/100 | L70: =G70*VLOOKUP($D70,'Продукты'!$A$4:$G$34,5,FALSE)/100
A71: Чт | B71: Завтрак | C71: Яйца вкрутую, хлеб, творог, овощи | D71: Творог 5% | E71: 100 | F71: =MIN(1.7,MAX(0.65,'Расчёт'!$B$17/2013.1)) | G71: =ROUND(E71*F71/5,0)*5 | H71: =ROUND(E71*F71*'Расчёт'!$B$10/5,0)*5 | I71: =G71*VLOOKUP($D71,'Продукты'!$A$4:$G$34,2,FALSE)/100 | J71: =G71*VLOOKUP($D71,'Продукты'!$A$4:$G$34,3,FALSE)/100 | K71: =G71*VLOOKUP($D71,'Продукты'!$A$4:$G$34,4,FALSE)/100 | L71: =G71*VLOOKUP($D71,'Продукты'!$A$4:$G$34,5,FALSE)/100
A72: Чт | B72: Завтрак | C72: Яйца вкрутую, хлеб, творог, овощи | D72: Огурцы | E72: 100 | F72: =MIN(1.7,MAX(0.65,'Расчёт'!$B$17/2013.1)) | G72: =ROUND(E72*F72/5,0)*5 | H72: =ROUND(E72*F72*'Расчёт'!$B$10/5,0)*5 | I72: =G72*VLOOKUP($D72,'Продукты'!$A$4:$G$34,2,FALSE)/100 | J72: =G72*VLOOKUP($D72,'Продукты'!$A$4:$G$34,3,FALSE)/100 | K72: =G72*VLOOKUP($D72,'Продукты'!$A$4:$G$34,4,FALSE)/100 | L72: =G72*VLOOKUP($D72,'Продукты'!$A$4:$G$34,5,FALSE)/100
A73: Чт | B73: Завтрак | C73: Яйца вкрутую, хлеб, творог, овощи | D73: Помидоры | E73: 100 | F73: =MIN(1.7,MAX(0.65,'Расчёт'!$B$17/2013.1)) | G73: =ROUND(E73*F73/5,0)*5 | H73: =ROUND(E73*F73*'Расчёт'!$B$10/5,0)*5 | I73: =G73*VLOOKUP($D73,'Продукты'!$A$4:$G$34,2,FALSE)/100 | J73: =G73*VLOOKUP($D73,'Продукты'!$A$4:$G$34,3,FALSE)/100 | K73: =G73*VLOOKUP($D73,'Продукты'!$A$4:$G$34,4,FALSE)/100 | L73: =G73*VLOOKUP($D73,'Продукты'!$A$4:$G$34,5,FALSE)/100
A74: Чт | B74: Обед | C74: Макароны с куриным фаршем и томатом | D74: Макароны (сухие) | E74: 80 | F74: =MIN(1.7,MAX(0.65,'Расчёт'!$B$17/2013.1)) | G74: =ROUND(E74*F74/5,0)*5 | H74: =ROUND(E74*F74*'Расчёт'!$B$10/5,0)*5 | I74: =G74*VLOOKUP($D74,'Продукты'!$A$4:$G$34,2,FALSE)/100 | J74: =G74*VLOOKUP($D74,'Продукты'!$A$4:$G$34,3,FALSE)/100 | K74: =G74*VLOOKUP($D74,'Продукты'!$A$4:$G$34,4,FALSE)/100 | L74: =G74*VLOOKUP($D74,'Продукты'!$A$4:$G$34,5,FALSE)/100
A75: Чт | B75: Обед | C75: Макароны с куриным фаршем и томатом | D75: Куриный фарш | E75: 150 | F75: =MIN(1.7,MAX(0.65,'Расчёт'!$B$17/2013.1)) | G75: =ROUND(E75*F75/5,0)*5 | H75: =ROUND(E75*F75*'Расчёт'!$B$10/5,0)*5 | I75: =G75*VLOOKUP($D75,'Продукты'!$A$4:$G$34,2,FALSE)/100 | J75: =G75*VLOOKUP($D75,'Продукты'!$A$4:$G$34,3,FALSE)/100 | K75: =G75*VLOOKUP($D75,'Продукты'!$A$4:$G$34,4,FALSE)/100 | L75: =G75*VLOOKUP($D75,'Продукты'!$A$4:$G$34,5,FALSE)/100
A76: Чт | B76: Обед | C76: Макароны с куриным фаршем и томатом | D76: Лук репчатый | E76: 40 | F76: =MIN(1.7,MAX(0.65,'Расчёт'!$B$17/2013.1)) | G76: =ROUND(E76*F76/5,0)*5 | H76: =ROUND(E76*F76*'Расчёт'!$B$10/5,0)*5 | I76: =G76*VLOOKUP($D76,'Продукты'!$A$4:$G$34,2,FALSE)/100 | J76: =G76*VLOOKUP($D76,'Продукты'!$A$4:$G$34,3,FALSE)/100 | K76: =G76*VLOOKUP($D76,'Продукты'!$A$4:$G$34,4,FALSE)/100 | L76: =G76*VLOOKUP($D76,'Продукты'!$A$4:$G$34,5,FALSE)/100
A77: Чт | B77: Обед | C77: Макароны с куриным фаршем и томатом | D77: Томатная паста | E77: 20 | F77: =MIN(1.7,MAX(0.65,'Расчёт'!$B$17/2013.1)) | G77: =ROUND(E77*F77/5,0)*5 | H77: =ROUND(E77*F77*'Расчёт'!$B$10/5,0)*5 | I77: =G77*VLOOKUP($D77,'Продукты'!$A$4:$G$34,2,FALSE)/100 | J77: =G77*VLOOKUP($D77,'Продукты'!$A$4:$G$34,3,FALSE)/100 | K77: =G77*VLOOKUP($D77,'Продукты'!$A$4:$G$34,4,FALSE)/100 | L77: =G77*VLOOKUP($D77,'Продукты'!$A$4:$G$34,5,FALSE)/100
A78: Чт | B78: Обед | C78: Макароны с куриным фаршем и томатом | D78: Помидоры | E78: 100 | F78: =MIN(1.7,MAX(0.65,'Расчёт'!$B$17/2013.1)) | G78: =ROUND(E78*F78/5,0)*5 | H78: =ROUND(E78*F78*'Расчёт'!$B$10/5,0)*5 | I78: =G78*VLOOKUP($D78,'Продукты'!$A$4:$G$34,2,FALSE)/100 | J78: =G78*VLOOKUP($D78,'Продукты'!$A$4:$G$34,3,FALSE)/100 | K78: =G78*VLOOKUP($D78,'Продукты'!$A$4:$G$34,4,FALSE)/100 | L78: =G78*VLOOKUP($D78,'Продукты'!$A$4:$G$34,5,FALSE)/100
A79: Чт | B79: Обед | C79: Макароны с куриным фаршем и томатом | D79: Масло растительное | E79: 3 | F79: =MIN(1.7,MAX(0.65,'Расчёт'!$B$17/2013.1)) | G79: =ROUND(E79*F79/5,0)*5 | H79: =ROUND(E79*F79*'Расчёт'!$B$10/5,0)*5 | I79: =G79*VLOOKUP($D79,'Продукты'!$A$4:$G$34,2,FALSE)/100 | J79: =G79*VLOOKUP($D79,'Продукты'!$A$4:$G$34,3,FALSE)/100 | K79: =G79*VLOOKUP($D79,'Продукты'!$A$4:$G$34,4,FALSE)/100 | L79: =G79*VLOOKUP($D79,'Продукты'!$A$4:$G$34,5,FALSE)/100
A80: Чт | B80: Обед | C80: Салат айсберг с яйцом и йогуртом | D80: Салат айсберг | E80: 150 | F80: =MIN(1.7,MAX(0.65,'Расчёт'!$B$17/2013.1)) | G80: =ROUND(E80*F80/5,0)*5 | H80: =ROUND(E80*F80*'Расчёт'!$B$10/5,0)*5 | I80: =G80*VLOOKUP($D80,'Продукты'!$A$4:$G$34,2,FALSE)/100 | J80: =G80*VLOOKUP($D80,'Продукты'!$A$4:$G$34,3,FALSE)/100 | K80: =G80*VLOOKUP($D80,'Продукты'!$A$4:$G$34,4,FALSE)/100 | L80: =G80*VLOOKUP($D80,'Продукты'!$A$4:$G$34,5,FALSE)/100
... A92: Чт | B92: Ужин | C92: Гречка с яйцами и овощами | D92: Творог 5% | E92: 100 | F92: =MIN(1.7,MAX(0.65,'Расчёт'!$B$17/2013.1)) | G92: =ROUND(E92*F92/5,0)*5 | H92: =ROUND(E92*F92*'Расчёт'!$B$10/5,0)*5 | I92: =G92*VLOOKUP($D92,'Продукты'!$A$4:$G$34,2,FALSE)/100 | J92: =G92*VLOOKUP($D92,'Продукты'!$A$4:$G$34,3,FALSE)/100 | K92: =G92*VLOOKUP($D92,'Продукты'!$A$4:$G$34,4,FALSE)/100 | L92: =G92*VLOOKUP($D92,'Продукты'!$A$4:$G$34,5,FALSE)/100
A93: Пт | B93: Завтрак | C93: Пшённая каша на молоке с яблоком | D93: Пшено (сухое) | E93: 60 | F93: =MIN(1.7,MAX(0.65,'Расчёт'!$B$17/1968.5)) | G93: =ROUND(E93*F93/5,0)*5 | H93: =ROUND(E93*F93*'Расчёт'!$B$10/5,0)*5 | I93: =G93*VLOOKUP($D93,'Продукты'!$A$4:$G$34,2,FALSE)/100 | J93: =G93*VLOOKUP($D93,'Продукты'!$A$4:$G$34,3,FALSE)/100 | K93: =G93*VLOOKUP($D93,'Продукты'!$A$4:$G$34,4,FALSE)/100 | L93: =G93*VLOOKUP($D93,'Продукты'!$A$4:$G$34,5,FALSE)/100
A94: Пт | B94: Завтрак | C94: Пшённая каша на молоке с яблоком | D94: Молоко 2.5% | E94: 250 | F94: =MIN(1.7,MAX(0.65,'Расчёт'!$B$17/1968.5)) | G94: =ROUND(E94*F94/5,0)*5 | H94: =ROUND(E94*F94*'Расчёт'!$B$10/5,0)*5 | I94: =G94*VLOOKUP($D94,'Продукты'!$A$4:$G$34,2,FALSE)/100 | J94: =G94*VLOOKUP($D94,'Продукты'!$A$4:$G$34,3,FALSE)/100 | K94: =G94*VLOOKUP($D94,'Продукты'!$A$4:$G$34,4,FALSE)/100 | L94: =G94*VLOOKUP($D94,'Продукты'!$A$4:$G$34,5,FALSE)/100
A95: Пт | B95: Завтрак | C95: Пшённая каша на молоке с яблоком | D95: Яблоки | E95: 120 | F95: =MIN(1.7,MAX(0.65,'Расчёт'!$B$17/1968.5)) | G95: =ROUND(E95*F95/5,0)*5 | H95: =ROUND(E95*F95*'Расчёт'!$B$10/5,0)*5 | I95: =G95*VLOOKUP($D95,'Продукты'!$A$4:$G$34,2,FALSE)/100 | J95: =G95*VLOOKUP($D95,'Продукты'!$A$4:$G$34,3,FALSE)/100 | K95: =G95*VLOOKUP($D95,'Продукты'!$A$4:$G$34,4,FALSE)/100 | L95: =G95*VLOOKUP($D95,'Продукты'!$A$4:$G$34,5,FALSE)/100
A96: Пт | B96: Завтрак | C96: Пшённая каша на молоке с яблоком | D96: Творог 5% | E96: 80 | F96: =MIN(1.7,MAX(0.65,'Расчёт'!$B$17/1968.5)) | G96: =ROUND(E96*F96/5,0)*5 | H96: =ROUND(E96*F96*'Расчёт'!$B$10/5,0)*5 | I96: =G96*VLOOKUP($D96,'Продукты'!$A$4:$G$34,2,FALSE)/100 | J96: =G96*VLOOKUP($D96,'Продукты'!$A$4:$G$34,3,FALSE)/100 | K96: =G96*VLOOKUP($D96,'Продукты'!$A$4:$G$34,4,FALSE)/100 | L96: =G96*VLOOKUP($D96,'Продукты'!$A$4:$G$34,5,FALSE)/100
A97: Пт | B97: Завтрак | C97: Добавка | D97: Яйцо | E97: 110 | F97: =MIN(1.7,MAX(0.65,'Расчёт'!$B$17/1968.5)) | G97: =ROUND(E97*F97/5,0)*5 | H97: =ROUND(E97*F97*'Расчёт'!$B$10/5,0)*5 | I97: =G97*VLOOKUP($D97,'Продукты'!$A$4:$G$34,2,FALSE)/100 | J97: =G97*VLOOKUP($D97,'Продукты'!$A$4:$G$34,3,FALSE)/100 | K97: =G97*VLOOKUP($D97,'Продукты'!$A$4:$G$34,4,FALSE)/100 | L97: =G97*VLOOKUP($D97,'Продукты'!$A$4:$G$34,5,FALSE)/100
A98: Пт | B98: Обед | C98: Красная рыба с картофелем (раз в неделю) | D98: Красная рыба (горбуша, форель) | E98: 150 | F98: =MIN(1.7,MAX(0.65,'Расчёт'!$B$17/1968.5)) | G98: =ROUND(E98*F98/5,0)*5 | H98: =ROUND(E98*F98*'Расчёт'!$B$10/5,0)*5 | I98: =G98*VLOOKUP($D98,'Продукты'!$A$4:$G$34,2,FALSE)/100 | J98: =G98*VLOOKUP($D98,'Продукты'!$A$4:$G$34,3,FALSE)/100 | K98: =G98*VLOOKUP($D98,'Продукты'!$A$4:$G$34,4,FALSE)/100 | L98: =G98*VLOOKUP($D98,'Продукты'!$A$4:$G$34,5,FALSE)/100
A99: Пт | B99: Обед | C99: Красная рыба с картофелем (раз в неделю) | D99: Картофель | E99: 250 | F99: =MIN(1.7,MAX(0.65,'Расчёт'!$B$17/1968.5)) | G99: =ROUND(E99*F99/5,0)*5 | H99: =ROUND(E99*F99*'Расчёт'!$B$10/5,0)*5 | I99: =G99*VLOOKUP($D99,'Продукты'!$A$4:$G$34,2,FALSE)/100 | J99: =G99*VLOOKUP($D99,'Продукты'!$A$4:$G$34,3,FALSE)/100 | K99: =G99*VLOOKUP($D99,'Продукты'!$A$4:$G$34,4,FALSE)/100 | L99: =G99*VLOOKUP($D99,'Продукты'!$A$4:$G$34,5,FALSE)/100
A100: Пт | B100: Обед | C100: Красная рыба с картофелем (раз в неделю) | D100: Масло растительное | E100: 3 | F100: =MIN(1.7,MAX(0.65,'Расчёт'!$B$17/1968.5)) | G100: =ROUND(E100*F100/5,0)*5 | H100: =ROUND(E100*F100*'Расчёт'!$B$10/5,0)*5 | I100: =G100*VLOOKUP($D100,'Продукты'!$A$4:$G$34,2,FALSE)/100 | J100: =G100*VLOOKUP($D100,'Продукты'!$A$4:$G$34,3,FALSE)/100 | K100: =G100*VLOOKUP($D100,'Продукты'!$A$4:$G$34,4,FALSE)/100 | L100: =G100*VLOOKUP($D100,'Продукты'!$A$4:$G$34,5,FALSE)/100
A101: Пт | B101: Обед | C101: Красная рыба с картофелем (раз в неделю) | D101: Огурцы | E101: 100 | F101: =MIN(1.7,MAX(0.65,'Расчёт'!$B$17/1968.5)) | G101: =ROUND(E101*F101/5,0)*5 | H101: =ROUND(E101*F101*'Расчёт'!$B$10/5,0)*5 | I101: =G101*VLOOKUP($D101,'Продукты'!$A$4:$G$34,2,FALSE)/100 | J101: =G101*VLOOKUP($D101,'Продукты'!$A$4:$G$34,3,FALSE)/100 | K101: =G101*VLOOKUP($D101,'Продукты'!$A$4:$G$34,4,FALSE)/100 | L101: =G101*VLOOKUP($D101,'Продукты'!$A$4:$G$34,5,FALSE)/100
A102: Пт | B102: Обед | C102: Красная рыба с картофелем (раз в неделю) | D102: Помидоры | E102: 80 | F102: =MIN(1.7,MAX(0.65,'Расчёт'!$B$17/1968.5)) | G102: =ROUND(E102*F102/5,0)*5 | H102: =ROUND(E102*F102*'Расчёт'!$B$10/5,0)*5 | I102: =G102*VLOOKUP($D102,'Продукты'!$A$4:$G$34,2,FALSE)/100 | J102: =G102*VLOOKUP($D102,'Продукты'!$A$4:$G$34,3,FALSE)/100 | K102: =G102*VLOOKUP($D102,'Продукты'!$A$4:$G$34,4,FALSE)/100 | L102: =G102*VLOOKUP($D102,'Продукты'!$A$4:$G$34,5,FALSE)/100
A103: Пт | B103: Перекус | C103: Кефир с бананом | D103: Кефир 1% | E103: 300 | F103: =MIN(1.7,MAX(0.65,'Расчёт'!$B$17/1968.5)) | G103: =ROUND(E103*F103/5,0)*5 | H103: =ROUND(E103*F103*'Расчёт'!$B$10/5,0)*5 | I103: =G103*VLOOKUP($D103,'Продукты'!$A$4:$G$34,2,FALSE)/100 | J103: =G103*VLOOKUP($D103,'Продукты'!$A$4:$G$34,3,FALSE)/100 | K103: =G103*VLOOKUP($D103,'Продукты'!$A$4:$G$34,4,FALSE)/100 | L103: =G103*VLOOKUP($D103,'Продукты'!$A$4:$G$34,5,FALSE)/100
A104: Пт | B104: Перекус | C104: Кефир с бананом | D104: Бананы (очищенные) | E104: 110 | F104: =MIN(1.7,MAX(0.65,'Расчёт'!$B$17/1968.5)) | G104: =ROUND(E104*F104/5,0)*5 | H104: =ROUND(E104*F104*'Расчёт'!$B$10/5,0)*5 | I104: =G104*VLOOKUP($D104,'Продукты'!$A$4:$G$34,2,FALSE)/100 | J104: =G104*VLOOKUP($D104,'Продукты'!$A$4:$G$34,3,FALSE)/100 | K104: =G104*VLOOKUP($D104,'Продукты'!$A$4:$G$34,4,FALSE)/100 | L104: =G104*VLOOKUP($D104,'Продукты'!$A$4:$G$34,5,FALSE)/100
... A111: Пт | B111: Ужин | C111: Перловка с курицей и овощами | D111: Масло растительное | E111: 5 | F111: =MIN(1.7,MAX(0.65,'Расчёт'!$B$17/1968.5)) | G111: =ROUND(E111*F111/5,0)*5 | H111: =ROUND(E111*F111*'Расчёт'!$B$10/5,0)*5 | I111: =G111*VLOOKUP($D111,'Продукты'!$A$4:$G$34,2,FALSE)/100 | J111: =G111*VLOOKUP($D111,'Продукты'!$A$4:$G$34,3,FALSE)/100 | K111: =G111*VLOOKUP($D111,'Продукты'!$A$4:$G$34,4,FALSE)/100 | L111: =G111*VLOOKUP($D111,'Продукты'!$A$4:$G$34,5,FALSE)/100
A112: Сб | B112: Завтрак | C112: Яйца вкрутую, хлеб, творог, овощи | D112: Яйцо | E112: 110 | F112: =MIN(1.7,MAX(0.65,'Расчёт'!$B$17/1850.1)) | G112: =ROUND(E112*F112/5,0)*5 | H112: =ROUND(E112*F112*'Расчёт'!$B$10/5,0)*5 | I112: =G112*VLOOKUP($D112,'Продукты'!$A$4:$G$34,2,FALSE)/100 | J112: =G112*VLOOKUP($D112,'Продукты'!$A$4:$G$34,3,FALSE)/100 | K112: =G112*VLOOKUP($D112,'Продукты'!$A$4:$G$34,4,FALSE)/100 | L112: =G112*VLOOKUP($D112,'Продукты'!$A$4:$G$34,5,FALSE)/100
A113: Сб | B113: Завтрак | C113: Яйца вкрутую, хлеб, творог, овощи | D113: Хлеб цельнозерновой/ржаной | E113: 50 | F113: =MIN(1.7,MAX(0.65,'Расчёт'!$B$17/1850.1)) | G113: =ROUND(E113*F113/5,0)*5 | H113: =ROUND(E113*F113*'Расчёт'!$B$10/5,0)*5 | I113: =G113*VLOOKUP($D113,'Продукты'!$A$4:$G$34,2,FALSE)/100 | J113: =G113*VLOOKUP($D113,'Продукты'!$A$4:$G$34,3,FALSE)/100 | K113: =G113*VLOOKUP($D113,'Продукты'!$A$4:$G$34,4,FALSE)/100 | L113: =G113*VLOOKUP($D113,'Продукты'!$A$4:$G$34,5,FALSE)/100
A114: Сб | B114: Завтрак | C114: Яйца вкрутую, хлеб, творог, овощи | D114: Творог 5% | E114: 100 | F114: =MIN(1.7,MAX(0.65,'Расчёт'!$B$17/1850.1)) | G114: =ROUND(E114*F114/5,0)*5 | H114: =ROUND(E114*F114*'Расчёт'!$B$10/5,0)*5 | I114: =G114*VLOOKUP($D114,'Продукты'!$A$4:$G$34,2,FALSE)/100 | J114: =G114*VLOOKUP($D114,'Продукты'!$A$4:$G$34,3,FALSE)/100 | K114: =G114*VLOOKUP($D114,'Продукты'!$A$4:$G$34,4,FALSE)/100 | L114: =G114*VLOOKUP($D114,'Продукты'!$A$4:$G$34,5,FALSE)/100
A115: Сб | B115: Завтрак | C115: Яйца вкрутую, хлеб, творог, овощи | D115: Огурцы | E115: 100 | F115: =MIN(1.7,MAX(0.65,'Расчёт'!$B$17/1850.1)) | G115: =ROUND(E115*F115/5,0)*5 | H115: =ROUND(E115*F115*'Расчёт'!$B$10/5,0)*5 | I115: =G115*VLOOKUP($D115,'Продукты'!$A$4:$G$34,2,FALSE)/100 | J115: =G115*VLOOKUP($D115,'Продукты'!$A$4:$G$34,3,FALSE)/100 | K115: =G115*VLOOKUP($D115,'Продукты'!$A$4:$G$34,4,FALSE)/100 | L115: =G115*VLOOKUP($D115,'Продукты'!$A$4:$G$34,5,FALSE)/100
A116: Сб | B116: Завтрак | C116: Яйца вкрутую, хлеб, творог, овощи | D116: Помидоры | E116: 100 | F116: =MIN(1.7,MAX(0.65,'Расчёт'!$B$17/1850.1)) | G116: =ROUND(E116*F116/5,0)*5 | H116: =ROUND(E116*F116*'Расчёт'!$B$10/5,0)*5 | I116: =G116*VLOOKUP($D116,'Продукты'!$A$4:$G$34,2,FALSE)/100 | J116: =G116*VLOOKUP($D116,'Продукты'!$A$4:$G$34,3,FALSE)/100 | K116: =G116*VLOOKUP($D116,'Продукты'!$A$4:$G$34,4,FALSE)/100 | L116: =G116*VLOOKUP($D116,'Продукты'!$A$4:$G$34,5,FALSE)/100
A117: Сб | B117: Обед | C117: Курица в кефире с картофелем | D117: Куриная грудка | E117: 160 | F117: =MIN(1.7,MAX(0.65,'Расчёт'!$B$17/1850.1)) | G117: =ROUND(E117*F117/5,0)*5 | H117: =ROUND(E117*F117*'Расчёт'!$B$10/5,0)*5 | I117: =G117*VLOOKUP($D117,'Продукты'!$A$4:$G$34,2,FALSE)/100 | J117: =G117*VLOOKUP($D117,'Продукты'!$A$4:$G$34,3,FALSE)/100 | K117: =G117*VLOOKUP($D117,'Продукты'!$A$4:$G$34,4,FALSE)/100 | L117: =G117*VLOOKUP($D117,'Продукты'!$A$4:$G$34,5,FALSE)/100
A118: Сб | B118: Обед | C118: Курица в кефире с картофелем | D118: Кефир 1% | E118: 100 | F118: =MIN(1.7,MAX(0.65,'Расчёт'!$B$17/1850.1)) | G118: =ROUND(E118*F118/5,0)*5 | H118: =ROUND(E118*F118*'Расчёт'!$B$10/5,0)*5 | I118: =G118*VLOOKUP($D118,'Продукты'!$A$4:$G$34,2,FALSE)/100 | J118: =G118*VLOOKUP($D118,'Продукты'!$A$4:$G$34,3,FALSE)/100 | K118: =G118*VLOOKUP($D118,'Продукты'!$A$4:$G$34,4,FALSE)/100 | L118: =G118*VLOOKUP($D118,'Продукты'!$A$4:$G$34,5,FALSE)/100
A119: Сб | B119: Обед | C119: Курица в кефире с картофелем | D119: Картофель | E119: 250 | F119: =MIN(1.7,MAX(0.65,'Расчёт'!$B$17/1850.1)) | G119: =ROUND(E119*F119/5,0)*5 | H119: =ROUND(E119*F119*'Расчёт'!$B$10/5,0)*5 | I119: =G119*VLOOKUP($D119,'Продукты'!$A$4:$G$34,2,FALSE)/100 | J119: =G119*VLOOKUP($D119,'Продукты'!$A$4:$G$34,3,FALSE)/100 | K119: =G119*VLOOKUP($D119,'Продукты'!$A$4:$G$34,4,FALSE)/100 | L119: =G119*VLOOKUP($D119,'Продукты'!$A$4:$G$34,5,FALSE)/100
A120: Сб | B120: Обед | C120: Курица в кефире с картофелем | D120: Лук репчатый | E120: 30 | F120: =MIN(1.7,MAX(0.65,'Расчёт'!$B$17/1850.1)) | G120: =ROUND(E120*F120/5,0)*5 | H120: =ROUND(E120*F120*'Расчёт'!$B$10/5,0)*5 | I120: =G120*VLOOKUP($D120,'Продукты'!$A$4:$G$34,2,FALSE)/100 | J120: =G120*VLOOKUP($D120,'Продукты'!$A$4:$G$34,3,FALSE)/100 | K120: =G120*VLOOKUP($D120,'Продукты'!$A$4:$G$34,4,FALSE)/100 | L120: =G120*VLOOKUP($D120,'Продукты'!$A$4:$G$34,5,FALSE)/100
A121: Сб | B121: Обед | C121: Курица в кефире с картофелем | D121: Масло растительное | E121: 3 | F121: =MIN(1.7,MAX(0.65,'Расчёт'!$B$17/1850.1)) | G121: =ROUND(E121*F121/5,0)*5 | H121: =ROUND(E121*F121*'Расчёт'!$B$10/5,0)*5 | I121: =G121*VLOOKUP($D121,'Продукты'!$A$4:$G$34,2,FALSE)/100 | J121: =G121*VLOOKUP($D121,'Продукты'!$A$4:$G$34,3,FALSE)/100 | K121: =G121*VLOOKUP($D121,'Продукты'!$A$4:$G$34,4,FALSE)/100 | L121: =G121*VLOOKUP($D121,'Продукты'!$A$4:$G$34,5,FALSE)/100
A122: Сб | B122: Обед | C122: Курица в кефире с картофелем | D122: Капуста белокочанная | E122: 100 | F122: =MIN(1.7,MAX(0.65,'Расчёт'!$B$17/1850.1)) | G122: =ROUND(E122*F122/5,0)*5 | H122: =ROUND(E122*F122*'Расчёт'!$B$10/5,0)*5 | I122: =G122*VLOOKUP($D122,'Продукты'!$A$4:$G$34,2,FALSE)/100 | J122: =G122*VLOOKUP($D122,'Продукты'!$A$4:$G$34,3,FALSE)/100 | K122: =G122*VLOOKUP($D122,'Продукты'!$A$4:$G$34,4,FALSE)/100 | L122: =G122*VLOOKUP($D122,'Продукты'!$A$4:$G$34,5,FALSE)/100
A123: Сб | B123: Перекус | C123: Творог с яблоком | D123: Творог 5% | E123: 150 | F123: =MIN(1.7,MAX(0.65,'Расчёт'!$B$17/1850.1)) | G123: =ROUND(E123*F123/5,0)*5 | H123: =ROUND(E123*F123*'Расчёт'!$B$10/5,0)*5 | I123: =G123*VLOOKUP($D123,'Продукты'!$A$4:$G$34,2,FALSE)/100 | J123: =G123*VLOOKUP($D123,'Продукты'!$A$4:$G$34,3,FALSE)/100 | K123: =G123*VLOOKUP($D123,'Продукты'!$A$4:$G$34,4,FALSE)/100 | L123: =G123*VLOOKUP($D123,'Продукты'!$A$4:$G$34,5,FALSE)/100
... A130: Сб | B130: Ужин | C130: Добавка | D130: Хлеб цельнозерновой/ржаной | E130: 60 | F130: =MIN(1.7,MAX(0.65,'Расчёт'!$B$17/1850.1)) | G130: =ROUND(E130*F130/5,0)*5 | H130: =ROUND(E130*F130*'Расчёт'!$B$10/5,0)*5 | I130: =G130*VLOOKUP($D130,'Продукты'!$A$4:$G$34,2,FALSE)/100 | J130: =G130*VLOOKUP($D130,'Продукты'!$A$4:$G$34,3,FALSE)/100 | K130: =G130*VLOOKUP($D130,'Продукты'!$A$4:$G$34,4,FALSE)/100 | L130: =G130*VLOOKUP($D130,'Продукты'!$A$4:$G$34,5,FALSE)/100
A131: Вс | B131: Завтрак | C131: Овсянка на молоке с бананом | D131: Овсяные хлопья (сухие) | E131: 70 | F131: =MIN(1.7,MAX(0.65,'Расчёт'!$B$17/1971.9)) | G131: =ROUND(E131*F131/5,0)*5 | H131: =ROUND(E131*F131*'Расчёт'!$B$10/5,0)*5 | I131: =G131*VLOOKUP($D131,'Продукты'!$A$4:$G$34,2,FALSE)/100 | J131: =G131*VLOOKUP($D131,'Продукты'!$A$4:$G$34,3,FALSE)/100 | K131: =G131*VLOOKUP($D131,'Продукты'!$A$4:$G$34,4,FALSE)/100 | L131: =G131*VLOOKUP($D131,'Продукты'!$A$4:$G$34,5,FALSE)/100
A132: Вс | B132: Завтрак | C132: Овсянка на молоке с бананом | D132: Молоко 2.5% | E132: 200 | F132: =MIN(1.7,MAX(0.65,'Расчёт'!$B$17/1971.9)) | G132: =ROUND(E132*F132/5,0)*5 | H132: =ROUND(E132*F132*'Расчёт'!$B$10/5,0)*5 | I132: =G132*VLOOKUP($D132,'Продукты'!$A$4:$G$34,2,FALSE)/100 | J132: =G132*VLOOKUP($D132,'Продукты'!$A$4:$G$34,3,FALSE)/100 | K132: =G132*VLOOKUP($D132,'Продукты'!$A$4:$G$34,4,FALSE)/100 | L132: =G132*VLOOKUP($D132,'Продукты'!$A$4:$G$34,5,FALSE)/100
A133: Вс | B133: Завтрак | C133: Овсянка на молоке с бананом | D133: Бананы (очищенные) | E133: 100 | F133: =MIN(1.7,MAX(0.65,'Расчёт'!$B$17/1971.9)) | G133: =ROUND(E133*F133/5,0)*5 | H133: =ROUND(E133*F133*'Расчёт'!$B$10/5,0)*5 | I133: =G133*VLOOKUP($D133,'Продукты'!$A$4:$G$34,2,FALSE)/100 | J133: =G133*VLOOKUP($D133,'Продукты'!$A$4:$G$34,3,FALSE)/100 | K133: =G133*VLOOKUP($D133,'Продукты'!$A$4:$G$34,4,FALSE)/100 | L133: =G133*VLOOKUP($D133,'Продукты'!$A$4:$G$34,5,FALSE)/100
A134: Вс | B134: Завтрак | C134: Овсянка на молоке с бананом | D134: Грецкие орехи | E134: 10 | F134: =MIN(1.7,MAX(0.65,'Расчёт'!$B$17/1971.9)) | G134: =ROUND(E134*F134/5,0)*5 | H134: =ROUND(E134*F134*'Расчёт'!$B$10/5,0)*5 | I134: =G134*VLOOKUP($D134,'Продукты'!$A$4:$G$34,2,FALSE)/100 | J134: =G134*VLOOKUP($D134,'Продукты'!$A$4:$G$34,3,FALSE)/100 | K134: =G134*VLOOKUP($D134,'Продукты'!$A$4:$G$34,4,FALSE)/100 | L134: =G134*VLOOKUP($D134,'Продукты'!$A$4:$G$34,5,FALSE)/100
A135: Вс | B135: Завтрак | C135: Добавка | D135: Яйцо | E135: 110 | F135: =MIN(1.7,MAX(0.65,'Расчёт'!$B$17/1971.9)) | G135: =ROUND(E135*F135/5,0)*5 | H135: =ROUND(E135*F135*'Расчёт'!$B$10/5,0)*5 | I135: =G135*VLOOKUP($D135,'Продукты'!$A$4:$G$34,2,FALSE)/100 | J135: =G135*VLOOKUP($D135,'Продукты'!$A$4:$G$34,3,FALSE)/100 | K135: =G135*VLOOKUP($D135,'Продукты'!$A$4:$G$34,4,FALSE)/100 | L135: =G135*VLOOKUP($D135,'Продукты'!$A$4:$G$34,5,FALSE)/100
A136: Вс | B136: Обед | C136: Куриный суп с картофелем и пшеном | D136: Куриные бёдра/голень без кожи | E136: 170 | F136: =MIN(1.7,MAX(0.65,'Расчёт'!$B$17/1971.9)) | G136: =ROUND(E136*F136/5,0)*5 | H136: =ROUND(E136*F136*'Расчёт'!$B$10/5,0)*5 | I136: =G136*VLOOKUP($D136,'Продукты'!$A$4:$G$34,2,FALSE)/100 | J136: =G136*VLOOKUP($D136,'Продукты'!$A$4:$G$34,3,FALSE)/100 | K136: =G136*VLOOKUP($D136,'Продукты'!$A$4:$G$34,4,FALSE)/100 | L136: =G136*VLOOKUP($D136,'Продукты'!$A$4:$G$34,5,FALSE)/100
A137: Вс | B137: Обед | C137: Куриный суп с картофелем и пшеном | D137: Картофель | E137: 200 | F137: =MIN(1.7,MAX(0.65,'Расчёт'!$B$17/1971.9)) | G137: =ROUND(E137*F137/5,0)*5 | H137: =ROUND(E137*F137*'Расчёт'!$B$10/5,0)*5 | I137: =G137*VLOOKUP($D137,'Продукты'!$A$4:$G$34,2,FALSE)/100 | J137: =G137*VLOOKUP($D137,'Продукты'!$A$4:$G$34,3,FALSE)/100 | K137: =G137*VLOOKUP($D137,'Продукты'!$A$4:$G$34,4,FALSE)/100 | L137: =G137*VLOOKUP($D137,'Продукты'!$A$4:$G$34,5,FALSE)/100
A138: Вс | B138: Обед | C138: Куриный суп с картофелем и пшеном | D138: Пшено (сухое) | E138: 30 | F138: =MIN(1.7,MAX(0.65,'Расчёт'!$B$17/1971.9)) | G138: =ROUND(E138*F138/5,0)*5 | H138: =ROUND(E138*F138*'Расчёт'!$B$10/5,0)*5 | I138: =G138*VLOOKUP($D138,'Продукты'!$A$4:$G$34,2,FALSE)/100 | J138: =G138*VLOOKUP($D138,'Продукты'!$A$4:$G$34,3,FALSE)/100 | K138: =G138*VLOOKUP($D138,'Продукты'!$A$4:$G$34,4,FALSE)/100 | L138: =G138*VLOOKUP($D138,'Продукты'!$A$4:$G$34,5,FALSE)/100
A139: Вс | B139: Обед | C139: Куриный суп с картофелем и пшеном | D139: Морковь | E139: 50 | F139: =MIN(1.7,MAX(0.65,'Расчёт'!$B$17/1971.9)) | G139: =ROUND(E139*F139/5,0)*5 | H139: =ROUND(E139*F139*'Расчёт'!$B$10/5,0)*5 | I139: =G139*VLOOKUP($D139,'Продукты'!$A$4:$G$34,2,FALSE)/100 | J139: =G139*VLOOKUP($D139,'Продукты'!$A$4:$G$34,3,FALSE)/100 | K139: =G139*VLOOKUP($D139,'Продукты'!$A$4:$G$34,4,FALSE)/100 | L139: =G139*VLOOKUP($D139,'Продукты'!$A$4:$G$34,5,FALSE)/100
A140: Вс | B140: Обед | C140: Куриный суп с картофелем и пшеном | D140: Лук репчатый | E140: 40 | F140: =MIN(1.7,MAX(0.65,'Расчёт'!$B$17/1971.9)) | G140: =ROUND(E140*F140/5,0)*5 | H140: =ROUND(E140*F140*'Расчёт'!$B$10/5,0)*5 | I140: =G140*VLOOKUP($D140,'Продукты'!$A$4:$G$34,2,FALSE)/100 | J140: =G140*VLOOKUP($D140,'Продукты'!$A$4:$G$34,3,FALSE)/100 | K140: =G140*VLOOKUP($D140,'Продукты'!$A$4:$G$34,4,FALSE)/100 | L140: =G140*VLOOKUP($D140,'Продукты'!$A$4:$G$34,5,FALSE)/100
A141: Вс | B141: Обед | C141: Куриный суп с картофелем и пшеном | D141: Масло растительное | E141: 3 | F141: =MIN(1.7,MAX(0.65,'Расчёт'!$B$17/1971.9)) | G141: =ROUND(E141*F141/5,0)*5 | H141: =ROUND(E141*F141*'Расчёт'!$B$10/5,0)*5 | I141: =G141*VLOOKUP($D141,'Продукты'!$A$4:$G$34,2,FALSE)/100 | J141: =G141*VLOOKUP($D141,'Продукты'!$A$4:$G$34,3,FALSE)/100 | K141: =G141*VLOOKUP($D141,'Продукты'!$A$4:$G$34,4,FALSE)/100 | L141: =G141*VLOOKUP($D141,'Продукты'!$A$4:$G$34,5,FALSE)/100
...

Sheet Рецепты
A1: Рецепты
A2: Продукты даны на 1 порцию (твою). Для жены умножь на долю из листа «Расчёт».
A4: Блюдо | B4: Приём | C4: Время | D4: Ккал | E4: Белок | F4: Жиры | G4: Углев. | H4: Продукты на 1 порцию | I4: Как готовить | J4: Совет
A5: Овсянка на молоке с бананом | B5: Завтрак | C5: 10 мин | D5: 515 | E5: 17 | F5: 16 | G5: 73 | H5: • Овсяные хлопья (сухие): 70 г • Молоко 2.5%: 200 г • Бананы (очищенные): 100 г (≈1 шт) • Грецкие орехи: 10 г | I5: 1. Залей хлопья горячим молоком, вари 5–7 минут на слабом огне. 2. Нарежь банан, добавь в тарелку, сверху крошёные орехи. 3. Для двоих вари в одной кастрюле: хлопья и молоко умножь на 2. | J5: Не сладкая, потому что вся сладость от банана. Сахар и сиропы не добавляй.
A6: Омлет с овощами и хлебом | B6: Завтрак/ужин | C6: 10 мин | D6: 414 | E6: 25 | F6: 25 | G6: 23 | H6: • Яйцо: 165 г (≈3 шт) • Помидоры: 80 г • Лук репчатый: 20 г • Масло растительное: 5 г • Хлеб цельнозерновой/ржаной: 40 г | I6: 1. Взбей яйца вилкой с щепоткой соли. 2. Лук и помидор нарежь, быстро обжарь на масле 2–3 минуты. 3. Залей яйцами, накрой крышкой на 4–5 минут на слабом огне. 4. Подавай с куском хлеба. | J6: 3 яйца на порцию. Если боишься холестерина, возьми 2 яйца и добавь 100 г творога сбоку.
A7: Яйца вкрутую, хлеб, творог, овощи | B7: Завтрак | C7: 12 мин | D7: 436 | E7: 36 | F7: 19 | G7: 31 | H7: • Яйцо: 110 г (≈2 шт) • Хлеб цельнозерновой/ржаной: 50 г • Творог 5%: 100 г • Огурцы: 100 г • Помидоры: 100 г | I7: 1. Яйца вари 9 минут с момента закипания, остуди под холодной водой. 2. Творог намажь на хлеб, сверху овощи ломтиками. 3. Яйца подавай рядом. | J7: Быстрый завтрак. Яйца можно сварить сразу на 3 дня и хранить в холодильнике.
A8: Пшённая каша на молоке с яблоком | B8: Завтрак | C8: 25 мин | D8: 488 | E8: 28 | F8: 13 | G8: 66 | H8: • Пшено (сухое): 60 г • Молоко 2.5%: 250 г • Яблоки: 120 г (≈1 шт) • Творог 5%: 80 г | I8: 1. Пшено промой горячей водой 2–3 раза, чтобы ушла горечь. 2. Залей молоком и половиной стакана воды, вари 20 минут, помешивая. 3. Добавь тёртое яблоко и сверху ложку творога. | J8: Дешёвая каша, долго держит сытость.
A9: Овсянка с йогуртом и яблоком | B9: Завтрак | C9: 10 мин | D9: 514 | E9: 32 | F9: 15 | G9: 62 | H9: • Овсяные хлопья (сухие): 70 г • Йогурт натуральный: 150 г • Яблоки: 100 г (≈1 шт) • Творог 5%: 100 г | I9: 1. Залей хлопья кипятком на 5 минут, слей лишнюю воду. 2. Смешай с йогуртом, добавь яблоко кубиками. 3. Творог подай отдельно или смешай. | J9: Можно сделать с вечера: залить хлопья йогуртом и оставить в холодильнике.
A10: Гречка с тушёной курицей и капустой | B10: Обед | C10: 35 мин | D10: 581 | E10: 45 | F10: 19 | G10: 56 | H10: • Гречка (сухая): 70 г • Куриные бёдра/голень без кожи: 170 г • Капуста белокочанная: 150 г • Морковь: 40 г • Лук репчатый: 30 г • Масло растительное: 5 г | I10: 1. Гречку промой, залей водой 1:2, вари под крышкой 15 минут. 2. Лук и морковь обжарь 3 минуты на масле, добавь кусочки курицы. 3. Добавь капусту, немного воды, туши под крышкой 15–20 минут. 4. Подавай вместе. | J10: Готовь сразу на 2 дня: курицу с капустой можно разогревать.
A11: Рис с запечёнными бёдрами и овощами | B11: Обед/ужин | C11: 45 мин | D11: 579 | E11: 41 | F11: 17 | G11: 64 | H11: • Рис (сухой): 70 г • Куриные бёдра/голень без кожи: 180 г • Морковь: 50 г • Лук репчатый: 30 г • Помидоры: 100 г • Масло растительное: 5 г | I11: 1. Бёдра сними с кожи, посоли, добавь паприку или чеснок. 2. Выложи на противень с морковью и луком, запекай 35 минут при 200 °C. 3. Рис свари отдельно 15 минут (вода 1:2). 4. Помидоры нарежь свежими в тарелку. | J11: Кожа даёт лишние 100–150 ккал, поэтому её снимаем.
A12: Перловка с курицей и овощами | B12: Обед/ужин | C12: 50 мин | D12: 548 | E12: 41 | F12: 17 | G12: 61 | H12: • Перловка (сухая): 70 г • Куриные бёдра/голень без кожи: 170 г • Морковь: 50 г • Лук репчатый: 40 г • Помидоры: 80 г • Масло растительное: 5 г | I12: 1. Перловку замочи на 2–3 часа или на ночь, вари 35–40 минут. 2. Курицу, лук и морковь потуши 20 минут с водой. 3. Смешай с кашей, добавь томаты. | J12: Самая дешёвая крупа. Замачивание сильно ускоряет варку.
A13: Минтай с картофелем, запечённые | B13: Обед/ужин | C13: 40 мин | D13: 490 | E13: 41 | F13: 11 | G13: 53 | H13: • Белая рыба (минтай, хек): 200 г • Картофель: 300 г • Масло растительное: 8 г • Лук репчатый: 30 г • Огурцы: 100 г | I13: 1. Картофель нарежь дольками, смешай с маслом и солью, запекай 20 минут при 200 °C. 2. Добавь рыбу и лук, запекай ещё 15 минут. 3. Огурец подай свежим. | J13: Минтай дешёвый и постный. Размораживай в холодильнике, не в горячей воде.
A14: Красная рыба с картофелем (раз в неделю) | B14: Обед/ужин | C14: 30 мин | D14: 476 | E14: 37 | F14: 16 | G14: 45 | H14: • Красная рыба (горбуша, форель): 150 г • Картофель: 250 г • Масло растительное: 3 г • Огурцы: 100 г • Помидоры: 80 г | I14: 1. Рыбу посоли, сбрызни лимоном, заверни в фольгу. 2. Запекай 20 минут при 200 °C вместе с картофелем. 3. Подавай с овощами. | J14: Жирные омега-3 полезны для суставов и сердца. Одного раза в неделю достаточно.
A15: Чечевица с курицей | B15: Обед | C15: 35 мин | D15: 500 | E15: 47 | F15: 16 | G15: 42 | H15: • Чечевица (сухая): 70 г • Куриные бёдра/голень без кожи: 150 г • Морковь: 50 г • Лук репчатый: 40 г • Томатная паста: 15 г • Масло растительное: 5 г | I15: 1. Чечевицу промой, вари 20 минут без замачивания. 2. Лук с морковью обжарь с томатной пастой 3 минуты. 3. Добавь курицу кусочками, туши 12 минут, смешай с чечевицей. | J15: Бобовые дают клетчатку и белок за копейки.
A16: Макароны с куриным фаршем и томатом | B16: Обед/ужин | C16: 30 мин | D16: 574 | E16: 38 | F16: 16 | G16: 68 | H16: • Макароны (сухие): 80 г • Куриный фарш: 150 г • Лук репчатый: 40 г • Томатная паста: 20 г • Помидоры: 100 г • Масло растительное: 3 г | I16: 1. Лук обжарь, добавь фарш и жарь 8 минут, разбивая комочки. 2. Добавь томатную пасту, помидоры и немного воды, туши 10 минут. 3. Макароны вари на 1 минуту меньше, чем на пачке. | J16: Макароны выбирай из твёрдых сортов (на упаковке «группа А»).
... A25: Гречка с яйцами и овощами | B25: Ужин | C25: 25 мин | D25: 578 | E25: 40 | F25: 25 | G25: 47 | H25: • Гречка (сухая): 60 г • Яйцо: 110 г (≈2 шт) • Помидоры: 100 г • Огурцы: 100 г • Масло растительное: 5 г • Творог 5%: 100 г | I25: 1. Гречку свари 15 минут. 2. Яйца пожарь глазуньей или вари вкрутую. 3. Подай с овощами и творогом на гарнир. | J25: Быстрый ужин после тренировки.

Sheet Покупки
A1: Список покупок на неделю на двоих
A2: Считается из листа «Меню»: твои граммы плюс граммы жены, запас 5%. Цену за кг можно поменять на листе «Продукты».
A4: Продукт | B4: Нужно, кг | C4: Штук (если считается) | D4: Цена, ₽/кг | E4: Сумма, ₽ | F4: Куплено
A5: Бананы (очищенные) | B5: =(SUMIFS('Меню'!$G$5:$G$149,'Меню'!$D$5:$D$149,A5)+SUMIFS('Меню'!$H$5:$H$149,'Меню'!$D$5:$D$149,A5))*1.05/1000 | C5: =IF('Продукты'!G29>0,ROUNDUP(B5*1000/'Продукты'!G29,0),"") | D5: ='Продукты'!F29 | E5: =B5*D5
A6: Белая рыба (минтай, хек) | B6: =(SUMIFS('Меню'!$G$5:$G$149,'Меню'!$D$5:$D$149,A6)+SUMIFS('Меню'!$H$5:$H$149,'Меню'!$D$5:$D$149,A6))*1.05/1000 | C6: =IF('Продукты'!G15>0,ROUNDUP(B6*1000/'Продукты'!G15,0),"") | D6: ='Продукты'!F15 | E6: =B6*D6
A7: Грецкие орехи | B7: =(SUMIFS('Меню'!$G$5:$G$149,'Меню'!$D$5:$D$149,A7)+SUMIFS('Меню'!$H$5:$H$149,'Меню'!$D$5:$D$149,A7))*1.05/1000 | C7: =IF('Продукты'!G33>0,ROUNDUP(B7*1000/'Продукты'!G33,0),"") | D7: ='Продукты'!F33 | E7: =B7*D7
A8: Гречка (сухая) | B8: =(SUMIFS('Меню'!$G$5:$G$149,'Меню'!$D$5:$D$149,A8)+SUMIFS('Меню'!$H$5:$H$149,'Меню'!$D$5:$D$149,A8))*1.05/1000 | C8: =IF('Продукты'!G5>0,ROUNDUP(B8*1000/'Продукты'!G5,0),"") | D8: ='Продукты'!F5 | E8: =B8*D8
A9: Йогурт натуральный | B9: =(SUMIFS('Меню'!$G$5:$G$149,'Меню'!$D$5:$D$149,A9)+SUMIFS('Меню'!$H$5:$H$149,'Меню'!$D$5:$D$149,A9))*1.05/1000 | C9: =IF('Продукты'!G19>0,ROUNDUP(B9*1000/'Продукты'!G19,0),"") | D9: ='Продукты'!F19 | E9: =B9*D9
A10: Капуста белокочанная | B10: =(SUMIFS('Меню'!$G$5:$G$149,'Меню'!$D$5:$D$149,A10)+SUMIFS('Меню'!$H$5:$H$149,'Меню'!$D$5:$D$149,A10))*1.05/1000 | C10: =IF('Продукты'!G24>0,ROUNDUP(B10*1000/'Продукты'!G24,0),"") | D10: ='Продукты'!F24 | E10: =B10*D10
A11: Картофель | B11: =(SUMIFS('Меню'!$G$5:$G$149,'Меню'!$D$5:$D$149,A11)+SUMIFS('Меню'!$H$5:$H$149,'Меню'!$D$5:$D$149,A11))*1.05/1000 | C11: =IF('Продукты'!G10>0,ROUNDUP(B11*1000/'Продукты'!G10,0),"") | D11: ='Продукты'!F10 | E11: =B11*D11
A12: Кефир 1% | B12: =(SUMIFS('Меню'!$G$5:$G$149,'Меню'!$D$5:$D$149,A12)+SUMIFS('Меню'!$H$5:$H$149,'Меню'!$D$5:$D$149,A12))*1.05/1000 | C12: =IF('Продукты'!G18>0,ROUNDUP(B12*1000/'Продукты'!G18,0),"") | D12: ='Продукты'!F18 | E12: =B12*D12
A13: Красная рыба (горбуша, форель) | B13: =(SUMIFS('Меню'!$G$5:$G$149,'Меню'!$D$5:$D$149,A13)+SUMIFS('Меню'!$H$5:$H$149,'Меню'!$D$5:$D$149,A13))*1.05/1000 | C13: =IF('Продукты'!G16>0,ROUNDUP(B13*1000/'Продукты'!G16,0),"") | D13: ='Продукты'!F16 | E13: =B13*D13
A14: Куриная грудка | B14: =(SUMIFS('Меню'!$G$5:$G$149,'Меню'!$D$5:$D$149,A14)+SUMIFS('Меню'!$H$5:$H$149,'Меню'!$D$5:$D$149,A14))*1.05/1000 | C14: =IF('Продукты'!G12>0,ROUNDUP(B14*1000/'Продукты'!G12,0),"") | D14: ='Продукты'!F12 | E14: =B14*D14
A15: Куриные бёдра/голень без кожи | B15: =(SUMIFS('Меню'!$G$5:$G$149,'Меню'!$D$5:$D$149,A15)+SUMIFS('Меню'!$H$5:$H$149,'Меню'!$D$5:$D$149,A15))*1.05/1000 | C15: =IF('Продукты'!G13>0,ROUNDUP(B15*1000/'Продукты'!G13,0),"") | D15: ='Продукты'!F13 | E15: =B15*D15
A16: Куриный фарш | B16: =(SUMIFS('Меню'!$G$5:$G$149,'Меню'!$D$5:$D$149,A16)+SUMIFS('Меню'!$H$5:$H$149,'Меню'!$D$5:$D$149,A16))*1.05/1000 | C16: =IF('Продукты'!G14>0,ROUNDUP(B16*1000/'Продукты'!G14,0),"") | D16: ='Продукты'!F14 | E16: =B16*D16
A17: Лук репчатый | B17: =(SUMIFS('Меню'!$G$5:$G$149,'Меню'!$D$5:$D$149,A17)+SUMIFS('Меню'!$H$5:$H$149,'Меню'!$D$5:$D$149,A17))*1.05/1000 | C17: =IF('Продукты'!G26>0,ROUNDUP(B17*1000/'Продукты'!G26,0),"") | D17: ='Продукты'!F26 | E17: =B17*D17
A18: Макароны (сухие) | B18: =(SUMIFS('Меню'!$G$5:$G$149,'Меню'!$D$5:$D$149,A18)+SUMIFS('Меню'!$H$5:$H$149,'Меню'!$D$5:$D$149,A18))*1.05/1000 | C18: =IF('Продукты'!G9>0,ROUNDUP(B18*1000/'Продукты'!G9,0),"") | D18: ='Продукты'!F9 | E18: =B18*D18
A19: Масло растительное | B19: =(SUMIFS('Меню'!$G$5:$G$149,'Меню'!$D$5:$D$149,A19)+SUMIFS('Меню'!$H$5:$H$149,'Меню'!$D$5:$D$149,A19))*1.05/1000 | C19: =IF('Продукты'!G32>0,ROUNDUP(B19*1000/'Продукты'!G32,0),"") | D19: ='Продукты'!F32 | E19: =B19*D19
A20: Молоко 2.5% | B20: =(SUMIFS('Меню'!$G$5:$G$149,'Меню'!$D$5:$D$149,A20)+SUMIFS('Меню'!$H$5:$H$149,'Меню'!$D$5:$D$149,A20))*1.05/1000 | C20: =IF('Продукты'!G20>0,ROUNDUP(B20*1000/'Продукты'!G20,0),"") | D20: ='Продукты'!F20 | E20: =B20*D20
A21: Морковь | B21: =(SUMIFS('Меню'!$G$5:$G$149,'Меню'!$D$5:$D$149,A21)+SUMIFS('Меню'!$H$5:$H$149,'Меню'!$D$5:$D$149,A21))*1.05/1000 | C21: =IF('Продукты'!G25>0,ROUNDUP(B21*1000/'Продукты'!G25,0),"") | D21: ='Продукты'!F25 | E21: =B21*D21
A22: Овсяные хлопья (сухие) | B22: =(SUMIFS('Меню'!$G$5:$G$149,'Меню'!$D$5:$D$149,A22)+SUMIFS('Меню'!$H$5:$H$149,'Меню'!$D$5:$D$149,A22))*1.05/1000 | C22: =IF('Продукты'!G4>0,ROUNDUP(B22*1000/'Продукты'!G4,0),"") | D22: ='Продукты'!F4 | E22: =B22*D22
A23: Огурцы | B23: =(SUMIFS('Меню'!$G$5:$G$149,'Меню'!$D$5:$D$149,A23)+SUMIFS('Меню'!$H$5:$H$149,'Меню'!$D$5:$D$149,A23))*1.05/1000 | C23: =IF('Продукты'!G28>0,ROUNDUP(B23*1000/'Продукты'!G28,0),"") | D23: ='Продукты'!F28 | E23: =B23*D23
A24: Перловка (сухая) | B24: =(SUMIFS('Меню'!$G$5:$G$149,'Меню'!$D$5:$D$149,A24)+SUMIFS('Меню'!$H$5:$H$149,'Меню'!$D$5:$D$149,A24))*1.05/1000 | C24: =IF('Продукты'!G8>0,ROUNDUP(B24*1000/'Продукты'!G8,0),"") | D24: ='Продукты'!F8 | E24: =B24*D24
A25: Помидоры | B25: =(SUMIFS('Меню'!$G$5:$G$149,'Меню'!$D$5:$D$149,A25)+SUMIFS('Меню'!$H$5:$H$149,'Меню'!$D$5:$D$149,A25))*1.05/1000 | C25: =IF('Продукты'!G27>0,ROUNDUP(B25*1000/'Продукты'!G27,0),"") | D25: ='Продукты'!F27 | E25: =B25*D25
A26: Пшено (сухое) | B26: =(SUMIFS('Меню'!$G$5:$G$149,'Меню'!$D$5:$D$149,A26)+SUMIFS('Меню'!$H$5:$H$149,'Меню'!$D$5:$D$149,A26))*1.05/1000 | C26: =IF('Продукты'!G6>0,ROUNDUP(B26*1000/'Продукты'!G6,0),"") | D26: ='Продукты'!F6 | E26: =B26*D26
A27: Рис (сухой) | B27: =(SUMIFS('Меню'!$G$5:$G$149,'Меню'!$D$5:$D$149,A27)+SUMIFS('Меню'!$H$5:$H$149,'Меню'!$D$5:$D$149,A27))*1.05/1000 | C27: =IF('Продукты'!G7>0,ROUNDUP(B27*1000/'Продукты'!G7,0),"") | D27: ='Продукты'!F7 | E27: =B27*D27
A28: Салат айсберг | B28: =(SUMIFS('Меню'!$G$5:$G$149,'Меню'!$D$5:$D$149,A28)+SUMIFS('Меню'!$H$5:$H$149,'Меню'!$D$5:$D$149,A28))*1.05/1000 | C28: =IF('Продукты'!G23>0,ROUNDUP(B28*1000/'Продукты'!G23,0),"") | D28: ='Продукты'!F23 | E28: =B28*D28
A29: Творог 5% | B29: =(SUMIFS('Меню'!$G$5:$G$149,'Меню'!$D$5:$D$149,A29)+SUMIFS('Меню'!$H$5:$H$149,'Меню'!$D$5:$D$149,A29))*1.05/1000 | C29: =IF('Продукты'!G17>0,ROUNDUP(B29*1000/'Продукты'!G17,0),"") | D29: ='Продукты'!F17 | E29: =B29*D29
A30: Томатная паста | B30: =(SUMIFS('Меню'!$G$5:$G$149,'Меню'!$D$5:$D$149,A30)+SUMIFS('Меню'!$H$5:$H$149,'Меню'!$D$5:$D$149,A30))*1.05/1000 | C30: =IF('Продукты'!G34>0,ROUNDUP(B30*1000/'Продукты'!G34,0),"") | D30: ='Продукты'!F34 | E30: =B30*D30
A31: Хлеб цельнозерновой/ржаной | B31: =(SUMIFS('Меню'!$G$5:$G$149,'Меню'!$D$5:$D$149,A31)+SUMIFS('Меню'!$H$5:$H$149,'Меню'!$D$5:$D$149,A31))*1.05/1000 | C31: =IF('Продукты'!G31>0,ROUNDUP(B31*1000/'Продукты'!G31,0),"") | D31: ='Продукты'!F31 | E31: =B31*D31
A32: Чечевица (сухая) | B32: =(SUMIFS('Меню'!$G$5:$G$149,'Меню'!$D$5:$D$149,A32)+SUMIFS('Меню'!$H$5:$H$149,'Меню'!$D$5:$D$149,A32))*1.05/1000 | C32: =IF('Продукты'!G22>0,ROUNDUP(B32*1000/'Продукты'!G22,0),"") | D32: ='Продукты'!F22 | E32: =B32*D32
A33: Яблоки | B33: =(SUMIFS('Меню'!$G$5:$G$149,'Меню'!$D$5:$D$149,A33)+SUMIFS('Меню'!$H$5:$H$149,'Меню'!$D$5:$D$149,A33))*1.05/1000 | C33: =IF('Продукты'!G30>0,ROUNDUP(B33*1000/'Продукты'!G30,0),"") | D33: ='Продукты'!F30 | E33: =B33*D33
A34: Яйцо | B34: =(SUMIFS('Меню'!$G$5:$G$149,'Меню'!$D$5:$D$149,A34)+SUMIFS('Меню'!$H$5:$H$149,'Меню'!$D$5:$D$149,A34))*1.05/1000 | C34: =IF('Продукты'!G11>0,ROUNDUP(B34*1000/'Продукты'!G11,0),"") | D34: ='Продукты'!F11 | E34: =B34*D34
A36: Итого в неделю, ₽ | E36: =SUM(E5:E34)
A37: Итого в месяц (×4,3), ₽ | E37: =E36*4.3
A38: Бюджет на еду в месяц, ₽ | E38: ='Расчёт'!B13
A39: Остаток бюджета, ₽ | E39: =E38-E37
A41: Как сэкономить: бёдра вместо грудки, минтай вместо красной рыбы в 6 из 7 дней, сезонные овощи, айсберг можно заменить пекинской капустой.

Sheet Экипировка
A1: Что купить
A2: Обязательное отмечено «да». Впиши фактическую цену в жёлтую ячейку.
A4: Группа | B4: Предмет | C4: От, ₽ | D4: До, ₽ | E4: Нужно? | F4: Как выбирать | G4: Купил за, ₽
A5: Обувь | B5: Беговые кроссовки с хорошей амортизацией | C5: 6000 | D5: 9000 | E5: да | F5: • Для веса 90 кг и крепитации в коленях бери модель с толстой мягкой подошвой (категория «max cushion» или нейтральная амортизация). • Примеряй вечером, когда нога чуть отекла, и в тех носках, в которых будешь бегать. • Запас 1–1,5 см перед большим пальцем, пятка не соскальзывает, перед свободный. • Прогуляйся и пробеги несколько шагов в магазине. Ничего не должно давить. • Для парка с грунтом подойдёт обычная дорожная подошва, шипы не нужны. • Меняй через 600–800 км, если подошва стёрлась или стало жёстче.
A6: Обувь | B6: Носки беговые 2–3 пары | C6: 600 | D6: 1500 | E6: да | F6: • Синтетика или шерсть мериноса, хлопок мокнет и натирает. • Без грубых швов, с плотной зоной на пятке.
A7: Одежда | B7: Термобельё (базовый слой), осень/зима | C7: 1500 | D7: 3000 | E7: да | F7: • Первый слой отводит влагу: синтетика или мериносовая шерсть. • Хлопковая футболка мокнет и остывает, поэтому под низ не надевай.
A8: Одежда | B8: Беговые футболки 2 шт. | C8: 1000 | D8: 2000 | E8: да | F8: • Лёгкая синтетика, швы плоские, чтобы не натирало.
A9: Одежда | B9: Шорты и тайтсы/лосины | C9: 1500 | D9: 2500 | E9: да | F9: • Тайтсы для прохладной погоды, шорты для зала и тёплых дней. • Должны сидеть плотно, но не стягивать колени.
A10: Одежда | B10: Ветровка (лёгкая куртка) | C10: 2000 | D10: 4000 | E10: да | F10: • Ветрозащита важнее утепления: греет движение. • Светоотражающие элементы, если бегаешь в сумерках. • Берётся на размер больше, чтобы под неё влез слой.
A11: Одежда | B11: Шапка/бафф и тонкие перчатки | C11: 800 | D11: 1500 | E11: по желанию | F11: • Нужны при температуре ниже +8 °C.
A12: Для подтягиваний | B12: Резиновые петли (набор из 2–3) | C12: 1000 | D12: 2000 | E12: да | F12: • Для помощи в подтягиваниях и разгрузки в начале. • Бери разное сопротивление (лёгкая и средняя).
A13: Для подтягиваний | B13: Магнезия или перчатки без пальцев | C13: 300 | D13: 800 | E13: по желанию | F13: • Сухие руки лучше держат, мозоли реже. Магнезия в мешочке — самый дешёвый вариант.
A14: Для подтягиваний | B14: Рюкзак для груза + бутылки с водой | C14: 0 | D14: 500 | E14: да | F14: • Для румынской тяги и приседов с рюкзаком. Нагрузку наращивай бутылками по 1,5 л (1,5 кг каждая).
A15: Прочее | B15: Бутылка для воды 0,75 л | C15: 200 | D15: 600 | E15: да | F15: • На тренировку бери воду: 300–500 мл в течение занятия.
A16: Прочее | B16: Массажный ролик (пенный) | C16: 800 | D16: 1500 | E16: по желанию | F16: • Прокатывай бёдра и икры после тренировки по 1–2 минуты на зону. Колени и суставы не катай.
... A18: Прочее | B18: Коврик (туристический) | C18: 500 | D18: 1200 | E18: по желанию | F18: • Для мостиков, скручиваний и планки на траве или земле.
A20: Обязательное: от | B20: =SUMIFS(C5:C18,E5:E18,"да")
A21: Обязательное: до | B21: =SUMIFS(D5:D18,E5:E18,"да")
A22: Всё вместе: до | B22: =SUM(D5:D18)
A23: Потрачено фактически | B23: =SUM(G5:G18)
A24: Бюджет | B24: ='Расчёт'!B12
A25: Остаток | B25: =B24-B23
A27: Как проверить кроссовки в магазине
A28: • | B28: Большой палец не упирается в носок, запас около 1 см.
A29: • | B29: Пятка не выскальзывает при шаге и беге.
A30: • | B30: Нет давления на подъёме, шнуровка не режет.
A31: • | B31: Подошва сгибается в районе плюсны, а не посередине.
A32: • | B32: Через 10 минут ходьбы нога не горит.

Sheet Техника
A1: Техника упражнений
A2: Снимай себя сбоку и сверяй. Боль и отёк в суставах означают стоп.
A4: Упражнение | B4: Группа | C4: Инвентарь | D4: Дозировка | E4: Как делать | F4: Частые ошибки | G4: Подсказка | H4: Легче | I4: Сложнее | J4: Колени
A5: Подтягивания | B5: Подтягивания | C5: Турник | D5: Силовые: подходы не до отказа, пауза 2 мин | E5: 1. Хват прямой, чуть шире плеч. Начинай из виса на прямых руках, плечи опущены от ушей. 2. Сведи лопатки и тяни локти вниз и к рёбрам, подбородок выше перекладины. 3. Опускайся 2–3 секунды до полного выпрямления рук. 4. Корпус почти вертикально, ноги скрещены или слегка согнуты, без раскачки. | F5: • Не добирают амплитуду внизу (руки не выпрямляются), на зачёте такое не засчитают. • Рывок ногами и «киппинг», обычно в зачёт он не идёт. • Плечи подняты к ушам, вся работа идёт на трапеции и шею. • Подход до полного отказа каждый день, мышцы и локти не успевают восстановиться. | G5: Тяни локти в карманы. Грудь к перекладине. | H5: Негативы, резиновая петля, австралийские подтягивания. | I5: Пауза 2 секунды вверху, затем с грузом на поясе. | J5: Колени не нагружаются, это главное упражнение в твоём плане.
A6: Негативные подтягивания | B6: Подтягивания | C6: Турник + скамейка | D6: 3×3–5, спуск 4–5 секунд | E6: 1. Встань на скамью или подпрыгни, чтобы подбородок оказался над перекладиной. 2. Медленно опускайся 4–5 секунд до полного виса. 3. Спустись, отдохни 2 минуты, повтори. | F6: • Падают вниз за 1 секунду, нужен контролируемый спуск. • Не доходят до полного выпрямления рук. | G6: Считай про себя «двадцать один, двадцать два…» на спуске. | H6: Спуск за 3 секунды. | I6: Спуск 6–8 секунд, пауза в середине. | J6: Нагрузка на колени отсутствует.
A7: Австралийские подтягивания | B7: Подтягивания | C7: Низкая перекладина или брусья | D7: 3×8–12 | E7: 1. Лягь под низкую перекладину (на уровне пояса), хват прямой, тело прямое от пяток до головы. 2. Подтяни грудь к перекладине, локти идут вниз и назад. 3. Опустись контролируемо, не прогибай поясницу. | F7: • Таз провисает, корпус не держится прямой линией. • Тянут только руками, лопатки не сводятся. | G7: Тело как доска. Грудь к перекладине. | H7: Согни колени, ноги ближе к рукам. | I7: Ноги выше уровня таза, пауза 2 секунды. | J7: Колени не нагружаются.
A8: Отжимания | B8: Сила верха | C8: Пол или скамейка | D8: 3 подхода по (максимум − 2) | E8: 1. Упор лёжа: ладони под плечами, тело прямое, ягодицы не торчат. 2. Опускайся до касания грудью или до угла локтей 90°. 3. Локти под 45° к корпусу, не разводи в стороны. 4. Выдох при отжимании вверх. | F8: • Таз провисает или торчит вверх. • Локти разведены на 90° и давят на плечи. • Неполная амплитуда. | G8: Плечи от ушей, пресс напряжён. | H8: Руки на скамье или столе (чем выше, тем легче). | I8: Ноги на скамье или пауза внизу 2 секунды. | J8: Если больно стоять на коленях, оставайся на носках.
A9: Присед до скамьи | B9: Ноги | C9: Скамейка | D9: 3×10–12, затем с рюкзаком | E9: 1. Встань спиной к скамье, стопы на ширине плеч, носки чуть в стороны. 2. Тазом назад, как будто садишься на стул, колени идут над стопами. 3. Коснись скамьи и встань без раскачки, на выдохе. 4. Амплитуду ограничивает скамья: глубже не нужно. | F9: • Колени заваливаются внутрь, держи их над мизинцем. • Пятки отрываются от земли. • Падают на скамью, нужен контроль. | G9: Колени смотрят туда же, куда носки. | H9: Более высокая скамья. | I9: Рюкзак с грузом на груди (гоблет). | J9: Хруст без боли допустим. Глубокую «лягушку» и полный присед отложи, пока колени не окрепнут. Боль, отёк или блокировка означают стоп и визит к врачу.
A10: Подъём на скамью | B10: Ноги | C10: Скамейка | D10: 3×8 на ногу | E10: 1. Поставь всю стопу на скамью (высота не выше колена). 2. Поднимись усилием ноги на скамье, не отталкивайся задней ногой. 3. Медленно опустись обратно. | F10: • Толкаются нижней ногой. • Колено уходит внутрь. | G10: Вся стопа на опоре, корпус прямой. | H10: Низкая опора (подножка). | I10: С рюкзаком в руках. | J10: Нагружает колено мягче, чем выпады. Опускайся медленно.
A11: Румынская тяга с рюкзаком | B11: Ноги | C11: Рюкзак с грузом (5–12 кг) | D11: 3×10–12 | E11: 1. Рюкзак держи перед бёдрами, колени слегка согнуты. 2. Таз отводи назад, спина прямая, рюкзак скользит вдоль ног. 3. Остановись, когда чувствуешь растяжение задней поверхности бедра. 4. Встань, сжимая ягодицы. | F11: • Круглая спина, нужно держать нейтральную поясницу. • Приседают вместо наклона. | G11: Закрой дверь ягодицами позади себя. | H11: Без рюкзака. | I11: Больший вес или на одной ноге. | J11: Колени почти не работают, отличный вариант для твоей ситуации.
A12: Ягодичный мостик | B12: Ноги | C12: Пол | D12: 3×12–15 | E12: 1. Лягь на спину, стопы у ягодиц, колени согнуты. 2. Поднимай таз, сжимая ягодицы, до прямой линии плечи-колени. 3. В верхней точке пауза 1–2 секунды. | F12: • Прогиб в пояснице вместо работы ягодиц. • Стопы слишком далеко. | G12: Толкай пятками пол. | H12: Меньше амплитуды. | I12: Одна нога, груз на таз. | J12: Безопасное упражнение для коленей.
A13: Подъём на носки | B13: Ноги | C13: Ступенька | D13: 3×15–20 | E13: 1. Встань носками на край ступеньки. 2. Поднимись максимально высоко, задержись на 1 секунду. 3. Опусти пятки ниже ступеньки до растяжения икр. | F13: • Работают с половиной амплитуды. • Заваливают стопы внутрь. | G13: Вверх как балерина. | H13: На полу. | I13: На одной ноге. | J13: Укрепляет икры и ахиллы, нужны для бега.
A14: Планка | B14: Кор | C14: Пол | D14: 3×30–60 секунд | E14: 1. Локти под плечами, предплечья параллельны. 2. Тело ровной линией от пяток до затылка. 3. Ягодицы и пресс напряжены, дыши ровно. | F14: • Таз провисает, поясница болит. • Таз торчит вверх, пресс не работает. • Задерживают дыхание. | G14: Подтяни пупок к позвоночнику, ягодицы сжаты. | H14: С коленей. | I14: Подъём ноги или рук. | J14: Если колени болят, подложи коврик или сверни куртку.
A15: Подъём коленей/ног в висе | B15: Кор | C15: Турник | D15: 3×6–12 | E15: 1. Вис на перекладине, лопатки слегка опущены. 2. Подтяни колени к груди, подкручивая таз. 3. Опусти без раскачки. 4. Когда будет легко, поднимай прямые ноги до горизонтали. | F15: • Раскачиваются и работают инерцией. • Поднимают только бёдра, таз остаётся неподвижным. | G15: Подкручивай таз к рёбрам. | H15: Колени чуть ниже. | I15: Прямые ноги, затем носки к перекладине. | J15: Нагрузки на колени нет.
... A20: Разминка и заминка | B20: Разминка | C20: — | D20: 8–10 минут до, 5–8 после | E20: 1. Ходьба и лёгкий бег 4–5 минут. 2. Круги: плечи, таз, колени, голеностоп по 10. 3. Выпады с поворотом, махи ногами по 8–10. 4. Ускорения 3×40 метров без напряжения. 5. После тренировки: ходьба 3–5 минут, растяжка икр, бёдер, ягодиц и груди по 30 секунд. | F20: • Пропуск разминки перед интервалами. • Растяжка с болью. | G20: После разминки должно быть тепло и слегка влажно. | H20: — | I20: — | J20: Динамическая разминка снижает риск травм колена.

Sheet Разбор плана
A1: Что было не так и что изменено
A3: Проблема в исходной таблице | B3: Что сделано
A4: Контроль на 19–20 день | B4: За три недели с 3 до 15 подтягиваний не дойти, это нереалистично и ведёт к травме. Контроли оставил каждые 4 недели, цели разбиты на реалистичные ступени.
A5: Мало объёма подтягиваний | B5: 5 подходов по 2 раза это около 10 повторений в тренировке, а в программе нет силовой работы спины. Добавил негативы, австралийские подтягивания, лестницы и ежедневные мини-подходы.
A6: 2 тренировки в неделю после 20 дня | B6: Для трёх нормативов, снижения веса и мышц этого мало. На ближайшие 2 недели оставил плотный старт, а потом две сессии А и Б, где в каждой есть бег или челнок, подтягивания и кор. Плюс ежедневная пятиминутка.
A7: Нет темпов и пауз | B7: «6×200 м» не говорит, с какой скоростью бежать и сколько отдыхать. Теперь у каждого отрезка есть целевое время, пауза и подстройка под твой последний тест.
A8: Ноги без упражнений | B8: Запись «ноги» ничего не объясняла. Колени у тебя хрустят, поэтому глубокие приседания и прыжки убрал, поставил присед до скамьи, подъёмы на скамью, румынскую тягу и мостик.
A9: Нет разминки, заминки и отдыха | B9: В таблице нет разминки перед интервалами и разгрузочных недель. Теперь они есть в каждой тренировке, а каждая четвёртая неделя лёгкая.
A10: Питание без граммов и калорий | B10: Меню было набором блюд без порций. Теперь есть расчёт калорий и белка под твои данные, граммы на тебя и на жену, рецепты и список покупок.
A11: Много углеводов, мало овощей и белка в завтраках | B11: Овсянка, картофель, макароны, рис шли почти каждый приём. Добавил творог, кефир, яйца и овощной салат на каждый обед и ужин, чтобы белка хватало на мышцы.
A12: Нет фокуса на похудение и кубики | B12: Живот убирается питанием и шагами, а не пресс-упражнениями. Задан дефицит около 20%, контроль веса и талии, и честный прогноз по срокам.
A13: Нет учёта | B13: В таблице контроля не было графиков, талии и шагов. В дневнике теперь графики с плановой траекторией и рамки целей.

Sheet Продукты
A1: Продукты: калории и цены
A2: На 100 г сырого продукта. Цены в рублях за кг, ориентир, поправь на свои.
A3: Продукт | B3: Ккал | C3: Белок | D3: Жиры | E3: Углеводы | F3: Цена, ₽/кг | G3: 1 шт, г
A4: Овсяные хлопья (сухие) | B4: 366 | C4: 12 | D4: 6.5 | E4: 60 | F4: 90
A5: Гречка (сухая) | B5: 340 | C5: 12.6 | D5: 3.3 | E5: 62 | F5: 120
A6: Пшено (сухое) | B6: 342 | C6: 11.5 | D6: 3.3 | E6: 66 | F6: 70
A7: Рис (сухой) | B7: 345 | C7: 7 | D7: 0.7 | E7: 77 | F7: 100
A8: Перловка (сухая) | B8: 320 | C8: 9.3 | D8: 1.1 | E8: 73 | F8: 70
A9: Макароны (сухие) | B9: 350 | C9: 12 | D9: 1.5 | E9: 71 | F9: 90
A10: Картофель | B10: 77 | C10: 2 | D10: 0.4 | E10: 16 | F10: 45
A11: Яйцо | B11: 157 | C11: 12.7 | D11: 11.5 | E11: 0.7 | F11: 220 | G11: 55
A12: Куриная грудка | B12: 115 | C12: 23 | D12: 1.9 | E12: 0 | F12: 380
A13: Куриные бёдра/голень без кожи | B13: 135 | C13: 19 | D13: 6.5 | E13: 0 | F13: 260
A14: Куриный фарш | B14: 143 | C14: 17.5 | D14: 8 | E14: 0.4 | F14: 300
A15: Белая рыба (минтай, хек) | B15: 80 | C15: 17 | D15: 1 | E15: 0 | F15: 330
A16: Красная рыба (горбуша, форель) | B16: 150 | C16: 20 | D16: 8 | E16: 0 | F16: 700
A17: Творог 5% | B17: 121 | C17: 17 | D17: 5 | E17: 3 | F17: 420
A18: Кефир 1% | B18: 40 | C18: 3 | D18: 1 | E18: 4 | F18: 90
A19: Йогурт натуральный | B19: 60 | C19: 4 | D19: 3.2 | E19: 4.5 | F19: 150
A20: Молоко 2.5% | B20: 52 | C20: 3 | D20: 2.5 | E20: 4.7 | F20: 80
A21: Сыр твёрдый | B21: 350 | C21: 25 | D21: 27 | E21: 0 | F21: 700
A22: Чечевица (сухая) | B22: 295 | C22: 24 | D22: 1.5 | E22: 46 | F22: 160
A23: Салат айсберг | B23: 14 | C23: 0.9 | D23: 0.1 | E23: 3 | F23: 330
... A28: Огурцы | B28: 15 | C28: 0.8 | D28: 0.1 | E28: 2.5 | F28: 150
A29: Бананы (очищенные) | B29: 90 | C29: 1.5 | D29: 0.2 | E29: 21 | F29: 120 | G29: 110
A30: Яблоки | B30: 47 | C30: 0.4 | D30: 0.4 | E30: 10 | F30: 120 | G30: 150
A31: Хлеб цельнозерновой/ржаной | B31: 215 | C31: 7 | D31: 1.5 | E31: 42 | F31: 90
A32: Масло растительное | B32: 900 | C32: 0 | D32: 100 | E32: 0 | F32: 170
A33: Грецкие орехи | B33: 650 | C33: 15 | D33: 65 | E33: 7 | F33: 1200
A34: Томатная паста | B34: 80 | C34: 4 | D34: 0.5 | E34: 15 | F34: 400
